Workbook
Name Capital_Tot: '11_Performance'!$B$6
Name CatchUpPct: '01_Assumptions'!$B$13
Name DataOggi: '01_Assumptions'!$B$6
Name GPCarry: '01_Assumptions'!$B$11
Name Hurdle: '01_Assumptions'!$B$10
Name Listed_Tot_Cost: '09_Posizioni'!$K$60
Name LPSplit: '01_Assumptions'!$B$12
Name MV_Listed_Tot: '09_Posizioni'!$O$60
Name NAV_Curr: '11_Performance'!$B$16
Name NAVperUnit_Curr: '11_Performance'!$B$18
Name RiskFree: '01_Assumptions'!$B$7
Name Subscription_Pricing_Policy: '01_Assumptions'!$B$8
Name Units_Curr: '11_Performance'!$B$17

Sheet 00_Dashboard
A1: Ariete Capital — Investment Dashboard
A2: Riepilogo aggiornato in tempo reale dai dati dei sheet di input. Tutti i valori sono in EUR.
A4: Data Snapshot | B4: =DataOggi -> 46160
A6: Capitale e NAV | D6: Indicatori di Rendimento
A7: Capitale Raccolto EUR | B7: =Capital_Tot -> 2000000 | D7: IRR (XIRR) | E7: ='11_Performance'!B25 -> -0.020910069
A8: NAV Corrente EUR | B8: =NAV_Curr -> 1971514.5 | D8: CAGR | E8: ='11_Performance'!B26 -> 0
A9: Profitto Totale EUR | B9: =NAV_Curr-Capital_Tot -> -28485.504 | D9: Volatilità Annua | E9: ='11_Performance'!B27 -> 0.06891298
A10: MOIC | B10: =IFERROR(NAV_Curr/Capital_Tot,0) -> 0.98575725 | D10: Sharpe Ratio | E10: ='11_Performance'!B28 -> -0.44360567
A11: Quote Outstanding | B11: =Units_Curr -> 2000000 | D11: Sortino Ratio | E11: ='11_Performance'!B29 -> 0
A12: NAV/Unit | B12: =NAVperUnit_Curr -> 0.98575725 | D12: Max Drawdown | E12: ='11_Performance'!B30 -> -0.050029439
A15: Composizione NAV (EUR) | D15: Flussi Cumulativi (EUR)
A16: Cassa Non Remunerata | B16: ='11_Performance'!B12 -> 611761.75 | C16: =IFERROR(B16/NAV_Curr,0) -> 0.31030041 | D16: Net Trade (Listed) | E16: ='11_Performance'!B7 -> 1082225.7
A17: Strumenti Quotati (MV) | B17: ='11_Performance'!B13 -> 1069752.7 | C17: =IFERROR(B17/NAV_Curr,0) -> 0.54260455 | D17: Dividendi/Interessi Lordi | E17: ='11_Performance'!B8 -> 8226.2
A18: Partecipazioni Non Quotate | B18: ='11_Performance'!B14 -> 155000 | C18: =IFERROR(B18/NAV_Curr,0) -> 0.078619762 | D18: Partecipazioni Net | E18: ='11_Performance'!B9 -> 165000
A19: Prestiti Outstanding | B19: ='11_Performance'!B15 -> 135000 | C19: =IFERROR(B19/NAV_Curr,0) -> 0.068475276 | D19: Prestiti Net | E19: ='11_Performance'!B10 -> 135000
A20: TOTALE NAV | B20: =SUM(B16:B19) -> 1971514.5 | C20: =SUM(C16:C19) -> 1 | D20: P/L Operativa | E20: ='11_Performance'!B11 -> -14238.73
A24: Sommario Waterfall (Ipotetico Oggi)
A25: Hurdle Amount Totale EUR | B25: ='13_Waterfall'!B7 -> 67735.291
A26: Distribuito a LP+GP (capital+pref+split) | B26: ='13_Waterfall'!B22 -> 1971514.5
A27: Carry GP (catch-up + 20%) | B27: ='13_Waterfall'!C22 -> 0

Sheet 01_Assumptions
A1: Ariete Capital — Investment Tracker | Parametri Generali
A2: Tutte le celle gialle in BLU sono input utente. Le celle in NERO sono formule. Le celle in VERDE sono link ad altri sheet.
A4: Parametri Generali
A5: Valuta Base | B5: EUR
A6: Data Odierna (per snapshot) | B6: =TODAY() -> 46160
A7: Tasso Risk-Free Annuo | B7: 0.03 | C7: Modificabile — usato per Sharpe ratio
A8: Subscription Pricing Policy | B8: NAV/Unit del mese precedente la sottoscrizione | C8: Politica di pricing per nuove sottoscrizioni LP
A9: Parametri Waterfall (European-style)
A10: Hurdle Rate (annuo) | B10: 0.05 | C10: Preferred return LP
A11: GP Carry % (post catch-up) | B11: 0.2
A12: LP % (post catch-up) | B12: =1-B11 -> 0.8
A13: Catch-up GP Target % | B13: 0.2 | C13: % del profitto totale che spetta al GP dopo catch-up
A15: Indice del Workbook
A16: 00_Dashboard | B16: Riepilogo KPI principali
A17: 01_Assumptions | B17: Parametri generali, risk-free, waterfall
A18: 02_FX_Rates | B18: Tabella riferimento tassi di cambio
A19: 03_Investitori | B19: Sottoscrizioni di capitale (LP)
A20: 04_Trades | B20: Acquisti/vendite strumenti quotati
A21: 05_Dividendi_Interessi | B21: Dividendi, cedole, interessi (importi LORDI)
A22: 06_Partecipazioni | B22: Acquisti/vendite partecipazioni non quotate
A23: 07_Prestiti | B23: Prestiti verso partecipate (principal)
A24: 08_PL_Operativa | B24: P/L da attività operativa (input manuale)
A25: 09_Posizioni | B25: Posizioni aperte computed
A26: 10_NAV_Mensile | B26: NAV mensile con override valutazioni
A27: 11_Performance | B27: IRR totale, MOIC, Sharpe, drawdown
... A29: 13_Waterfall | B29: Distribuzione waterfall ipotetica oggi

Sheet 02_FX_Rates
A1: Tassi di Cambio — Riferimento
A2: Tabella di riferimento. Ogni transazione contiene la propria colonna FX→EUR per il tasso storico al trade date. Aggiorna questa tabella per facilitare l'inserimento futuro.
A4: Valuta | B4: EUR per 1 unità FX | C4: Ultima Data Aggiornamento | D4: Note
A5: EUR | B5: 1 | D5: Valuta base — sempre 1
A6: USD | B6: 0.92 | D6: Esempio — aggiorna periodicamente
A7: GBP | B7: 1.17
A8: CHF | B8: 1.06
A9: JPY | B9: 0.0061
A10: CNY | B10: 0.13

Sheet 03_Investitori
A1: Sottoscrizioni Capitale (LP)
A2: Ogni riga = una sottoscrizione di capitale da un socio. Per le quote (units), il default NAV/Unit a sottoscrizione è 1.0; per sottoscrizioni successive a movimenti di portafoglio, l'utente può sovrascrivere usando NAV/Unit corrente.
A4: ID | B4: Nome Investitore | C4: Data Sottoscrizione | D4: Tipo | E4: Valuta | F4: Importo Locale | G4: FX→EUR | H4: Importo EUR | I4: NAV/Unit @ Sub | J4: Quote (Units) | K4: % Capitale
A5: =IF(B5="","",ROW()-4) -> 1 | B5: Osy Harrison | C5: 45736 | D5: LP | E5: EUR | F5: 500000 | G5: 1 | H5: =IF(F5="","",F5*G5) -> 500000 | I5: 1 | J5: =IF(OR(H5="",I5="",I5=0),"",H5/I5) -> 500000 | K5: =IF(H5="","",H5/SUM($H$5:$H$104)) -> 0.25
A6: =IF(B6="","",ROW()-4) -> 2 | B6: Bradley Jackson | C6: 45904 | D6: LP | E6: EUR | F6: 500000 | G6: 1 | H6: =IF(F6="","",F6*G6) -> 500000 | I6: 1 | J6: =IF(OR(H6="",I6="",I6=0),"",H6/I6) -> 500000 | K6: =IF(H6="","",H6/SUM($H$5:$H$104)) -> 0.25
A7: =IF(B7="","",ROW()-4) -> 3 | B7: Grant Kauffman | C7: 45910 | D7: LP | E7: EUR | F7: 500000 | G7: 1 | H7: =IF(F7="","",F7*G7) -> 500000 | I7: 1 | J7: =IF(OR(H7="",I7="",I7=0),"",H7/I7) -> 500000 | K7: =IF(H7="","",H7/SUM($H$5:$H$104)) -> 0.25
A8: =IF(B8="","",ROW()-4) -> 4 | B8: Esra Sertoglu | C8: 46097 | D8: LP | E8: EUR | F8: 500000 | G8: 1 | H8: =IF(F8="","",F8*G8) -> 500000 | I8: 1 | J8: =IF(OR(H8="",I8="",I8=0),"",H8/I8) -> 500000 | K8: =IF(H8="","",H8/SUM($H$5:$H$104)) -> 0.25
A9: =IF(B9="","",ROW()-4) | H9: =IF(F9="","",F9*G9) | J9: =IF(OR(H9="",I9="",I9=0),"",H9/I9) | K9: =IF(H9="","",H9/SUM($H$5:$H$104))
A10: =IF(B10="","",ROW()-4) | H10: =IF(F10="","",F10*G10) | J10: =IF(OR(H10="",I10="",I10=0),"",H10/I10) | K10: =IF(H10="","",H10/SUM($H$5:$H$104))
A11: =IF(B11="","",ROW()-4) | H11: =IF(F11="","",F11*G11) | J11: =IF(OR(H11="",I11="",I11=0),"",H11/I11) | K11: =IF(H11="","",H11/SUM($H$5:$H$104))
A12: =IF(B12="","",ROW()-4) | H12: =IF(F12="","",F12*G12) | J12: =IF(OR(H12="",I12="",I12=0),"",H12/I12) | K12: =IF(H12="","",H12/SUM($H$5:$H$104))
A13: =IF(B13="","",ROW()-4) | H13: =IF(F13="","",F13*G13) | J13: =IF(OR(H13="",I13="",I13=0),"",H13/I13) | K13: =IF(H13="","",H13/SUM($H$5:$H$104))
A14: =IF(B14="","",ROW()-4) | H14: =IF(F14="","",F14*G14) | J14: =IF(OR(H14="",I14="",I14=0),"",H14/I14) | K14: =IF(H14="","",H14/SUM($H$5:$H$104))
A15: =IF(B15="","",ROW()-4) | H15: =IF(F15="","",F15*G15) | J15: =IF(OR(H15="",I15="",I15=0),"",H15/I15) | K15: =IF(H15="","",H15/SUM($H$5:$H$104))
A16: =IF(B16="","",ROW()-4) | H16: =IF(F16="","",F16*G16) | J16: =IF(OR(H16="",I16="",I16=0),"",H16/I16) | K16: =IF(H16="","",H16/SUM($H$5:$H$104))
A17: =IF(B17="","",ROW()-4) | H17: =IF(F17="","",F17*G17) | J17: =IF(OR(H17="",I17="",I17=0),"",H17/I17) | K17: =IF(H17="","",H17/SUM($H$5:$H$104))
A18: =IF(B18="","",ROW()-4) | H18: =IF(F18="","",F18*G18) | J18: =IF(OR(H18="",I18="",I18=0),"",H18/I18) | K18: =IF(H18="","",H18/SUM($H$5:$H$104))
A19: =IF(B19="","",ROW()-4) | H19: =IF(F19="","",F19*G19) | J19: =IF(OR(H19="",I19="",I19=0),"",H19/I19) | K19: =IF(H19="","",H19/SUM($H$5:$H$104))
A20: =IF(B20="","",ROW()-4) | H20: =IF(F20="","",F20*G20) | J20: =IF(OR(H20="",I20="",I20=0),"",H20/I20) | K20: =IF(H20="","",H20/SUM($H$5:$H$104))
... A104: =IF(B104="","",ROW()-4) | H104: =IF(F104="","",F104*G104) | J104: =IF(OR(H104="",I104="",I104=0),"",H104/I104) | K104: =IF(H104="","",H104/SUM($H$5:$H$104))
A106: TOTALE | F106: =SUM(F5:F104) -> 2000000 | H106: =SUM(H5:H104) -> 2000000 | J106: =SUM(J5:J104) -> 2000000

Sheet 04_Trades
A1: Acquisti / Vendite Strumenti Quotati
A2: Tipo = BUY o SELL. Importo Locale = Quantità × Prezzo. Le commissioni sono incluse nell'importo (modello al lordo delle imposte). Per ogni trade indicare la valuta e l'FX→EUR al trade date.
A4: ID | B4: Data | C4: Tipo | D4: Nome Strumento | E4: ISIN | F4: Valuta | G4: Quantità | H4: Prezzo Loc. | I4: Importo Loc. | J4: FX→EUR | K4: Importo EUR | L4: Note
A5: =IF(B5="","",ROW()-4) -> 1 | B5: 45658 | C5: BUY | D5: CELSIUS HOLDINGS | E5: US15118V2079 | F5: EUR | G5: 369 | H5: 25.4223 | I5: =IF(OR(G5="",H5=""),"",G5*H5) -> 9380.8287 | J5: 1 | K5: =IF(OR(I5="",J5=""),"",I5*J5) -> 9380.8287 | L5: Posizione di apertura al 01/01/2025 (pre-investitori). Registrato come BUY al valore di mercato 01/01/2025 da Situazione Patrimoniale Directa conto B6166 — questo è il costo di carico ai fini del modello. Liquidità di apertura €371,80 trascurata.
A6: =IF(B6="","",ROW()-4) -> 2 | B6: 45807 | C6: BUY | D6: SANLORENZO | E6: IT0003549422 | F6: EUR | G6: 1000 | H6: 30.55 | I6: =IF(OR(G6="",H6=""),"",G6*H6) -> 30550 | J6: 1 | K6: =IF(OR(I6="",J6=""),"",I6*J6) -> 30550 | L6: Acquisto 30/05/2025 (valuta 03/06/2025), aggregato di 16 eseguiti stesso prezzo. Commissioni €5,00 escluse dall'importo.
A7: =IF(B7="","",ROW()-4) -> 3 | B7: 45831 | C7: BUY | D7: WisdomTree Europe Defence UCITS ETF | E7: IE0002Y8CX98 | F7: EUR | G7: 33 | H7: 29.72 | I7: =IF(OR(G7="",H7=""),"",G7*H7) -> 980.76 | J7: 1 | K7: =IF(OR(I7="",J7=""),"",I7*J7) -> 980.76 | L7: Acquisto 23/06/2025 (valuta 25/06/2025). ETF EUDF/WDEF, EUR Acc, accumulation.
A8: =IF(B8="","",ROW()-4) -> 4 | B8: 45839 | C8: BUY | D8: WisdomTree Europe Defence UCITS ETF | E8: IE0002Y8CX98 | F8: EUR | G8: 33 | H8: 29.68 | I8: =IF(OR(G8="",H8=""),"",G8*H8) -> 979.44 | J8: 1 | K8: =IF(OR(I8="",J8=""),"",I8*J8) -> 979.44 | L8: Acquisto 01/07 valuta 03/07. ETF EUDF/WDEF EUR Acc.
A9: =IF(B9="","",ROW()-4) -> 5 | B9: 45846 | C9: BUY | D9: WisdomTree Europe Defence UCITS ETF | E9: IE0002Y8CX98 | F9: EUR | G9: 32 | H9: 30.625 | I9: =IF(OR(G9="",H9=""),"",G9*H9) -> 980 | J9: 1 | K9: =IF(OR(I9="",J9=""),"",I9*J9) -> 980 | L9: Acquisto 08/07 valuta 10/07.
A10: =IF(B10="","",ROW()-4) -> 6 | B10: 45853 | C10: BUY | D10: CARRARO FINANCE 5.25% Apr30 | E10: IT0006768151 | F10: EUR | G10: 20000 | H10: 1.0174 | I10: =IF(OR(G10="",H10=""),"",G10*H10) -> 20348 | J10: 1 | K10: =IF(OR(I10="",J10=""),"",I10*J10) -> 20348 | L10: Bond Carraro Fin 5,25% scad. 17/04/2030, callable. Nominale €20.000 @ 101,74% = €20.348. Prezzo espresso come decimale (quotazione %/100) per coerenza con formula. Commissioni €5,00 e rateo cedolare €261,07 contabilizzati separatamente.
A11: =IF(B11="","",ROW()-4) -> 7 | B11: 45853 | C11: BUY | D11: BOT Zero Coupon Dec25 | E11: IT0005627853 | F11: EUR | G11: 50000 | H11: 0.99228 | I11: =IF(OR(G11="",H11=""),"",G11*H11) -> 49614 | J11: 1 | K11: =IF(OR(I11="",J11=""),"",I11*J11) -> 49614 | L11: BOT scad. 12/12/2025. Nominale €50.000 @ 99,228% = €49.614. Prezzo in decimale per coerenza formula.
A12: =IF(B12="","",ROW()-4) -> 8 | B12: 45853 | C12: BUY | D12: iShares EUR High Yield Corp Bond UCITS ETF | E12: IE00B66F4759 | F12: EUR | G12: 250 | H12: 94.07 | I12: =IF(OR(G12="",H12=""),"",G12*H12) -> 23517.5 | J12: 1 | K12: =IF(OR(I12="",J12=""),"",I12*J12) -> 23517.5 | L12: ETF IHYG (Dist).
A13: =IF(B13="","",ROW()-4) -> 9 | B13: 45853 | C13: BUY | D13: WisdomTree Europe Defence UCITS ETF | E13: IE0002Y8CX98 | F13: EUR | G13: 32 | H13: 30.55 | I13: =IF(OR(G13="",H13=""),"",G13*H13) -> 977.6 | J13: 1 | K13: =IF(OR(I13="",J13=""),"",I13*J13) -> 977.6
A14: =IF(B14="","",ROW()-4) -> 10 | B14: 45853 | C14: BUY | D14: iShares FTSE MIB UCITS ETF Acc | E14: IE00B53L4X51 | F14: EUR | G14: 13 | H14: 190.28 | I14: =IF(OR(G14="",H14=""),"",G14*H14) -> 2473.64 | J14: 1 | K14: =IF(OR(I14="",J14=""),"",I14*J14) -> 2473.64 | L14: ETF SXRY (Acc).
A15: =IF(B15="","",ROW()-4) -> 11 | B15: 45854 | C15: BUY | D15: EXOR NV | E15: NL0012059018 | F15: EUR | G15: 100 | H15: 88.3 | I15: =IF(OR(G15="",H15=""),"",G15*H15) -> 8830 | J15: 1 | K15: =IF(OR(I15="",J15=""),"",I15*J15) -> 8830 | L15: Commissioni €9,50.
A16: =IF(B16="","",ROW()-4) -> 12 | B16: 45856 | C16: BUY | D16: FERRARI NV | E16: NL0011585146 | F16: EUR | G16: 100 | H16: 435.426 | I16: =IF(OR(G16="",H16=""),"",G16*H16) -> 43542.6 | J16: 1 | K16: =IF(OR(I16="",J16=""),"",I16*J16) -> 43542.6 | L16: Aggregato 6 eseguiti (prezzi 435,40-435,50). Prezzo medio ponderato. Importo totale €43.542,60. Commissioni €5,00.
A17: =IF(B17="","",ROW()-4) -> 13 | B17: 45859 | C17: BUY | D17: Bitwise Physical Bitcoin ETP | E17: DE000A27Z304 | F17: EUR | G17: 1 | H17: 91.865 | I17: =IF(OR(G17="",H17=""),"",G17*H17) -> 91.865 | J17: 1 | K17: =IF(OR(I17="",J17=""),"",I17*J17) -> 91.865 | L17: ETP BTCE.
A18: =IF(B18="","",ROW()-4) -> 14 | B18: 45859 | C18: BUY | D18: ITALGAS | E18: IT0005211237 | F18: EUR | G18: 1000 | H18: 7.215 | I18: =IF(OR(G18="",H18=""),"",G18*H18) -> 7215 | J18: 1 | K18: =IF(OR(I18="",J18=""),"",I18*J18) -> 7215
A19: =IF(B19="","",ROW()-4) -> 15 | B19: 45859 | C19: BUY | D19: ASML HOLDING NV | E19: NL0010273215 | F19: EUR | G19: 20 | H19: 624.3 | I19: =IF(OR(G19="",H19=""),"",G19*H19) -> 12486 | J19: 1 | K19: =IF(OR(I19="",J19=""),"",I19*J19) -> 12486
A20: =IF(B20="","",ROW()-4) -> 16 | B20: 45859 | C20: BUY | D20: PIAGGIO | E20: IT0003073266 | F20: EUR | G20: 5000 | H20: 1.9348 | I20: =IF(OR(G20="",H20=""),"",G20*H20) -> 9674 | J20: 1 | K20: =IF(OR(I20="",J20=""),"",I20*J20) -> 9674 | L20: Aggregato 2 eseguiti (1,934 / 1,935). Importo totale €9.674.
A21: =IF(B21="","",ROW()-4) -> 17 | B21: 45859 | C21: BUY | D21: RAI WAY | E21: IT0005054967 | F21: EUR | G21: 1000 | H21: 5.96621 | I21: =IF(OR(G21="",H21=""),"",G21*H21) -> 5966.21 | J21: 1 | K21: =IF(OR(I21="",J21=""),"",I21*J21) -> 5966.21 | L21: Aggregato 3 eseguiti (5,96-5,97). Importo totale €5.966,21.
A22: =IF(B22="","",ROW()-4) -> 18 | B22: 45859 | C22: BUY | D22: NEXI | E22: IT0005366767 | F22: EUR | G22: 1000 | H22: 5.134 | I22: =IF(OR(G22="",H22=""),"",G22*H22) -> 5134 | J22: 1 | K22: =IF(OR(I22="",J22=""),"",I22*J22) -> 5134
A23: =IF(B23="","",ROW()-4) -> 19 | B23: 45859 | C23: BUY | D23: BOT Zero Coupon Dec25 | E23: IT0005627853 | F23: EUR | G23: 50000 | H23: 0.99255 | I23: =IF(OR(G23="",H23=""),"",G23*H23) -> 49627.5 | J23: 1 | K23: =IF(OR(I23="",J23=""),"",I23*J23) -> 49627.5 | L23: Nominale €50.000 @ 99,255% = €49.627,50. Prezzo in decimale.
A24: =IF(B24="","",ROW()-4) -> 20 | B24: 45859 | C24: BUY | D24: BOT Zero Coupon Jan26 | E24: IT0005631533 | F24: EUR | G24: 20000 | H24: 0.99079 | I24: =IF(OR(G24="",H24=""),"",G24*H24) -> 19815.8 | J24: 1 | K24: =IF(OR(I24="",J24=""),"",I24*J24) -> 19815.8 | L24: BOT scad. 14/01/2026. Nominale €20.000 @ 99,079% = €19.815,80.
A25: =IF(B25="","",ROW()-4) -> 21 | B25: 45860 | C25: BUY | D25: Bitwise Physical Bitcoin ETP | E25: DE000A27Z304 | F25: EUR | G25: 1 | H25: 91.295 | I25: =IF(OR(G25="",H25=""),"",G25*H25) -> 91.295 | J25: 1 | K25: =IF(OR(I25="",J25=""),"",I25*J25) -> 91.295
A26: =IF(B26="","",ROW()-4) -> 22 | B26: 45861 | C26: BUY | D26: Bitwise Physical Bitcoin ETP | E26: DE000A27Z304 | F26: EUR | G26: 1 | H26: 91.065 | I26: =IF(OR(G26="",H26=""),"",G26*H26) -> 91.065 | J26: 1 | K26: =IF(OR(I26="",J26=""),"",I26*J26) -> 91.065
A27: =IF(B27="","",ROW()-4) -> 23 | B27: 45861 | C27: BUY | D27: Bitwise Ethereum Staking ETP | E27: DE000A3G90G9 | F27: EUR | G27: 100 | H27: 6.381 | I27: =IF(OR(G27="",H27=""),"",G27*H27) -> 638.1 | J27: 1 | K27: =IF(OR(I27="",J27=""),"",I27*J27) -> 638.1 | L27: ETP ET32.
A28: =IF(B28="","",ROW()-4) -> 24 | B28: 45861 | C28: BUY | D28: Bitwise Physical Ethereum ETP | E28: DE000A3GMKD7 | F28: EUR | G28: 4 | H28: 29.154 | I28: =IF(OR(G28="",H28=""),"",G28*H28) -> 116.616 | J28: 1 | K28: =IF(OR(I28="",J28=""),"",I28*J28) -> 116.616 | L28: ETP ZETH.
A29: =IF(B29="","",ROW()-4) -> 25 | B29: 45861 | C29: BUY | D29: iShares FTSE MIB UCITS ETF Acc | E29: IE00B53L4X51 | F29: EUR | G29: 12 | H29: 194.54 | I29: =IF(OR(G29="",H29=""),"",G29*H29) -> 2334.48 | J29: 1 | K29: =IF(OR(I29="",J29=""),"",I29*J29) -> 2334.48
A30: =IF(B30="","",ROW()-4) -> 26 | B30: 45861 | C30: BUY | D30: WisdomTree Core Physical Gold | E30: JE00BN2CJ301 | F30: EUR | G30: 1 | H30: 289.55 | I30: =IF(OR(G30="",H30=""),"",G30*H30) -> 289.55 | J30: 1 | K30: =IF(OR(I30="",J30=""),"",I30*J30) -> 289.55 | L30: ETC WGLD.
A31: =IF(B31="","",ROW()-4) -> 27 | B31: 45861 | C31: BUY | D31: WisdomTree Physical Silver | E31: JE00B1VS3333 | F31: EUR | G31: 16 | H31: 30.83 | I31: =IF(OR(G31="",H31=""),"",G31*H31) -> 493.28 | J31: 1 | K31: =IF(OR(I31="",J31=""),"",I31*J31) -> 493.28
A32: =IF(B32="","",ROW()-4) -> 28 | B32: 45861 | C32: BUY | D32: WisdomTree Europe Defence UCITS ETF | E32: IE0002Y8CX98 | F32: EUR | G32: 32 | H32: 30.445 | I32: =IF(OR(G32="",H32=""),"",G32*H32) -> 974.24 | J32: 1 | K32: =IF(OR(I32="",J32=""),"",I32*J32) -> 974.24
A33: =IF(B33="","",ROW()-4) -> 29 | B33: 45862 | C33: BUY | D33: Bitwise Ethereum Staking ETP | E33: DE000A3G90G9 | F33: EUR | G33: 10 | H33: 6.3465 | I33: =IF(OR(G33="",H33=""),"",G33*H33) -> 63.465 | J33: 1 | K33: =IF(OR(I33="",J33=""),"",I33*J33) -> 63.465
A34: =IF(B34="","",ROW()-4) -> 30 | B34: 45862 | C34: BUY | D34: Bitwise Physical Bitcoin ETP | E34: DE000A27Z304 | F34: EUR | G34: 1 | H34: 91.105 | I34: =IF(OR(G34="",H34=""),"",G34*H34) -> 91.105 | J34: 1 | K34: =IF(OR(I34="",J34=""),"",I34*J34) -> 91.105
A35: =IF(B35="","",ROW()-4) -> 31 | B35: 45862 | C35: BUY | D35: Bitwise Physical Ethereum ETP | E35: DE000A3GMKD7 | F35: EUR | G35: 10 | H35: 29.044 | I35: =IF(OR(G35="",H35=""),"",G35*H35) -> 290.44 | J35: 1 | K35: =IF(OR(I35="",J35=""),"",I35*J35) -> 290.44
A36: =IF(B36="","",ROW()-4) -> 32 | B36: 45863 | C36: BUY | D36: Bitwise Ethereum Staking ETP | E36: DE000A3G90G9 | F36: EUR | G36: 10 | H36: 6.369 | I36: =IF(OR(G36="",H36=""),"",G36*H36) -> 63.69 | J36: 1 | K36: =IF(OR(I36="",J36=""),"",I36*J36) -> 63.69
A37: =IF(B37="","",ROW()-4) -> 33 | B37: 45863 | C37: BUY | D37: Bitwise Physical Bitcoin ETP | E37: DE000A27Z304 | F37: EUR | G37: 1 | H37: 88.445 | I37: =IF(OR(G37="",H37=""),"",G37*H37) -> 88.445 | J37: 1 | K37: =IF(OR(I37="",J37=""),"",I37*J37) -> 88.445
A38: =IF(B38="","",ROW()-4) -> 34 | B38: 45863 | C38: BUY | D38: Bitwise Physical Ethereum ETP | E38: DE000A3GMKD7 | F38: EUR | G38: 1 | H38: 29.206 | I38: =IF(OR(G38="",H38=""),"",G38*H38) -> 29.206 | J38: 1 | K38: =IF(OR(I38="",J38=""),"",I38*J38) -> 29.206
A39: =IF(B39="","",ROW()-4) -> 35 | B39: 45863 | C39: BUY | D39: WisdomTree Core Physical Gold | E39: JE00BN2CJ301 | F39: EUR | G39: 10 | H39: 283.37 | I39: =IF(OR(G39="",H39=""),"",G39*H39) -> 2833.7 | J39: 1 | K39: =IF(OR(I39="",J39=""),"",I39*J39) -> 2833.7
A40: =IF(B40="","",ROW()-4) -> 36 | B40: 45863 | C40: BUY | D40: WisdomTree Physical Silver | E40: JE00B1VS3333 | F40: EUR | G40: 10 | H40: 30.275 | I40: =IF(OR(G40="",H40=""),"",G40*H40) -> 302.75 | J40: 1 | K40: =IF(OR(I40="",J40=""),"",I40*J40) -> 302.75
A41: =IF(B41="","",ROW()-4) -> 37 | B41: 45868 | C41: BUY | D41: Bitwise Physical Bitcoin ETP | E41: DE000A27Z304 | F41: EUR | G41: 1 | H41: 92.26 | I41: =IF(OR(G41="",H41=""),"",G41*H41) -> 92.26 | J41: 1 | K41: =IF(OR(I41="",J41=""),"",I41*J41) -> 92.26
A42: =IF(B42="","",ROW()-4) -> 38 | B42: 45868 | C42: BUY | D42: Bitwise Ethereum Staking ETP | E42: DE000A3G90G9 | F42: EUR | G42: 10 | H42: 6.726 | I42: =IF(OR(G42="",H42=""),"",G42*H42) -> 67.26 | J42: 1 | K42: =IF(OR(I42="",J42=""),"",I42*J42) -> 67.26
A43: =IF(B43="","",ROW()-4) -> 39 | B43: 45870 | C43: BUY | D43: FERRARI NV | E43: NL0011585146 | F43: EUR | G43: 100 | H43: 371.879 | I43: =IF(OR(G43="",H43=""),"",G43*H43) -> 37187.9 | J43: 1 | K43: =IF(OR(I43="",J43=""),"",I43*J43) -> 37187.9 | L43: Aggregato 3 eseguiti (371,80/371,90), prezzo medio ponderato. Importo €37.187,90. Commissioni €5,00.
A44: =IF(B44="","",ROW()-4) -> 40 | B44: 45870 | C44: BUY | D44: EXOR NV | E44: NL0012059018 | F44: EUR | G44: 120 | H44: 83.7 | I44: =IF(OR(G44="",H44=""),"",G44*H44) -> 10044 | J44: 1 | K44: =IF(OR(I44="",J44=""),"",I44*J44) -> 10044 | L44: Aggregato 5 eseguiti stesso prezzo. Importo €10.044. Commissioni €19,00 (2x9,50).
A45: =IF(B45="","",ROW()-4) -> 41 | B45: 45870 | C45: BUY | D45: Bitwise Physical Bitcoin ETP | E45: DE000A27Z304 | F45: EUR | G45: 1 | H45: 90.81 | I45: =IF(OR(G45="",H45=""),"",G45*H45) -> 90.81 | J45: 1 | K45: =IF(OR(I45="",J45=""),"",I45*J45) -> 90.81
A46: =IF(B46="","",ROW()-4) -> 42 | B46: 45870 | C46: BUY | D46: Bitwise Ethereum Staking ETP | E46: DE000A3G90G9 | F46: EUR | G46: 10 | H46: 6.498 | I46: =IF(OR(G46="",H46=""),"",G46*H46) -> 64.98 | J46: 1 | K46: =IF(OR(I46="",J46=""),"",I46*J46) -> 64.98
A47: =IF(B47="","",ROW()-4) -> 43 | B47: 45870 | C47: BUY | D47: Bitwise Physical Ethereum ETP | E47: DE000A3GMKD7 | F47: EUR | G47: 10 | H47: 29.724 | I47: =IF(OR(G47="",H47=""),"",G47*H47) -> 297.24 | J47: 1 | K47: =IF(OR(I47="",J47=""),"",I47*J47) -> 297.24
A48: =IF(B48="","",ROW()-4) -> 44 | B48: 45870 | C48: BUY | D48: ASML HOLDING NV | E48: NL0010273215 | F48: EUR | G48: 10 | H48: 598.5 | I48: =IF(OR(G48="",H48=""),"",G48*H48) -> 5985 | J48: 1 | K48: =IF(OR(I48="",J48=""),"",I48*J48) -> 5985
A49: =IF(B49="","",ROW()-4) -> 45 | B49: 45870 | C49: BUY | D49: WisdomTree Europe Defence UCITS ETF | E49: IE0002Y8CX98 | F49: EUR | G49: 33 | H49: 29.665 | I49: =IF(OR(G49="",H49=""),"",G49*H49) -> 978.945 | J49: 1 | K49: =IF(OR(I49="",J49=""),"",I49*J49) -> 978.945
A50: =IF(B50="","",ROW()-4) -> 46 | B50: 45870 | C50: BUY | D50: iShares FTSE MIB UCITS ETF Acc | E50: IE00B53L4X51 | F50: EUR | G50: 13 | H50: 190.92 | I50: =IF(OR(G50="",H50=""),"",G50*H50) -> 2481.96 | J50: 1 | K50: =IF(OR(I50="",J50=""),"",I50*J50) -> 2481.96
A51: =IF(B51="","",ROW()-4) -> 47 | B51: 45870 | C51: BUY | D51: WisdomTree Core Physical Gold | E51: JE00BN2CJ301 | F51: EUR | G51: 1 | H51: 288.53 | I51: =IF(OR(G51="",H51=""),"",G51*H51) -> 288.53 | J51: 1 | K51: =IF(OR(I51="",J51=""),"",I51*J51) -> 288.53
A52: =IF(B52="","",ROW()-4) -> 48 | B52: 45870 | C52: BUY | D52: WisdomTree Physical Silver | E52: JE00B1VS3333 | F52: EUR | G52: 17 | H52: 29.2853 | I52: =IF(OR(G52="",H52=""),"",G52*H52) -> 497.8501 | J52: 1 | K52: =IF(OR(I52="",J52=""),"",I52*J52) -> 497.8501 | L52: Prezzo medio ponderato (qty 17). Importo €497,85.
A53: =IF(B53="","",ROW()-4) -> 49 | B53: 45877 | C53: BUY | D53: Bitwise Physical Bitcoin ETP | E53: DE000A27Z304 | F53: EUR | G53: 160 | H53: 90.23125 | I53: =IF(OR(G53="",H53=""),"",G53*H53) -> 14437 | J53: 1 | K53: =IF(OR(I53="",J53=""),"",I53*J53) -> 14437 | L53: Aggregato 3 eseguiti (90,22/90,25), prezzo medio ponderato. Importo €14.437.
A54: =IF(B54="","",ROW()-4) -> 50 | B54: 45877 | C54: BUY | D54: Bitwise Ethereum Staking ETP | E54: DE000A3G90G9 | F54: EUR | G54: 100 | H54: 6.854 | I54: =IF(OR(G54="",H54=""),"",G54*H54) -> 685.4 | J54: 1 | K54: =IF(OR(I54="",J54=""),"",I54*J54) -> 685.4
A55: =IF(B55="","",ROW()-4) -> 51 | B55: 45877 | C55: BUY | D55: WisdomTree Europe Defence UCITS ETF | E55: IE0002Y8CX98 | F55: EUR | G55: 34 | H55: 29.15 | I55: =IF(OR(G55="",H55=""),"",G55*H55) -> 991.1 | J55: 1 | K55: =IF(OR(I55="",J55=""),"",I55*J55) -> 991.1
A56: =IF(B56="","",ROW()-4) -> 52 | B56: 45877 | C56: BUY | D56: iShares FTSE MIB UCITS ETF Acc | E56: IE00B53L4X51 | F56: EUR | G56: 12 | H56: 199.02 | I56: =IF(OR(G56="",H56=""),"",G56*H56) -> 2388.24 | J56: 1 | K56: =IF(OR(I56="",J56=""),"",I56*J56) -> 2388.24
A57: =IF(B57="","",ROW()-4) -> 53 | B57: 45877 | C57: BUY | D57: WisdomTree Core Physical Gold | E57: JE00BN2CJ301 | F57: EUR | G57: 1 | H57: 289.27 | I57: =IF(OR(G57="",H57=""),"",G57*H57) -> 289.27 | J57: 1 | K57: =IF(OR(I57="",J57=""),"",I57*J57) -> 289.27
A58: =IF(B58="","",ROW()-4) -> 54 | B58: 45877 | C58: BUY | D58: WisdomTree Physical Silver | E58: JE00B1VS3333 | F58: EUR | G58: 16 | H58: 30.07 | I58: =IF(OR(G58="",H58=""),"",G58*H58) -> 481.12 | J58: 1 | K58: =IF(OR(I58="",J58=""),"",I58*J58) -> 481.12
A59: =IF(B59="","",ROW()-4) -> 55 | B59: 45880 | C59: BUY | D59: Bitwise Ethereum Staking ETP | E59: DE000A3G90G9 | F59: EUR | G59: 200 | H59: 7.4975 | I59: =IF(OR(G59="",H59=""),"",G59*H59) -> 1499.5 | J59: 1 | K59: =IF(OR(I59="",J59=""),"",I59*J59) -> 1499.5
A60: =IF(B60="","",ROW()-4) -> 56 | B60: 45880 | C60: BUY | D60: Bitwise Solana Staking ETP | E60: DE000A4A59D2 | F60: EUR | G60: 200 | H60: 8.0635 | I60: =IF(OR(G60="",H60=""),"",G60*H60) -> 1612.7 | J60: 1 | K60: =IF(OR(I60="",J60=""),"",I60*J60) -> 1612.7 | L60: ETP BSOL EU — prima apertura posizione.
A61: =IF(B61="","",ROW()-4) -> 57 | B61: 45881 | C61: BUY | D61: Bitwise Solana Staking ETP | E61: DE000A4A59D2 | F61: EUR | G61: 200 | H61: 7.844 | I61: =IF(OR(G61="",H61=""),"",G61*H61) -> 1568.8 | J61: 1 | K61: =IF(OR(I61="",J61=""),"",I61*J61) -> 1568.8
A62: =IF(B62="","",ROW()-4) -> 58 | B62: 45881 | C62: BUY | D62: Bitwise Ethereum Staking ETP | E62: DE000A3G90G9 | F62: EUR | G62: 400 | H62: 7.716 | I62: =IF(OR(G62="",H62=""),"",G62*H62) -> 3086.4 | J62: 1 | K62: =IF(OR(I62="",J62=""),"",I62*J62) -> 3086.4 | L62: Aggregato 2 eseguiti stesso prezzo (7,7165/7,7155). Importo €3.086,40.
A63: =IF(B63="","",ROW()-4) -> 59 | B63: 45881 | C63: BUY | D63: Bitwise Physical Ethereum ETP | E63: DE000A3GMKD7 | F63: EUR | G63: 200 | H63: 34.96 | I63: =IF(OR(G63="",H63=""),"",G63*H63) -> 6992 | J63: 1 | K63: =IF(OR(I63="",J63=""),"",I63*J63) -> 6992 | L63: Aggregato 2 eseguiti (34,95/34,97). Importo €6.992.
A64: =IF(B64="","",ROW()-4) -> 60 | B64: 45887 | C64: BUY | D64: WisdomTree Europe Defence UCITS ETF | E64: IE0002Y8CX98 | F64: EUR | G64: 32 | H64: 30.205 | I64: =IF(OR(G64="",H64=""),"",G64*H64) -> 966.56 | J64: 1 | K64: =IF(OR(I64="",J64=""),"",I64*J64) -> 966.56
A65: =IF(B65="","",ROW()-4) -> 61 | B65: 45887 | C65: BUY | D65: iShares FTSE MIB UCITS ETF Acc | E65: IE00B53L4X51 | F65: EUR | G65: 12 | H65: 203.95 | I65: =IF(OR(G65="",H65=""),"",G65*H65) -> 2447.4 | J65: 1 | K65: =IF(OR(I65="",J65=""),"",I65*J65) -> 2447.4
A66: =IF(B66="","",ROW()-4) -> 62 | B66: 45887 | C66: BUY | D66: WisdomTree Core Physical Gold | E66: JE00BN2CJ301 | F66: EUR | G66: 1 | H66: 284.06 | I66: =IF(OR(G66="",H66=""),"",G66*H66) -> 284.06 | J66: 1 | K66: =IF(OR(I66="",J66=""),"",I66*J66) -> 284.06
A67: =IF(B67="","",ROW()-4) -> 63 | B67: 45887 | C67: BUY | D67: WisdomTree Physical Silver | E67: JE00B1VS3333 | F67: EUR | G67: 16 | H67: 29.82 | I67: =IF(OR(G67="",H67=""),"",G67*H67) -> 477.12 | J67: 1 | K67: =IF(OR(I67="",J67=""),"",I67*J67) -> 477.12
A68: =IF(B68="","",ROW()-4) -> 64 | B68: 45894 | C68: BUY | D68: WisdomTree Europe Defence UCITS ETF | E68: IE0002Y8CX98 | F68: EUR | G68: 33 | H68: 29.725 | I68: =IF(OR(G68="",H68=""),"",G68*H68) -> 980.925 | J68: 1 | K68: =IF(OR(I68="",J68=""),"",I68*J68) -> 980.925
A69: =IF(B69="","",ROW()-4) -> 65 | B69: 45894 | C69: BUY | D69: iShares FTSE MIB UCITS ETF Acc | E69: IE00B53L4X51 | F69: EUR | G69: 12 | H69: 206.75 | I69: =IF(OR(G69="",H69=""),"",G69*H69) -> 2481 | J69: 1 | K69: =IF(OR(I69="",J69=""),"",I69*J69) -> 2481
A70: =IF(B70="","",ROW()-4) -> 66 | B70: 45894 | C70: BUY | D70: WisdomTree Core Physical Gold | E70: JE00BN2CJ301 | F70: EUR | G70: 1 | H70: 287.08 | I70: =IF(OR(G70="",H70=""),"",G70*H70) -> 287.08 | J70: 1 | K70: =IF(OR(I70="",J70=""),"",I70*J70) -> 287.08
A71: =IF(B71="","",ROW()-4) -> 67 | B71: 45894 | C71: BUY | D71: WisdomTree Physical Silver | E71: JE00B1VS3333 | F71: EUR | G71: 16 | H71: 30.39 | I71: =IF(OR(G71="",H71=""),"",G71*H71) -> 486.24 | J71: 1 | K71: =IF(OR(I71="",J71=""),"",I71*J71) -> 486.24
A72: =IF(B72="","",ROW()-4) -> 68 | B72: 45897 | C72: BUY | D72: Tamburi Investment Partners | E72: IT0003153621 | F72: EUR | G72: 2500 | H72: 8.252252 | I72: =IF(OR(G72="",H72=""),"",G72*H72) -> 20630.63 | J72: 1 | K72: =IF(OR(I72="",J72=""),"",I72*J72) -> 20630.63 | L72: Aggregato 8 eseguiti (8,25/8,26), prezzo medio ponderato. Importo €20.630,63. Commissioni €5,00.
A73: =IF(B73="","",ROW()-4) -> 69 | B73: 45901 | C73: BUY | D73: WisdomTree Europe Defence UCITS ETF | E73: IE0002Y8CX98 | F73: EUR | G73: 32 | H73: 30.545 | I73: =IF(OR(G73="",H73=""),"",G73*H73) -> 977.44 | J73: 1 | K73: =IF(OR(I73="",J73=""),"",I73*J73) -> 977.44
A74: =IF(B74="","",ROW()-4) -> 70 | B74: 45901 | C74: BUY | D74: iShares FTSE MIB UCITS ETF Acc | E74: IE00B53L4X51 | F74: EUR | G74: 12 | H74: 202.8 | I74: =IF(OR(G74="",H74=""),"",G74*H74) -> 2433.6 | J74: 1 | K74: =IF(OR(I74="",J74=""),"",I74*J74) -> 2433.6
A75: =IF(B75="","",ROW()-4) -> 71 | B75: 45901 | C75: BUY | D75: WisdomTree Core Physical Gold | E75: JE00BN2CJ301 | F75: EUR | G75: 1 | H75: 295.4 | I75: =IF(OR(G75="",H75=""),"",G75*H75) -> 295.4 | J75: 1 | K75: =IF(OR(I75="",J75=""),"",I75*J75) -> 295.4
A76: =IF(B76="","",ROW()-4) -> 72 | B76: 45901 | C76: BUY | D76: WisdomTree Physical Silver | E76: JE00B1VS3333 | F76: EUR | G76: 15 | H76: 31.8053 | I76: =IF(OR(G76="",H76=""),"",G76*H76) -> 477.0795 | J76: 1 | K76: =IF(OR(I76="",J76=""),"",I76*J76) -> 477.0795
A77: =IF(B77="","",ROW()-4) -> 73 | B77: 45908 | C77: BUY | D77: WisdomTree Europe Defence UCITS ETF | E77: IE0002Y8CX98 | F77: EUR | G77: 32 | H77: 30.25 | I77: =IF(OR(G77="",H77=""),"",G77*H77) -> 968 | J77: 1 | K77: =IF(OR(I77="",J77=""),"",I77*J77) -> 968
A78: =IF(B78="","",ROW()-4) -> 74 | B78: 45908 | C78: BUY | D78: iShares FTSE MIB UCITS ETF Acc | E78: IE00B53L4X51 | F78: EUR | G78: 12 | H78: 199.5 | I78: =IF(OR(G78="",H78=""),"",G78*H78) -> 2394 | J78: 1 | K78: =IF(OR(I78="",J78=""),"",I78*J78) -> 2394
A79: =IF(B79="","",ROW()-4) -> 75 | B79: 45908 | C79: BUY | D79: WisdomTree Core Physical Gold | E79: JE00BN2CJ301 | F79: EUR | G79: 1 | H79: 307.71 | I79: =IF(OR(G79="",H79=""),"",G79*H79) -> 307.71 | J79: 1 | K79: =IF(OR(I79="",J79=""),"",I79*J79) -> 307.71
A80: =IF(B80="","",ROW()-4) -> 76 | B80: 45908 | C80: BUY | D80: WisdomTree Physical Silver | E80: JE00B1VS3333 | F80: EUR | G80: 15 | H80: 32.13 | I80: =IF(OR(G80="",H80=""),"",G80*H80) -> 481.95 | J80: 1 | K80: =IF(OR(I80="",J80=""),"",I80*J80) -> 481.95
A81: =IF(B81="","",ROW()-4) -> 77 | B81: 45911 | C81: BUY | D81: ORACLE CORP | E81: US68389X1054 | F81: USD | G81: 10 | H81: 330 | I81: =IF(OR(G81="",H81=""),"",G81*H81) -> 3300 | J81: 0.851861 | K81: =IF(OR(I81="",J81=""),"",I81*J81) -> 2811.1413 | L81: Prima posizione USA. FX EUR/USD implicito 0,851861 (importo EUR 2.811,14 / 3.300 USD). Commissioni €7,67.
A82: =IF(B82="","",ROW()-4) -> 78 | B82: 45911 | C82: BUY | D82: EXOR NV | E82: NL0012059018 | F82: EUR | G82: 100 | H82: 83.45 | I82: =IF(OR(G82="",H82=""),"",G82*H82) -> 8345 | J82: 1 | K82: =IF(OR(I82="",J82=""),"",I82*J82) -> 8345 | L82: Aggregato 2 eseguiti stesso prezzo. Commissioni €9,50.
A83: =IF(B83="","",ROW()-4) -> 79 | B83: 45911 | C83: BUY | D83: NEXI | E83: IT0005366767 | F83: EUR | G83: 1000 | H83: 4.7145 | I83: =IF(OR(G83="",H83=""),"",G83*H83) -> 4714.5 | J83: 1 | K83: =IF(OR(I83="",J83=""),"",I83*J83) -> 4714.5 | L83: Aggregato 3 eseguiti (4,738/4,691). Prezzo medio ponderato. Commissioni €10.
A84: =IF(B84="","",ROW()-4) -> 80 | B84: 45912 | C84: BUY | D84: ORACLE CORP | E84: US68389X1054 | F84: USD | G84: 15 | H84: 298.31667 | I84: =IF(OR(G84="",H84=""),"",G84*H84) -> 4474.75 | J84: 0.852008 | K84: =IF(OR(I84="",J84=""),"",I84*J84) -> 3812.5228 | L84: Aggregato 2 eseguiti USD (306,00/294,4745). Prezzo medio ponderato. FX EUR/USD implicito ~0,852008. Importo €3.812,52. Commissioni €15,34.
A85: =IF(B85="","",ROW()-4) -> 81 | B85: 45912 | C85: BUY | D85: NEXI | E85: IT0005366767 | F85: EUR | G85: 500 | H85: 4.656 | I85: =IF(OR(G85="",H85=""),"",G85*H85) -> 2328 | J85: 1 | K85: =IF(OR(I85="",J85=""),"",I85*J85) -> 2328
A86: =IF(B86="","",ROW()-4) -> 82 | B86: 45915 | C86: BUY | D86: WisdomTree Europe Defence UCITS ETF | E86: IE0002Y8CX98 | F86: EUR | G86: 30 | H86: 32.7 | I86: =IF(OR(G86="",H86=""),"",G86*H86) -> 981 | J86: 1 | K86: =IF(OR(I86="",J86=""),"",I86*J86) -> 981
A87: =IF(B87="","",ROW()-4) -> 83 | B87: 45915 | C87: BUY | D87: iShares FTSE MIB UCITS ETF Acc | E87: IE00B53L4X51 | F87: EUR | G87: 12 | H87: 205.8 | I87: =IF(OR(G87="",H87=""),"",G87*H87) -> 2469.6 | J87: 1 | K87: =IF(OR(I87="",J87=""),"",I87*J87) -> 2469.6
A88: =IF(B88="","",ROW()-4) -> 84 | B88: 45915 | C88: BUY | D88: WisdomTree Core Physical Gold | E88: JE00BN2CJ301 | F88: EUR | G88: 1 | H88: 309.85 | I88: =IF(OR(G88="",H88=""),"",G88*H88) -> 309.85 | J88: 1 | K88: =IF(OR(I88="",J88=""),"",I88*J88) -> 309.85
A89: =IF(B89="","",ROW()-4) -> 85 | B89: 45915 | C89: BUY | D89: WisdomTree Physical Silver | E89: JE00B1VS3333 | F89: EUR | G89: 15 | H89: 32.9653 | I89: =IF(OR(G89="",H89=""),"",G89*H89) -> 494.4795 | J89: 1 | K89: =IF(OR(I89="",J89=""),"",I89*J89) -> 494.4795
A90: =IF(B90="","",ROW()-4) -> 86 | B90: 45916 | C90: BUY | D90: ORACLE CORP | E90: US68389X1054 | F90: USD | G90: 10 | H90: 304.16 | I90: =IF(OR(G90="",H90=""),"",G90*H90) -> 3041.6 | J90: 0.843099 | K90: =IF(OR(I90="",J90=""),"",I90*J90) -> 2564.3699 | L90: FX EUR/USD implicito 0,843099. Importo €2.564,37. Commissioni €7,59.
A91: =IF(B91="","",ROW()-4) -> 87 | B91: 45917 | C91: BUY | D91: Tamburi Investment Partners | E91: IT0003153621 | F91: EUR | G91: 1000 | H91: 8.36 | I91: =IF(OR(G91="",H91=""),"",G91*H91) -> 8360 | J91: 1 | K91: =IF(OR(I91="",J91=""),"",I91*J91) -> 8360
A92: =IF(B92="","",ROW()-4) -> 88 | B92: 45917 | C92: BUY | D92: IGD - Immobiliare Grande Distribuzione SIIQ | E92: IT0005322612 | F92: EUR | G92: 1000 | H92: 3.34 | I92: =IF(OR(G92="",H92=""),"",G92*H92) -> 3340 | J92: 1 | K92: =IF(OR(I92="",J92=""),"",I92*J92) -> 3340 | L92: Aggregato 3 eseguiti stesso prezzo. Importo €3.340.
A93: =IF(B93="","",ROW()-4) -> 89 | B93: 45917 | C93: BUY | D93: WisdomTree New Economy Real Estate UCITS ETF | E93: IE000MO2MB07 | F93: EUR | G93: 1000 | H93: 23.45 | I93: =IF(OR(G93="",H93=""),"",G93*H93) -> 23450 | J93: 1 | K93: =IF(OR(I93="",J93=""),"",I93*J93) -> 23450 | L93: ETF WTRE USD Acc, ma trade su Borsa Italiana in EUR. Aggregato 2 eseguiti stesso prezzo. Importo €23.450.
A94: =IF(B94="","",ROW()-4) -> 90 | B94: 45923 | C94: BUY | D94: WisdomTree Europe Defence UCITS ETF | E94: IE0002Y8CX98 | F94: EUR | G94: 30 | H94: 32.105 | I94: =IF(OR(G94="",H94=""),"",G94*H94) -> 963.15 | J94: 1 | K94: =IF(OR(I94="",J94=""),"",I94*J94) -> 963.15
A95: =IF(B95="","",ROW()-4) -> 91 | B95: 45923 | C95: BUY | D95: iShares FTSE MIB UCITS ETF Acc | E95: IE00B53L4X51 | F95: EUR | G95: 12 | H95: 203.3 | I95: =IF(OR(G95="",H95=""),"",G95*H95) -> 2439.6 | J95: 1 | K95: =IF(OR(I95="",J95=""),"",I95*J95) -> 2439.6
A96: =IF(B96="","",ROW()-4) -> 92 | B96: 45923 | C96: BUY | D96: WisdomTree Core Physical Gold | E96: JE00BN2CJ301 | F96: EUR | G96: 1 | H96: 318.86 | I96: =IF(OR(G96="",H96=""),"",G96*H96) -> 318.86 | J96: 1 | K96: =IF(OR(I96="",J96=""),"",I96*J96) -> 318.86
A97: =IF(B97="","",ROW()-4) -> 93 | B97: 45923 | C97: BUY | D97: WisdomTree Physical Silver | E97: JE00B1VS3333 | F97: EUR | G97: 14 | H97: 34.315 | I97: =IF(OR(G97="",H97=""),"",G97*H97) -> 480.41 | J97: 1 | K97: =IF(OR(I97="",J97=""),"",I97*J97) -> 480.41
A98: =IF(B98="","",ROW()-4) -> 94 | B98: 45924 | C98: BUY | D98: IGD - Immobiliare Grande Distribuzione SIIQ | E98: IT0005322612 | F98: EUR | G98: 2000 | H98: 3.334595 | I98: =IF(OR(G98="",H98=""),"",G98*H98) -> 6669.19 | J98: 1 | K98: =IF(OR(I98="",J98=""),"",I98*J98) -> 6669.19 | L98: Aggregato 4 eseguiti (3,33/3,335/3,34). Prezzo medio ponderato. Importo €6.669,19. Commissioni €5.
A99: =IF(B99="","",ROW()-4) -> 95 | B99: 45929 | C99: BUY | D99: Bitwise Ethereum Staking ETP | E99: DE000A3G90G9 | F99: EUR | G99: 500 | H99: 7.1555 | I99: =IF(OR(G99="",H99=""),"",G99*H99) -> 3577.75 | J99: 1 | K99: =IF(OR(I99="",J99=""),"",I99*J99) -> 3577.75
A100: =IF(B100="","",ROW()-4) -> 96 | B100: 45929 | C100: BUY | D100: WisdomTree Core Physical Gold | E100: JE00BN2CJ301 | F100: EUR | G100: 30 | H100: 324.46 | I100: =IF(OR(G100="",H100=""),"",G100*H100) -> 9733.8 | J100: 1 | K100: =IF(OR(I100="",J100=""),"",I100*J100) -> 9733.8
A101: =IF(B101="","",ROW()-4) -> 97 | B101: 45929 | C101: BUY | D101: WisdomTree Physical Silver | E101: JE00B1VS3333 | F101: EUR | G101: 200 | H101: 36.695 | I101: =IF(OR(G101="",H101=""),"",G101*H101) -> 7339 | J101: 1 | K101: =IF(OR(I101="",J101=""),"",I101*J101) -> 7339
...

Sheet 05_Dividendi_Interessi
A1: Dividendi, Cedole, Interessi (al LORDO delle imposte)
A2: Include dividendi azionari, cedole obbligazionarie, interessi su prestiti privati. Tutti gli importi sono al LORDO di ritenute e imposte. Le ritenute non vengono tracciate.
A4: ID | B4: Data | C4: Tipo | D4: Strumento/Controparte | E4: ISIN | F4: Valuta | G4: Lordo Loc. | H4: FX→EUR | I4: Lordo EUR
A5: =IF(B5="","",ROW()-4) -> 1 | B5: 45915 | C5: DIVIDEND | D5: iShares Core MSCI World | E5: IE00B4L5Y983 | F5: EUR | G5: 850 | H5: 1 | I5: =IF(OR(G5="",H5=""),"",G5*H5) -> 850
A6: =IF(B6="","",ROW()-4) -> 2 | B6: 45869 | C6: INTEREST | D6: SANLORENZO — Interessi prestito titoli | E6: IT0003549422 | F6: EUR | G6: 7.47 | H6: 1 | I6: =IF(OR(G6="",H6=""),"",G6*H6) -> 7.47
A7: =IF(B7="","",ROW()-4) -> 3 | B7: 45869 | C7: INTEREST | D7: BOT ZC DEC25 — Interessi prestito titoli | E7: IT0005627853 | F7: EUR | G7: 1.08 | H7: 1 | I7: =IF(OR(G7="",H7=""),"",G7*H7) -> 1.08
A8: =IF(B8="","",ROW()-4) -> 4 | B8: 45875 | C8: DIVIDEND | D8: ASML Holding NV | E8: NL0010273215 | F8: EUR | G8: 27.2 | H8: 1 | I8: =IF(OR(G8="",H8=""),"",G8*H8) -> 27.2
A9: =IF(B9="","",ROW()-4) -> 5 | B9: 45900 | C9: INTEREST | D9: SANLORENZO — Interessi prestito titoli | E9: IT0003549422 | F9: EUR | G9: 3.06 | H9: 1 | I9: =IF(OR(G9="",H9=""),"",G9*H9) -> 3.06
A10: =IF(B10="","",ROW()-4) -> 6 | B10: 45900 | C10: INTEREST | D10: BOT ZC DEC25 — Interessi prestito titoli | E10: IT0005627853 | F10: EUR | G10: 4.86 | H10: 1 | I10: =IF(OR(G10="",H10=""),"",G10*H10) -> 4.86
A11: =IF(B11="","",ROW()-4) -> 7 | B11: 45910 | C11: ETF_INCOME | D11: iShares EUR High Yield Corp Bond UCITS ETF (IHYG) | E11: IE00B66F4759 | F11: EUR | G11: 604.33 | H11: 1 | I11: =IF(OR(G11="",H11=""),"",G11*H11) -> 604.33
A12: =IF(B12="","",ROW()-4) -> 8 | B12: 45919 | C12: DIVIDEND | D12: PIAGGIO | E12: IT0003073266 | F12: EUR | G12: 200 | H12: 1 | I12: =IF(OR(G12="",H12=""),"",G12*H12) -> 200
A13: =IF(B13="","",ROW()-4) -> 9 | B13: 45944 | C13: COUPON | D13: Carraro Finance 5,25% Apr30 — cedola semestrale | E13: IT0006768151 | F13: EUR | G13: 525 | H13: 1 | I13: =IF(OR(G13="",H13=""),"",G13*H13) -> 525
A14: =IF(B14="","",ROW()-4) -> 10 | B14: 45954 | C14: DIVIDEND | D14: ORACLE CORP | E14: US68389X1054 | F14: EUR | G14: 20.12 | H14: 1 | I14: =IF(OR(G14="",H14=""),"",G14*H14) -> 20.12
A15: =IF(B15="","",ROW()-4) -> 11 | B15: 45968 | C15: DIVIDEND | D15: ASML Holding NV | E15: NL0010273215 | F15: EUR | G15: 40.8 | H15: 1 | I15: =IF(OR(G15="",H15=""),"",G15*H15) -> 40.8
A16: =IF(B16="","",ROW()-4) -> 12 | B16: 45981 | C16: DIVIDEND | D16: d'Amico International Shipping | E16: LU2592315662 | F16: EUR | G16: 296.38 | H16: 1 | I16: =IF(OR(G16="",H16=""),"",G16*H16) -> 296.38
... A31: =IF(B31="","",ROW()-4) -> 27 | B31: 46142 | C31: DIVIDEND | D31: IGD | E31: IT0005322612 | F31: EUR | G31: 450 | H31: 1 | I31: =IF(OR(G31="",H31=""),"",G31*H31) -> 450
A32: =IF(B32="","",ROW()-4) | I32: =IF(OR(G32="",H32=""),"",G32*H32)
A33: =IF(B33="","",ROW()-4) | I33: =IF(OR(G33="",H33=""),"",G33*H33)
A34: =IF(B34="","",ROW()-4) | I34: =IF(OR(G34="",H34=""),"",G34*H34)
A35: =IF(B35="","",ROW()-4) | I35: =IF(OR(G35="",H35=""),"",G35*H35)
A36: =IF(B36="","",ROW()-4) | I36: =IF(OR(G36="",H36=""),"",G36*H36)
A37: =IF(B37="","",ROW()-4) | I37: =IF(OR(G37="",H37=""),"",G37*H37)
A38: =IF(B38="","",ROW()-4) | I38: =IF(OR(G38="",H38=""),"",G38*H38)
A39: =IF(B39="","",ROW()-4) | I39: =IF(OR(G39="",H39=""),"",G39*H39)
A40: =IF(B40="","",ROW()-4) | I40: =IF(OR(G40="",H40=""),"",G40*H40)
A41: =IF(B41="","",ROW()-4) | I41: =IF(OR(G41="",H41=""),"",G41*H41)
A42: =IF(B42="","",ROW()-4) | I42: =IF(OR(G42="",H42=""),"",G42*H42)
A43: =IF(B43="","",ROW()-4) | I43: =IF(OR(G43="",H43=""),"",G43*H43)
... A504: =IF(B504="","",ROW()-4) | I504: =IF(OR(G504="",H504=""),"",G504*H504)

Sheet 06_Partecipazioni
A1: Partecipazioni Non Quotate
A2: Acquisti/vendite di quote di società non quotate. 'Valore Corrente EUR' è la valutazione mark-to-market della partecipazione oggi (override manuale). Lasciare vuoto per usare il costo storico.
A4: ID | B4: Data | C4: Tipo | D4: Investee | E4: Quota % | F4: Valuta | G4: Importo Loc. | H4: FX→EUR | I4: Importo EUR | J4: Valore Corrente EUR | K4: Note
A5: =IF(B5="","",ROW()-4) -> 1 | B5: 45940 | C5: BUY | D5: Ariete Tech Solutions | E5: 1 | F5: EUR | G5: 110000 | H5: 1 | I5: =IF(OR(G5="",H5=""),"",G5*H5) -> 110000 | J5: 100000
A6: =IF(B6="","",ROW()-4) -> 2 | B6: 45945 | C6: BUY | D6: BS2 Srl | F6: EUR | G6: 25000 | H6: 1 | I6: =IF(OR(G6="",H6=""),"",G6*H6) -> 25000 | J6: 25000
A7: =IF(B7="","",ROW()-4) -> 3 | B7: 46021 | C7: BUY | D7: Bollette Republic | F7: EUR | G7: 30000 | H7: 1 | I7: =IF(OR(G7="",H7=""),"",G7*H7) -> 30000 | J7: 30000
A8: =IF(B8="","",ROW()-4) | I8: =IF(OR(G8="",H8=""),"",G8*H8)
A9: =IF(B9="","",ROW()-4) | I9: =IF(OR(G9="",H9=""),"",G9*H9)
A10: =IF(B10="","",ROW()-4) | I10: =IF(OR(G10="",H10=""),"",G10*H10)
A11: =IF(B11="","",ROW()-4) | I11: =IF(OR(G11="",H11=""),"",G11*H11)
A12: =IF(B12="","",ROW()-4) | I12: =IF(OR(G12="",H12=""),"",G12*H12)
A13: =IF(B13="","",ROW()-4) | I13: =IF(OR(G13="",H13=""),"",G13*H13)
A14: =IF(B14="","",ROW()-4) | I14: =IF(OR(G14="",H14=""),"",G14*H14)
A15: =IF(B15="","",ROW()-4) | I15: =IF(OR(G15="",H15=""),"",G15*H15)
A16: =IF(B16="","",ROW()-4) | I16: =IF(OR(G16="",H16=""),"",G16*H16)
A17: =IF(B17="","",ROW()-4) | I17: =IF(OR(G17="",H17=""),"",G17*H17)
A18: =IF(B18="","",ROW()-4) | I18: =IF(OR(G18="",H18=""),"",G18*H18)
A19: =IF(B19="","",ROW()-4) | I19: =IF(OR(G19="",H19=""),"",G19*H19)
... A204: =IF(B204="","",ROW()-4) | I204: =IF(OR(G204="",H204=""),"",G204*H204)

Sheet 07_Prestiti
A1: Prestiti Privati verso Partecipate
A2: Solo principal (erogazioni e rimborsi). Gli interessi maturati e ricevuti sui prestiti vanno registrati in 05_Dividendi_Interessi con Tipo = LOAN_INT.
A4: ID | B4: Data | C4: Tipo | D4: Controparte | E4: Valuta | F4: Importo Loc. | G4: FX→EUR | H4: Importo EUR | I4: Outstanding EUR Override | J4: Note
A5: =IF(B5="","",ROW()-4) -> 1 | B5: 45961 | C5: DISBURSEMENT | D5: ATS | E5: EUR | F5: 15000 | G5: 1 | H5: =IF(OR(F5="",G5=""),"",F5*G5) -> 15000
A6: =IF(B6="","",ROW()-4) -> 2 | B6: 45992 | C6: DISBURSEMENT | D6: ATS | E6: EUR | F6: 15000 | G6: 1 | H6: =IF(OR(F6="",G6=""),"",F6*G6) -> 15000
A7: =IF(B7="","",ROW()-4) -> 3 | B7: 46007 | C7: DISBURSEMENT | D7: ATS | E7: EUR | F7: 15000 | G7: 1 | H7: =IF(OR(F7="",G7=""),"",F7*G7) -> 15000
A8: =IF(B8="","",ROW()-4) -> 4 | B8: 46018 | C8: DISBURSEMENT | D8: ATS | E8: EUR | F8: 15000 | G8: 1 | H8: =IF(OR(F8="",G8=""),"",F8*G8) -> 15000
A9: =IF(B9="","",ROW()-4) -> 5 | B9: 46049 | C9: DISBURSEMENT | D9: ATS | E9: EUR | F9: 10000 | G9: 1 | H9: =IF(OR(F9="",G9=""),"",F9*G9) -> 10000
A10: =IF(B10="","",ROW()-4) -> 6 | B10: 46066 | C10: DISBURSEMENT | D10: ATS | E10: EUR | F10: 10000 | G10: 1 | H10: =IF(OR(F10="",G10=""),"",F10*G10) -> 10000
A11: =IF(B11="","",ROW()-4) -> 7 | B11: 46084 | C11: DISBURSEMENT | D11: ATS | E11: EUR | F11: 10000 | G11: 1 | H11: =IF(OR(F11="",G11=""),"",F11*G11) -> 10000
A12: =IF(B12="","",ROW()-4) -> 8 | B12: 46104 | C12: DISBURSEMENT | D12: ATS | E12: EUR | F12: 15000 | G12: 1 | H12: =IF(OR(F12="",G12=""),"",F12*G12) -> 15000
A13: =IF(B13="","",ROW()-4) -> 9 | B13: 46120 | C13: DISBURSEMENT | D13: ATS | E13: EUR | F13: 15000 | G13: 1 | H13: =IF(OR(F13="",G13=""),"",F13*G13) -> 15000
A14: =IF(B14="","",ROW()-4) -> 10 | B14: 46136 | C14: DISBURSEMENT | D14: ATS | E14: EUR | F14: 15000 | G14: 1 | H14: =IF(OR(F14="",G14=""),"",F14*G14) -> 15000
A15: =IF(B15="","",ROW()-4) | H15: =IF(OR(F15="",G15=""),"",F15*G15)
A16: =IF(B16="","",ROW()-4) | H16: =IF(OR(F16="",G16=""),"",F16*G16)
A17: =IF(B17="","",ROW()-4) | H17: =IF(OR(F17="",G17=""),"",F17*G17)
A18: =IF(B18="","",ROW()-4) | H18: =IF(OR(F18="",G18=""),"",F18*G18)
A19: =IF(B19="","",ROW()-4) | H19: =IF(OR(F19="",G19=""),"",F19*G19)
A20: =IF(B20="","",ROW()-4) | H20: =IF(OR(F20="",G20=""),"",F20*G20)
A21: =IF(B21="","",ROW()-4) | H21: =IF(OR(F21="",G21=""),"",F21*G21)
A22: =IF(B22="","",ROW()-4) | H22: =IF(OR(F22="",G22=""),"",F22*G22)
A23: =IF(B23="","",ROW()-4) | H23: =IF(OR(F23="",G23=""),"",F23*G23)
A24: =IF(B24="","",ROW()-4) | H24: =IF(OR(F24="",G24=""),"",F24*G24)
A25: =IF(B25="","",ROW()-4) | H25: =IF(OR(F25="",G25=""),"",F25*G25)
A26: =IF(B26="","",ROW()-4) | H26: =IF(OR(F26="",G26=""),"",F26*G26)
... A204: =IF(B204="","",ROW()-4) | H204: =IF(OR(F204="",G204=""),"",F204*G204)

Sheet 08_PL_Operativa
A1: P/L da Attività Operativa
A2: Input manuale. Inserire il P/L netto dell'attività operativa per periodo: positivo se utile, negativo se perdita. Tutti gli importi sono al LORDO delle imposte.
A4: ID | B4: Data | C4: Categoria | D4: Descrizione | E4: Valuta | F4: P/L Loc. | G4: FX→EUR | H4: P/L EUR | I4: Note
A5: =IF(B5="","",ROW()-4) -> 1 | B5: 45667 | C5: Imposte e bolli | D5: Bollo portafoglio titoli (rif. 31/12/2024) — Directa B6166 | E5: EUR | F5: -4.7 | G5: 1 | H5: =IF(OR(F5="",G5=""),"",F5*G5) -> -4.7
A6: =IF(B6="","",ROW()-4) -> 2 | B6: 45847 | C6: Imposte e bolli | D6: Bollo portafoglio titoli (rif. 30/06/2025) — Directa B6166 | E6: EUR | F6: -45 | G6: 1 | H6: =IF(OR(F6="",G6=""),"",F6*G6) -> -45
A7: =IF(B7="","",ROW()-4) -> 3 | B7: 45853 | C7: Ratei passivi obbligazioni | D7: Rateo cedolare Carraro Finance 5.25% Apr30 acquisto | E7: EUR | F7: -261.07 | G7: 1 | H7: =IF(OR(F7="",G7=""),"",F7*G7) -> -261.07
A8: =IF(B8="","",ROW()-4) -> 4 | B8: 45859 | C8: Imposte e bolli | D8: Tobin Tax Italia (trade italiani del 21/07/2025) | E8: EUR | F8: -27.99 | G8: 1 | H8: =IF(OR(F8="",G8=""),"",F8*G8) -> -27.99
A9: =IF(B9="","",ROW()-4) -> 5 | B9: 45897 | C9: Imposte e bolli | D9: Tobin Tax Italia (acquisto Tamburi 28/08/2025) | E9: EUR | F9: -20.63 | G9: 1 | H9: =IF(OR(F9="",G9=""),"",F9*G9) -> -20.63
A10: =IF(B10="","",ROW()-4) -> 6 | B10: 45910 | C10: Imposte e bolli | D10: Ritenuta provento ETF IHYG (26%) | E10: EUR | F10: -156.73 | G10: 1 | H10: =IF(OR(F10="",G10=""),"",F10*G10) -> -156.73
A11: =IF(B11="","",ROW()-4) -> 7 | B11: 45911 | C11: Imposte e bolli | D11: Tobin Tax Italia (trade italiani del 11/09/2025) | E11: EUR | F11: -4.71 | G11: 1 | H11: =IF(OR(F11="",G11=""),"",F11*G11) -> -4.71
A12: =IF(B12="","",ROW()-4) -> 8 | B12: 45912 | C12: Imposte e bolli | D12: Tobin Tax Italia (trade italiani del 12/09/2025) | E12: EUR | F12: -2.33 | G12: 1 | H12: =IF(OR(F12="",G12=""),"",F12*G12) -> -2.33
A13: =IF(B13="","",ROW()-4) -> 9 | B13: 45917 | C13: Imposte e bolli | D13: Tobin Tax Italia (Tamburi/IGD/WTRE 17/09/2025) | E13: EUR | F13: -8.36 | G13: 1 | H13: =IF(OR(F13="",G13=""),"",F13*G13) -> -8.36
A14: =IF(B14="","",ROW()-4) -> 10 | B14: 45929 | C14: Imposte e bolli | D14: Tobin Tax Italia (acquisti 29/09/2025: B&C, CY4, AMICO, AZM, BC, IP) | E14: EUR | F14: -45.66 | G14: 1 | H14: =IF(OR(F14="",G14=""),"",F14*G14) -> -45.66
A15: =IF(B15="","",ROW()-4) -> 11 | B15: 45932 | C15: Ratei passivi obbligazioni | D15: Rateo cedolare BTP 3.2% Jan26 acquisto | E15: EUR | F15: -243.48 | G15: 1 | H15: =IF(OR(F15="",G15=""),"",F15*G15) -> -243.48
A16: =IF(B16="","",ROW()-4) -> 12 | B16: 45940 | C16: Imposte e bolli | D16: Bollo portafoglio titoli (rif. 30/09/2025) — Directa B6166 | E16: EUR | F16: -272.2 | G16: 1 | H16: =IF(OR(F16="",G16=""),"",F16*G16) -> -272.2
... A31: =IF(B31="","",ROW()-4) -> 27 | B31: 46112 | C31: Risultato | D31: Risultato primo trimestre 2026 | E31: EUR | F31: 64959 | G31: 1 | H31: =IF(OR(F31="",G31=""),"",F31*G31) -> 64959
A32: =IF(B32="","",ROW()-4) | H32: =IF(OR(F32="",G32=""),"",F32*G32)
A33: =IF(B33="","",ROW()-4) | H33: =IF(OR(F33="",G33=""),"",F33*G33)
A34: =IF(B34="","",ROW()-4) | H34: =IF(OR(F34="",G34=""),"",F34*G34)
A35: =IF(B35="","",ROW()-4) | H35: =IF(OR(F35="",G35=""),"",F35*G35)
A36: =IF(B36="","",ROW()-4) | H36: =IF(OR(F36="",G36=""),"",F36*G36)
A37: =IF(B37="","",ROW()-4) | H37: =IF(OR(F37="",G37=""),"",F37*G37)
A38: =IF(B38="","",ROW()-4) | H38: =IF(OR(F38="",G38=""),"",F38*G38)
A39: =IF(B39="","",ROW()-4) | H39: =IF(OR(F39="",G39=""),"",F39*G39)
A40: =IF(B40="","",ROW()-4) | H40: =IF(OR(F40="",G40=""),"",F40*G40)
A41: =IF(B41="","",ROW()-4) | H41: =IF(OR(F41="",G41=""),"",F41*G41)
A42: =IF(B42="","",ROW()-4) | H42: =IF(OR(F42="",G42=""),"",F42*G42)
A43: =IF(B43="","",ROW()-4) | H43: =IF(OR(F43="",G43=""),"",F43*G43)
... A503: =IF(B503="","",ROW()-4) | H503: =IF(OR(F503="",G503=""),"",F503*G503)

Sheet 09_Posizioni
A1: Posizioni Aperte (Strumenti Quotati)
A2: Inserire ogni ISIN una sola volta in colonna B. Le formule calcolano qty netta, market value all'ultimo prezzo di trade (metodologia di valutazione concordata), e P&L. Nome/Valuta sono presi dall'ultimo trade per quell'ISIN.
A4: # | B4: ISIN | C4: Nome (auto) | D4: Valuta (auto) | E4: Qty BUY | F4: Qty SELL | G4: Qty Netta | H4: Ultimo Prezzo Loc. | I4: Ultimo FX | J4: MV Loc. | K4: MV EUR | L4: Costo Medio EUR | M4: P&L Non Realiz. EUR | N4: =" Prezzo Spot @"&TEXT(DataOggi-1,"dd/mm/yy") -> Prezzo Spot @17/05/yy | O4: MV Spot EUR | P4: P&L Spot EUR
A5: =IF(B5="","",ROW()-4) -> 1 | B5: US15118V2079 | C5: =IFERROR(LOOKUP(2,1/('04_Trades'!$E$5:$E$1004=B5),'04_Trades'!$D$5:$D$1004),"") -> CELSIUS HOLDINGS | D5: =IFERROR(LOOKUP(2,1/('04_Trades'!$E$5:$E$1004=B5),'04_Trades'!$F$5:$F$1004),"") -> EUR | E5: =IF(B5="",0,SUMIFS('04_Trades'!$G$5:$G$1004,'04_Trades'!$E$5:$E$1004,B5,'04_Trades'!$C$5:$C$1004,"BUY")) -> 369 | F5: =IF(B5="",0,SUMIFS('04_Trades'!$G$5:$G$1004,'04_Trades'!$E$5:$E$1004,B5,'04_Trades'!$C$5:$C$1004,"SELL")) -> 0 | G5: =IF(B5="","",E5-F5) -> 369 | H5: =IFERROR(LOOKUP(2,1/('04_Trades'!$E$5:$E$1004=B5),'04_Trades'!$H$5:$H$1004),"") -> 25.4223 | I5: =IFERROR(VLOOKUP(D5,'02_FX_Rates'!$A$5:$B$10,2,FALSE),IFERROR(LOOKUP(2,1/('04_Trades'!$E$5:$E$1004=B5),'04_Trades'!$J$5:$J$1004),"")) -> 1 | J5: =IF(OR(B5="",G5="",H5=""),"",G5*H5) -> 9380.8287 | K5: =IF(OR(B5="",J5="",I5=""),"",J5*I5) -> 9380.8287 | L5: =IFERROR(SUMIFS('04_Trades'!$K$5:$K$1004,'04_Trades'!$E$5:$E$1004,B5,'04_Trades'!$C$5:$C$1004,"BUY")/SUMIFS('04_Trades'!$G$5:$G$1004,'04_Trades'!$E$5:$E$1004,B5,'04_Trades'!$C$5:$C$1004,"BUY"),"") -> 25.4223 | M5: =IF(OR(B5="",G5=0,K5="",L5=""),"",K5-G5*L5) -> 0 | N5: 25.42 | O5: =IFERROR(IF(N5="","",G5*N5*I5),"") -> 9379.98 | P5: =IFERROR(IF(OR(N5="",G5=0,L5=""),"",O5-G5*L5),"") -> -0.8487
A6: =IF(B6="","",ROW()-4) -> 2 | B6: IT0003549422 | C6: =IFERROR(LOOKUP(2,1/('04_Trades'!$E$5:$E$1004=B6),'04_Trades'!$D$5:$D$1004),"") -> SANLORENZO | D6: =IFERROR(LOOKUP(2,1/('04_Trades'!$E$5:$E$1004=B6),'04_Trades'!$F$5:$F$1004),"") -> EUR | E6: =IF(B6="",0,SUMIFS('04_Trades'!$G$5:$G$1004,'04_Trades'!$E$5:$E$1004,B6,'04_Trades'!$C$5:$C$1004,"BUY")) -> 1100 | F6: =IF(B6="",0,SUMIFS('04_Trades'!$G$5:$G$1004,'04_Trades'!$E$5:$E$1004,B6,'04_Trades'!$C$5:$C$1004,"SELL")) -> 0 | G6: =IF(B6="","",E6-F6) -> 1100 | H6: =IFERROR(LOOKUP(2,1/('04_Trades'!$E$5:$E$1004=B6),'04_Trades'!$H$5:$H$1004),"") -> 34.2 | I6: =IFERROR(VLOOKUP(D6,'02_FX_Rates'!$A$5:$B$10,2,FALSE),IFERROR(LOOKUP(2,1/('04_Trades'!$E$5:$E$1004=B6),'04_Trades'!$J$5:$J$1004),"")) -> 1 | J6: =IF(OR(B6="",G6="",H6=""),"",G6*H6) -> 37620 | K6: =IF(OR(B6="",J6="",I6=""),"",J6*I6) -> 37620 | L6: =IFERROR(SUMIFS('04_Trades'!$K$5:$K$1004,'04_Trades'!$E$5:$E$1004,B6,'04_Trades'!$C$5:$C$1004,"BUY")/SUMIFS('04_Trades'!$G$5:$G$1004,'04_Trades'!$E$5:$E$1004,B6,'04_Trades'!$C$5:$C$1004,"BUY"),"") -> 30.881818 | M6: =IF(OR(B6="",G6=0,K6="",L6=""),"",K6-G6*L6) -> 3650 | N6: 34.55 | O6: =IFERROR(IF(N6="","",G6*N6*I6),"") -> 38005 | P6: =IFERROR(IF(OR(N6="",G6=0,L6=""),"",O6-G6*L6),"") -> 4035
A7: =IF(B7="","",ROW()-4) -> 3 | B7: IE0002Y8CX98 | C7: =IFERROR(LOOKUP(2,1/('04_Trades'!$E$5:$E$1004=B7),'04_Trades'!$D$5:$D$1004),"") -> WisdomTree Europe Defence UCITS ETF | D7: =IFERROR(LOOKUP(2,1/('04_Trades'!$E$5:$E$1004=B7),'04_Trades'!$F$5:$F$1004),"") -> EUR | E7: =IF(B7="",0,SUMIFS('04_Trades'!$G$5:$G$1004,'04_Trades'!$E$5:$E$1004,B7,'04_Trades'!$C$5:$C$1004,"BUY")) -> 1266 | F7: =IF(B7="",0,SUMIFS('04_Trades'!$G$5:$G$1004,'04_Trades'!$E$5:$E$1004,B7,'04_Trades'!$C$5:$C$1004,"SELL")) -> 0 | G7: =IF(B7="","",E7-F7) -> 1266 | H7: =IFERROR(LOOKUP(2,1/('04_Trades'!$E$5:$E$1004=B7),'04_Trades'!$H$5:$H$1004),"") -> 31.7352 | I7: =IFERROR(VLOOKUP(D7,'02_FX_Rates'!$A$5:$B$10,2,FALSE),IFERROR(LOOKUP(2,1/('04_Trades'!$E$5:$E$1004=B7),'04_Trades'!$J$5:$J$1004),"")) -> 1 | J7: =IF(OR(B7="",G7="",H7=""),"",G7*H7) -> 40176.763 | K7: =IF(OR(B7="",J7="",I7=""),"",J7*I7) -> 40176.763 | L7: =IFERROR(SUMIFS('04_Trades'!$K$5:$K$1004,'04_Trades'!$E$5:$E$1004,B7,'04_Trades'!$C$5:$C$1004,"BUY")/SUMIFS('04_Trades'!$G$5:$G$1004,'04_Trades'!$E$5:$E$1004,B7,'04_Trades'!$C$5:$C$1004,"BUY"),"") -> 31.662912 | M7: =IF(OR(B7="",G7=0,K7="",L7=""),"",K7-G7*L7) -> 91.5162 | N7: 30.65 | O7: =IFERROR(IF(N7="","",G7*N7*I7),"") -> 38802.9 | P7: =IFERROR(IF(OR(N7="",G7=0,L7=""),"",O7-G7*L7),"") -> -1282.347
A8: =IF(B8="","",ROW()-4) -> 4 | B8: IT0006768151 | C8: =IFERROR(LOOKUP(2,1/('04_Trades'!$E$5:$E$1004=B8),'04_Trades'!$D$5:$D$1004),"") -> CARRARO FINANCE 5.25% Apr30 | D8: =IFERROR(LOOKUP(2,1/('04_Trades'!$E$5:$E$1004=B8),'04_Trades'!$F$5:$F$1004),"") -> EUR | E8: =IF(B8="",0,SUMIFS('04_Trades'!$G$5:$G$1004,'04_Trades'!$E$5:$E$1004,B8,'04_Trades'!$C$5:$C$1004,"BUY")) -> 20000 | F8: =IF(B8="",0,SUMIFS('04_Trades'!$G$5:$G$1004,'04_Trades'!$E$5:$E$1004,B8,'04_Trades'!$C$5:$C$1004,"SELL")) -> 0 | G8: =IF(B8="","",E8-F8) -> 20000 | H8: =IFERROR(LOOKUP(2,1/('04_Trades'!$E$5:$E$1004=B8),'04_Trades'!$H$5:$H$1004),"") -> 1.0174 | I8: =IFERROR(VLOOKUP(D8,'02_FX_Rates'!$A$5:$B$10,2,FALSE),IFERROR(LOOKUP(2,1/('04_Trades'!$E$5:$E$1004=B8),'04_Trades'!$J$5:$J$1004),"")) -> 1 | J8: =IF(OR(B8="",G8="",H8=""),"",G8*H8) -> 20348 | K8: =IF(OR(B8="",J8="",I8=""),"",J8*I8) -> 20348 | L8: =IFERROR(SUMIFS('04_Trades'!$K$5:$K$1004,'04_Trades'!$E$5:$E$1004,B8,'04_Trades'!$C$5:$C$1004,"BUY")/SUMIFS('04_Trades'!$G$5:$G$1004,'04_Trades'!$E$5:$E$1004,B8,'04_Trades'!$C$5:$C$1004,"BUY"),"") -> 1.0174 | M8: =IF(OR(B8="",G8=0,K8="",L8=""),"",K8-G8*L8) -> 0 | N8: 1.015 | O8: =IFERROR(IF(N8="","",G8*N8*I8),"") -> 20300 | P8: =IFERROR(IF(OR(N8="",G8=0,L8=""),"",O8-G8*L8),"") -> -48
A9: =IF(B9="","",ROW()-4) -> 5 | B9: IT0005627853 | C9: =IFERROR(LOOKUP(2,1/('04_Trades'!$E$5:$E$1004=B9),'04_Trades'!$D$5:$D$1004),"") -> BOT Zero Coupon Dec25 | D9: =IFERROR(LOOKUP(2,1/('04_Trades'!$E$5:$E$1004=B9),'04_Trades'!$F$5:$F$1004),"") -> EUR | E9: =IF(B9="",0,SUMIFS('04_Trades'!$G$5:$G$1004,'04_Trades'!$E$5:$E$1004,B9,'04_Trades'!$C$5:$C$1004,"BUY")) -> 150000 | F9: =IF(B9="",0,SUMIFS('04_Trades'!$G$5:$G$1004,'04_Trades'!$E$5:$E$1004,B9,'04_Trades'!$C$5:$C$1004,"SELL")) -> 150000 | G9: =IF(B9="","",E9-F9) -> 0 | H9: =IFERROR(LOOKUP(2,1/('04_Trades'!$E$5:$E$1004=B9),'04_Trades'!$H$5:$H$1004),"") -> 1 | I9: =IFERROR(VLOOKUP(D9,'02_FX_Rates'!$A$5:$B$10,2,FALSE),IFERROR(LOOKUP(2,1/('04_Trades'!$E$5:$E$1004=B9),'04_Trades'!$J$5:$J$1004),"")) -> 1 | J9: =IF(OR(B9="",G9="",H9=""),"",G9*H9) -> 0 | K9: =IF(OR(B9="",J9="",I9=""),"",J9*I9) -> 0 | L9: =IFERROR(SUMIFS('04_Trades'!$K$5:$K$1004,'04_Trades'!$E$5:$E$1004,B9,'04_Trades'!$C$5:$C$1004,"BUY")/SUMIFS('04_Trades'!$G$5:$G$1004,'04_Trades'!$E$5:$E$1004,B9,'04_Trades'!$C$5:$C$1004,"BUY"),"") -> 0.993854 | M9: =IF(OR(B9="",G9=0,K9="",L9=""),"",K9-G9*L9) | N9: 1 | O9: =IFERROR(IF(N9="","",G9*N9*I9),"") -> 0 | P9: =IFERROR(IF(OR(N9="",G9=0,L9=""),"",O9-G9*L9),"")
A10: =IF(B10="","",ROW()-4) -> 6 | B10: IE00B66F4759 | C10: =IFERROR(LOOKUP(2,1/('04_Trades'!$E$5:$E$1004=B10),'04_Trades'!$D$5:$D$1004),"") -> iShares EUR High Yield Corp Bond UCITS ETF | D10: =IFERROR(LOOKUP(2,1/('04_Trades'!$E$5:$E$1004=B10),'04_Trades'!$F$5:$F$1004),"") -> EUR | E10: =IF(B10="",0,SUMIFS('04_Trades'!$G$5:$G$1004,'04_Trades'!$E$5:$E$1004,B10,'04_Trades'!$C$5:$C$1004,"BUY")) -> 350 | F10: =IF(B10="",0,SUMIFS('04_Trades'!$G$5:$G$1004,'04_Trades'!$E$5:$E$1004,B10,'04_Trades'!$C$5:$C$1004,"SELL")) -> 0 | G10: =IF(B10="","",E10-F10) -> 350 | H10: =IFERROR(LOOKUP(2,1/('04_Trades'!$E$5:$E$1004=B10),'04_Trades'!$H$5:$H$1004),"") -> 92.9 | I10: =IFERROR(VLOOKUP(D10,'02_FX_Rates'!$A$5:$B$10,2,FALSE),IFERROR(LOOKUP(2,1/('04_Trades'!$E$5:$E$1004=B10),'04_Trades'!$J$5:$J$1004),"")) -> 1 | J10: =IF(OR(B10="",G10="",H10=""),"",G10*H10) -> 32515 | K10: =IF(OR(B10="",J10="",I10=""),"",J10*I10) -> 32515 | L10: =IFERROR(SUMIFS('04_Trades'!$K$5:$K$1004,'04_Trades'!$E$5:$E$1004,B10,'04_Trades'!$C$5:$C$1004,"BUY")/SUMIFS('04_Trades'!$G$5:$G$1004,'04_Trades'!$E$5:$E$1004,B10,'04_Trades'!$C$5:$C$1004,"BUY"),"") -> 93.735714 | M10: =IF(OR(B10="",G10=0,K10="",L10=""),"",K10-G10*L10) -> -292.5 | N10: 91.46 | O10: =IFERROR(IF(N10="","",G10*N10*I10),"") -> 32011 | P10: =IFERROR(IF(OR(N10="",G10=0,L10=""),"",O10-G10*L10),"") -> -796.5
A11: =IF(B11="","",ROW()-4) -> 7 | B11: IE00B53L4X51 | C11: =IFERROR(LOOKUP(2,1/('04_Trades'!$E$5:$E$1004=B11),'04_Trades'!$D$5:$D$1004),"") -> iShares FTSE MIB UCITS ETF Acc | D11: =IFERROR(LOOKUP(2,1/('04_Trades'!$E$5:$E$1004=B11),'04_Trades'!$F$5:$F$1004),"") -> EUR | E11: =IF(B11="",0,SUMIFS('04_Trades'!$G$5:$G$1004,'04_Trades'!$E$5:$E$1004,B11,'04_Trades'!$C$5:$C$1004,"BUY")) -> 398 | F11: =IF(B11="",0,SUMIFS('04_Trades'!$G$5:$G$1004,'04_Trades'!$E$5:$E$1004,B11,'04_Trades'!$C$5:$C$1004,"SELL")) -> 0 | G11: =IF(B11="","",E11-F11) -> 398 | H11: =IFERROR(LOOKUP(2,1/('04_Trades'!$E$5:$E$1004=B11),'04_Trades'!$H$5:$H$1004),"") -> 233.9 | I11: =IFERROR(VLOOKUP(D11,'02_FX_Rates'!$A$5:$B$10,2,FALSE),IFERROR(LOOKUP(2,1/('04_Trades'!$E$5:$E$1004=B11),'04_Trades'!$J$5:$J$1004),"")) -> 1 | J11: =IF(OR(B11="",G11="",H11=""),"",G11*H11) -> 93092.2 | K11: =IF(OR(B11="",J11="",I11=""),"",J11*I11) -> 93092.2 | L11: =IFERROR(SUMIFS('04_Trades'!$K$5:$K$1004,'04_Trades'!$E$5:$E$1004,B11,'04_Trades'!$C$5:$C$1004,"BUY")/SUMIFS('04_Trades'!$G$5:$G$1004,'04_Trades'!$E$5:$E$1004,B11,'04_Trades'!$C$5:$C$1004,"BUY"),"") -> 210.34251 | M11: =IF(OR(B11="",G11=0,K11="",L11=""),"",K11-G11*L11) -> 9375.88 | N11: 242.85 | O11: =IFERROR(IF(N11="","",G11*N11*I11),"") -> 96654.3 | P11: =IFERROR(IF(OR(N11="",G11=0,L11=""),"",O11-G11*L11),"") -> 12937.98
A12: =IF(B12="","",ROW()-4) -> 8 | B12: NL0012059018 | C12: =IFERROR(LOOKUP(2,1/('04_Trades'!$E$5:$E$1004=B12),'04_Trades'!$D$5:$D$1004),"") -> EXOR NV | D12: =IFERROR(LOOKUP(2,1/('04_Trades'!$E$5:$E$1004=B12),'04_Trades'!$F$5:$F$1004),"") -> EUR | E12: =IF(B12="",0,SUMIFS('04_Trades'!$G$5:$G$1004,'04_Trades'!$E$5:$E$1004,B12,'04_Trades'!$C$5:$C$1004,"BUY")) -> 520 | F12: =IF(B12="",0,SUMIFS('04_Trades'!$G$5:$G$1004,'04_Trades'!$E$5:$E$1004,B12,'04_Trades'!$C$5:$C$1004,"SELL")) -> 0 | G12: =IF(B12="","",E12-F12) -> 520 | H12: =IFERROR(LOOKUP(2,1/('04_Trades'!$E$5:$E$1004=B12),'04_Trades'!$H$5:$H$1004),"") -> 75.91475 | I12: =IFERROR(VLOOKUP(D12,'02_FX_Rates'!$A$5:$B$10,2,FALSE),IFERROR(LOOKUP(2,1/('04_Trades'!$E$5:$E$1004=B12),'04_Trades'!$J$5:$J$1004),"")) -> 1 | J12: =IF(OR(B12="",G12="",H12=""),"",G12*H12) -> 39475.67 | K12: =IF(OR(B12="",J12="",I12=""),"",J12*I12) -> 39475.67 | L12: =IFERROR(SUMIFS('04_Trades'!$K$5:$K$1004,'04_Trades'!$E$5:$E$1004,B12,'04_Trades'!$C$5:$C$1004,"BUY")/SUMIFS('04_Trades'!$G$5:$G$1004,'04_Trades'!$E$5:$E$1004,B12,'04_Trades'!$C$5:$C$1004,"BUY"),"") -> 81.542212 | M12: =IF(OR(B12="",G12=0,K12="",L12=""),"",K12-G12*L12) -> -2926.28 | N12: 66.45 | O12: =IFERROR(IF(N12="","",G12*N12*I12),"") -> 34554 | P12: =IFERROR(IF(OR(N12="",G12=0,L12=""),"",O12-G12*L12),"") -> -7847.95
A13: =IF(B13="","",ROW()-4) -> 9 | B13: NL0011585146 | C13: =IFERROR(LOOKUP(2,1/('04_Trades'!$E$5:$E$1004=B13),'04_Trades'!$D$5:$D$1004),"") -> FERRARI NV | D13: =IFERROR(LOOKUP(2,1/('04_Trades'!$E$5:$E$1004=B13),'04_Trades'!$F$5:$F$1004),"") -> EUR | E13: =IF(B13="",0,SUMIFS('04_Trades'!$G$5:$G$1004,'04_Trades'!$E$5:$E$1004,B13,'04_Trades'!$C$5:$C$1004,"BUY")) -> 300 | F13: =IF(B13="",0,SUMIFS('04_Trades'!$G$5:$G$1004,'04_Trades'!$E$5:$E$1004,B13,'04_Trades'!$C$5:$C$1004,"SELL")) -> 0 | G13: =IF(B13="","",E13-F13) -> 300 | H13: =IFERROR(LOOKUP(2,1/('04_Trades'!$E$5:$E$1004=B13),'04_Trades'!$H$5:$H$1004),"") -> 360.418 | I13: =IFERROR(VLOOKUP(D13,'02_FX_Rates'!$A$5:$B$10,2,FALSE),IFERROR(LOOKUP(2,1/('04_Trades'!$E$5:$E$1004=B13),'04_Trades'!$J$5:$J$1004),"")) -> 1 | J13: =IF(OR(B13="",G13="",H13=""),"",G13*H13) -> 108125.4 | K13: =IF(OR(B13="",J13="",I13=""),"",J13*I13) -> 108125.4 | L13: =IFERROR(SUMIFS('04_Trades'!$K$5:$K$1004,'04_Trades'!$E$5:$E$1004,B13,'04_Trades'!$C$5:$C$1004,"BUY")/SUMIFS('04_Trades'!$G$5:$G$1004,'04_Trades'!$E$5:$E$1004,B13,'04_Trades'!$C$5:$C$1004,"BUY"),"") -> 389.241 | M13: =IF(OR(B13="",G13=0,K13="",L13=""),"",K13-G13*L13) -> -8646.9 | N13: 279.75 | O13: =IFERROR(IF(N13="","",G13*N13*I13),"") -> 83925 | P13: =IFERROR(IF(OR(N13="",G13=0,L13=""),"",O13-G13*L13),"") -> -32847.3
A14: =IF(B14="","",ROW()-4) -> 10 | B14: DE000A27Z304 | C14: =IFERROR(LOOKUP(2,1/('04_Trades'!$E$5:$E$1004=B14),'04_Trades'!$D$5:$D$1004),"") -> Bitwise Physical Bitcoin ETP | D14: =IFERROR(LOOKUP(2,1/('04_Trades'!$E$5:$E$1004=B14),'04_Trades'!$F$5:$F$1004),"") -> EUR | E14: =IF(B14="",0,SUMIFS('04_Trades'!$G$5:$G$1004,'04_Trades'!$E$5:$E$1004,B14,'04_Trades'!$C$5:$C$1004,"BUY")) -> 534 | F14: =IF(B14="",0,SUMIFS('04_Trades'!$G$5:$G$1004,'04_Trades'!$E$5:$E$1004,B14,'04_Trades'!$C$5:$C$1004,"SELL")) -> 0 | G14: =IF(B14="","",E14-F14) -> 534 | H14: =IFERROR(LOOKUP(2,1/('04_Trades'!$E$5:$E$1004=B14),'04_Trades'!$H$5:$H$1004),"") -> 50.1552 | I14: =IFERROR(VLOOKUP(D14,'02_FX_Rates'!$A$5:$B$10,2,FALSE),IFERROR(LOOKUP(2,1/('04_Trades'!$E$5:$E$1004=B14),'04_Trades'!$J$5:$J$1004),"")) -> 1 | J14: =IF(OR(B14="",G14="",H14=""),"",G14*H14) -> 26782.877 | K14: =IF(OR(B14="",J14="",I14=""),"",J14*I14) -> 26782.877 | L14: =IFERROR(SUMIFS('04_Trades'!$K$5:$K$1004,'04_Trades'!$E$5:$E$1004,B14,'04_Trades'!$C$5:$C$1004,"BUY")/SUMIFS('04_Trades'!$G$5:$G$1004,'04_Trades'!$E$5:$E$1004,B14,'04_Trades'!$C$5:$C$1004,"BUY"),"") -> 62.698134 | M14: =IF(OR(B14="",G14=0,K14="",L14=""),"",K14-G14*L14) -> -6697.9266 | N14: 60.5 | O14: =IFERROR(IF(N14="","",G14*N14*I14),"") -> 32307 | P14: =IFERROR(IF(OR(N14="",G14=0,L14=""),"",O14-G14*L14),"") -> -1173.8034
A15: =IF(B15="","",ROW()-4) -> 11 | B15: IT0005211237 | C15: =IFERROR(LOOKUP(2,1/('04_Trades'!$E$5:$E$1004=B15),'04_Trades'!$D$5:$D$1004),"") -> ITALGAS | D15: =IFERROR(LOOKUP(2,1/('04_Trades'!$E$5:$E$1004=B15),'04_Trades'!$F$5:$F$1004),"") -> EUR | E15: =IF(B15="",0,SUMIFS('04_Trades'!$G$5:$G$1004,'04_Trades'!$E$5:$E$1004,B15,'04_Trades'!$C$5:$C$1004,"BUY")) -> 1000 | F15: =IF(B15="",0,SUMIFS('04_Trades'!$G$5:$G$1004,'04_Trades'!$E$5:$E$1004,B15,'04_Trades'!$C$5:$C$1004,"SELL")) -> 0 | G15: =IF(B15="","",E15-F15) -> 1000 | H15: =IFERROR(LOOKUP(2,1/('04_Trades'!$E$5:$E$1004=B15),'04_Trades'!$H$5:$H$1004),"") -> 7.215 | I15: =IFERROR(VLOOKUP(D15,'02_FX_Rates'!$A$5:$B$10,2,FALSE),IFERROR(LOOKUP(2,1/('04_Trades'!$E$5:$E$1004=B15),'04_Trades'!$J$5:$J$1004),"")) -> 1 | J15: =IF(OR(B15="",G15="",H15=""),"",G15*H15) -> 7215 | K15: =IF(OR(B15="",J15="",I15=""),"",J15*I15) -> 7215 | L15: =IFERROR(SUMIFS('04_Trades'!$K$5:$K$1004,'04_Trades'!$E$5:$E$1004,B15,'04_Trades'!$C$5:$C$1004,"BUY")/SUMIFS('04_Trades'!$G$5:$G$1004,'04_Trades'!$E$5:$E$1004,B15,'04_Trades'!$C$5:$C$1004,"BUY"),"") -> 7.215 | M15: =IF(OR(B15="",G15=0,K15="",L15=""),"",K15-G15*L15) -> 0 | N15: 7.215 | O15: =IFERROR(IF(N15="","",G15*N15*I15),"") -> 7215 | P15: =IFERROR(IF(OR(N15="",G15=0,L15=""),"",O15-G15*L15),"") -> 0
A16: =IF(B16="","",ROW()-4) -> 12 | B16: NL0010273215 | C16: =IFERROR(LOOKUP(2,1/('04_Trades'!$E$5:$E$1004=B16),'04_Trades'!$D$5:$D$1004),"") -> ASML HOLDING NV | D16: =IFERROR(LOOKUP(2,1/('04_Trades'!$E$5:$E$1004=B16),'04_Trades'!$F$5:$F$1004),"") -> EUR | E16: =IF(B16="",0,SUMIFS('04_Trades'!$G$5:$G$1004,'04_Trades'!$E$5:$E$1004,B16,'04_Trades'!$C$5:$C$1004,"BUY")) -> 30 | F16: =IF(B16="",0,SUMIFS('04_Trades'!$G$5:$G$1004,'04_Trades'!$E$5:$E$1004,B16,'04_Trades'!$C$5:$C$1004,"SELL")) -> 30 | G16: =IF(B16="","",E16-F16) -> 0 | H16: =IFERROR(LOOKUP(2,1/('04_Trades'!$E$5:$E$1004=B16),'04_Trades'!$H$5:$H$1004),"") -> 1141.2 | I16: =IFERROR(VLOOKUP(D16,'02_FX_Rates'!$A$5:$B$10,2,FALSE),IFERROR(LOOKUP(2,1/('04_Trades'!$E$5:$E$1004=B16),'04_Trades'!$J$5:$J$1004),"")) -> 1 | J16: =IF(OR(B16="",G16="",H16=""),"",G16*H16) -> 0 | K16: =IF(OR(B16="",J16="",I16=""),"",J16*I16) -> 0 | L16: =IFERROR(SUMIFS('04_Trades'!$K$5:$K$1004,'04_Trades'!$E$5:$E$1004,B16,'04_Trades'!$C$5:$C$1004,"BUY")/SUMIFS('04_Trades'!$G$5:$G$1004,'04_Trades'!$E$5:$E$1004,B16,'04_Trades'!$C$5:$C$1004,"BUY"),"") -> 615.7 | M16: =IF(OR(B16="",G16=0,K16="",L16=""),"",K16-G16*L16) | N16: 600 | O16: =IFERROR(IF(N16="","",G16*N16*I16),"") -> 0 | P16: =IFERROR(IF(OR(N16="",G16=0,L16=""),"",O16-G16*L16),"")
... A59: =IF(B59="","",ROW()-4) -> 55 | B59: NL0009690239 | C59: =IFERROR(LOOKUP(2,1/('04_Trades'!$E$5:$E$1004=B59),'04_Trades'!$D$5:$D$1004),"") -> VanEck Global Real Estate UCITS ETF | D59: =IFERROR(LOOKUP(2,1/('04_Trades'!$E$5:$E$1004=B59),'04_Trades'!$F$5:$F$1004),"") -> EUR | E59: =IF(B59="",0,SUMIFS('04_Trades'!$G$5:$G$1004,'04_Trades'!$E$5:$E$1004,B59,'04_Trades'!$C$5:$C$1004,"BUY")) -> 124 | F59: =IF(B59="",0,SUMIFS('04_Trades'!$G$5:$G$1004,'04_Trades'!$E$5:$E$1004,B59,'04_Trades'!$C$5:$C$1004,"SELL")) -> 0 | G59: =IF(B59="","",E59-F59) -> 124 | H59: =IFERROR(LOOKUP(2,1/('04_Trades'!$E$5:$E$1004=B59),'04_Trades'!$H$5:$H$1004),"") -> 40.22 | I59: =IFERROR(VLOOKUP(D59,'02_FX_Rates'!$A$5:$B$10,2,FALSE),IFERROR(LOOKUP(2,1/('04_Trades'!$E$5:$E$1004=B59),'04_Trades'!$J$5:$J$1004),"")) -> 1 | J59: =IF(OR(B59="",G59="",H59=""),"",G59*H59) -> 4987.28 | K59: =IF(OR(B59="",J59="",I59=""),"",J59*I59) -> 4987.28 | L59: =IFERROR(SUMIFS('04_Trades'!$K$5:$K$1004,'04_Trades'!$E$5:$E$1004,B59,'04_Trades'!$C$5:$C$1004,"BUY")/SUMIFS('04_Trades'!$G$5:$G$1004,'04_Trades'!$E$5:$E$1004,B59,'04_Trades'!$C$5:$C$1004,"BUY"),"") -> 39.275484 | M59: =IF(OR(B59="",G59=0,K59="",L59=""),"",K59-G59*L59) -> 117.12 | N59: 40.22 | O59: =IFERROR(IF(N59="","",G59*N59*I59),"") -> 4987.28 | P59: =IFERROR(IF(OR(N59="",G59=0,L59=""),"",O59-G59*L59),"") -> 117.12
A60: TOTALE | K60: =SUM(K5:K59) -> 1084431.3 | M60: =SUM(M5:M59) -> -15933.563 | N60: TOTALE | O60: =SUM(O5:O59) -> 1069752.7 | P60: =SUM(P5:P59) -> -30612.134

Sheet 10_NAV_Mensile
A1: NAV Mensile
A2: Inserire la data fine mese in colonna B. Le formule calcolano cassa e NAV (modello al LORDO delle imposte). Per la valutazione di portafoglio quotato, partecipazioni e prestiti in date passate, inserire un override EUR (colonne J-L). Se vuoto, viene usato il costo storico.
A4: # | B4: Data Fine Mese | C4: Capitale Cum. | D4: Net Trade Cum. | E4: Div/Int Lordi Cum. | F4: Part. Net Cum. | G4: Loan Net Cum. | H4: P/L Op. Cum. | I4: Cassa | J4: Listed MV (override) | K4: Part. MV (override) | L4: Loan Outst. (override) | M4: NAV | N4: Quote Outst. | O4: NAV/Unit | P4: Ritorno Mensile
A5: =IF(B5="","",ROW()-4) -> 1 | B5: 45688 | C5: =IF(B5="","",SUMIFS('03_Investitori'!$H$5:$H$104,'03_Investitori'!$C$5:$C$104,"<="&B5)) -> 0 | D5: =IF(B5="","",SUMIFS('04_Trades'!$K$5:$K$1004,'04_Trades'!$C$5:$C$1004,"BUY",'04_Trades'!$B$5:$B$1004,"<="&B5)-SUMIFS('04_Trades'!$K$5:$K$1004,'04_Trades'!$C$5:$C$1004,"SELL",'04_Trades'!$B$5:$B$1004,"<="&B5)) -> 9380.8287 | E5: =IF(B5="","",SUMIFS('05_Dividendi_Interessi'!$I$5:$I$504,'05_Dividendi_Interessi'!$B$5:$B$504,"<="&B5)) -> 0 | F5: =IF(B5="","",SUMIFS('06_Partecipazioni'!$I$5:$I$204,'06_Partecipazioni'!$C$5:$C$204,"BUY",'06_Partecipazioni'!$B$5:$B$204,"<="&B5)-SUMIFS('06_Partecipazioni'!$I$5:$I$204,'06_Partecipazioni'!$C$5:$C$204,"SELL",'06_Partecipazioni'!$B$5:$B$204,"<="&B5)) -> 0 | G5: =IF(B5="","",SUMIFS('07_Prestiti'!$H$5:$H$204,'07_Prestiti'!$C$5:$C$204,"DISBURSEMENT",'07_Prestiti'!$B$5:$B$204,"<="&B5)-SUMIFS('07_Prestiti'!$H$5:$H$204,'07_Prestiti'!$C$5:$C$204,"REPAYMENT",'07_Prestiti'!$B$5:$B$204,"<="&B5)) -> 0 | H5: =IF(B5="","",SUMIFS('08_PL_Operativa'!$H$5:$H$503,'08_PL_Operativa'!$B$5:$B$503,"<="&B5)) -> -4.7 | I5: =IF(B5="","",C5-D5+E5-F5-G5+H5) -> -9385.5287 | M5: =IF(B5="","",I5+IF(AND(MONTH(B5)=MONTH(DataOggi),YEAR(B5)=YEAR(DataOggi)),MV_Listed_Tot,IF(J5="",D5,J5))+IF(K5="",F5,K5)+IF(L5="",G5,L5)) -> -4.7 | N5: =IF(B5="","",SUMIFS('03_Investitori'!$J$5:$J$104,'03_Investitori'!$C$5:$C$104,"<="&B5)) -> 0 | O5: =IF(OR(B5="",N5=0,N5=""),"",M5/N5)
A6: =IF(B6="","",ROW()-4) -> 2 | B6: 45716 | C6: =IF(B6="","",SUMIFS('03_Investitori'!$H$5:$H$104,'03_Investitori'!$C$5:$C$104,"<="&B6)) -> 0 | D6: =IF(B6="","",SUMIFS('04_Trades'!$K$5:$K$1004,'04_Trades'!$C$5:$C$1004,"BUY",'04_Trades'!$B$5:$B$1004,"<="&B6)-SUMIFS('04_Trades'!$K$5:$K$1004,'04_Trades'!$C$5:$C$1004,"SELL",'04_Trades'!$B$5:$B$1004,"<="&B6)) -> 9380.8287 | E6: =IF(B6="","",SUMIFS('05_Dividendi_Interessi'!$I$5:$I$504,'05_Dividendi_Interessi'!$B$5:$B$504,"<="&B6)) -> 0 | F6: =IF(B6="","",SUMIFS('06_Partecipazioni'!$I$5:$I$204,'06_Partecipazioni'!$C$5:$C$204,"BUY",'06_Partecipazioni'!$B$5:$B$204,"<="&B6)-SUMIFS('06_Partecipazioni'!$I$5:$I$204,'06_Partecipazioni'!$C$5:$C$204,"SELL",'06_Partecipazioni'!$B$5:$B$204,"<="&B6)) -> 0 | G6: =IF(B6="","",SUMIFS('07_Prestiti'!$H$5:$H$204,'07_Prestiti'!$C$5:$C$204,"DISBURSEMENT",'07_Prestiti'!$B$5:$B$204,"<="&B6)-SUMIFS('07_Prestiti'!$H$5:$H$204,'07_Prestiti'!$C$5:$C$204,"REPAYMENT",'07_Prestiti'!$B$5:$B$204,"<="&B6)) -> 0 | H6: =IF(B6="","",SUMIFS('08_PL_Operativa'!$H$5:$H$503,'08_PL_Operativa'!$B$5:$B$503,"<="&B6)) -> -4.7 | I6: =IF(B6="","",C6-D6+E6-F6-G6+H6) -> -9385.5287 | M6: =IF(B6="","",I6+IF(AND(MONTH(B6)=MONTH(DataOggi),YEAR(B6)=YEAR(DataOggi)),MV_Listed_Tot,IF(J6="",D6,J6))+IF(K6="",F6,K6)+IF(L6="",G6,L6)) -> -4.7 | N6: =IF(B6="","",SUMIFS('03_Investitori'!$J$5:$J$104,'03_Investitori'!$C$5:$C$104,"<="&B6)) -> 0 | O6: =IF(OR(B6="",N6=0,N6=""),"",M6/N6) | P6: =IFERROR(IF(OR(B6="",O5=""),"",O6/O5-1),"")
A7: =IF(B7="","",ROW()-4) -> 3 | B7: 45747 | C7: =IF(B7="","",SUMIFS('03_Investitori'!$H$5:$H$104,'03_Investitori'!$C$5:$C$104,"<="&B7)) -> 500000 | D7: =IF(B7="","",SUMIFS('04_Trades'!$K$5:$K$1004,'04_Trades'!$C$5:$C$1004,"BUY",'04_Trades'!$B$5:$B$1004,"<="&B7)-SUMIFS('04_Trades'!$K$5:$K$1004,'04_Trades'!$C$5:$C$1004,"SELL",'04_Trades'!$B$5:$B$1004,"<="&B7)) -> 9380.8287 | E7: =IF(B7="","",SUMIFS('05_Dividendi_Interessi'!$I$5:$I$504,'05_Dividendi_Interessi'!$B$5:$B$504,"<="&B7)) -> 0 | F7: =IF(B7="","",SUMIFS('06_Partecipazioni'!$I$5:$I$204,'06_Partecipazioni'!$C$5:$C$204,"BUY",'06_Partecipazioni'!$B$5:$B$204,"<="&B7)-SUMIFS('06_Partecipazioni'!$I$5:$I$204,'06_Partecipazioni'!$C$5:$C$204,"SELL",'06_Partecipazioni'!$B$5:$B$204,"<="&B7)) -> 0 | G7: =IF(B7="","",SUMIFS('07_Prestiti'!$H$5:$H$204,'07_Prestiti'!$C$5:$C$204,"DISBURSEMENT",'07_Prestiti'!$B$5:$B$204,"<="&B7)-SUMIFS('07_Prestiti'!$H$5:$H$204,'07_Prestiti'!$C$5:$C$204,"REPAYMENT",'07_Prestiti'!$B$5:$B$204,"<="&B7)) -> 0 | H7: =IF(B7="","",SUMIFS('08_PL_Operativa'!$H$5:$H$503,'08_PL_Operativa'!$B$5:$B$503,"<="&B7)) -> -4.7 | I7: =IF(B7="","",C7-D7+E7-F7-G7+H7) -> 490614.47 | M7: =IF(B7="","",I7+IF(AND(MONTH(B7)=MONTH(DataOggi),YEAR(B7)=YEAR(DataOggi)),MV_Listed_Tot,IF(J7="",D7,J7))+IF(K7="",F7,K7)+IF(L7="",G7,L7)) -> 499995.3 | N7: =IF(B7="","",SUMIFS('03_Investitori'!$J$5:$J$104,'03_Investitori'!$C$5:$C$104,"<="&B7)) -> 500000 | O7: =IF(OR(B7="",N7=0,N7=""),"",M7/N7) -> 0.9999906 | P7: =IFERROR(IF(OR(B7="",O6=""),"",O7/O6-1),"")
A8: =IF(B8="","",ROW()-4) -> 4 | B8: 45777 | C8: =IF(B8="","",SUMIFS('03_Investitori'!$H$5:$H$104,'03_Investitori'!$C$5:$C$104,"<="&B8)) -> 500000 | D8: =IF(B8="","",SUMIFS('04_Trades'!$K$5:$K$1004,'04_Trades'!$C$5:$C$1004,"BUY",'04_Trades'!$B$5:$B$1004,"<="&B8)-SUMIFS('04_Trades'!$K$5:$K$1004,'04_Trades'!$C$5:$C$1004,"SELL",'04_Trades'!$B$5:$B$1004,"<="&B8)) -> 9380.8287 | E8: =IF(B8="","",SUMIFS('05_Dividendi_Interessi'!$I$5:$I$504,'05_Dividendi_Interessi'!$B$5:$B$504,"<="&B8)) -> 0 | F8: =IF(B8="","",SUMIFS('06_Partecipazioni'!$I$5:$I$204,'06_Partecipazioni'!$C$5:$C$204,"BUY",'06_Partecipazioni'!$B$5:$B$204,"<="&B8)-SUMIFS('06_Partecipazioni'!$I$5:$I$204,'06_Partecipazioni'!$C$5:$C$204,"SELL",'06_Partecipazioni'!$B$5:$B$204,"<="&B8)) -> 0 | G8: =IF(B8="","",SUMIFS('07_Prestiti'!$H$5:$H$204,'07_Prestiti'!$C$5:$C$204,"DISBURSEMENT",'07_Prestiti'!$B$5:$B$204,"<="&B8)-SUMIFS('07_Prestiti'!$H$5:$H$204,'07_Prestiti'!$C$5:$C$204,"REPAYMENT",'07_Prestiti'!$B$5:$B$204,"<="&B8)) -> 0 | H8: =IF(B8="","",SUMIFS('08_PL_Operativa'!$H$5:$H$503,'08_PL_Operativa'!$B$5:$B$503,"<="&B8)) -> -4.7 | I8: =IF(B8="","",C8-D8+E8-F8-G8+H8) -> 490614.47 | M8: =IF(B8="","",I8+IF(AND(MONTH(B8)=MONTH(DataOggi),YEAR(B8)=YEAR(DataOggi)),MV_Listed_Tot,IF(J8="",D8,J8))+IF(K8="",F8,K8)+IF(L8="",G8,L8)) -> 499995.3 | N8: =IF(B8="","",SUMIFS('03_Investitori'!$J$5:$J$104,'03_Investitori'!$C$5:$C$104,"<="&B8)) -> 500000 | O8: =IF(OR(B8="",N8=0,N8=""),"",M8/N8) -> 0.9999906 | P8: =IFERROR(IF(OR(B8="",O7=""),"",O8/O7-1),"") -> 0
A9: =IF(B9="","",ROW()-4) -> 5 | B9: 45808 | C9: =IF(B9="","",SUMIFS('03_Investitori'!$H$5:$H$104,'03_Investitori'!$C$5:$C$104,"<="&B9)) -> 500000 | D9: =IF(B9="","",SUMIFS('04_Trades'!$K$5:$K$1004,'04_Trades'!$C$5:$C$1004,"BUY",'04_Trades'!$B$5:$B$1004,"<="&B9)-SUMIFS('04_Trades'!$K$5:$K$1004,'04_Trades'!$C$5:$C$1004,"SELL",'04_Trades'!$B$5:$B$1004,"<="&B9)) -> 39930.829 | E9: =IF(B9="","",SUMIFS('05_Dividendi_Interessi'!$I$5:$I$504,'05_Dividendi_Interessi'!$B$5:$B$504,"<="&B9)) -> 0 | F9: =IF(B9="","",SUMIFS('06_Partecipazioni'!$I$5:$I$204,'06_Partecipazioni'!$C$5:$C$204,"BUY",'06_Partecipazioni'!$B$5:$B$204,"<="&B9)-SUMIFS('06_Partecipazioni'!$I$5:$I$204,'06_Partecipazioni'!$C$5:$C$204,"SELL",'06_Partecipazioni'!$B$5:$B$204,"<="&B9)) -> 0 | G9: =IF(B9="","",SUMIFS('07_Prestiti'!$H$5:$H$204,'07_Prestiti'!$C$5:$C$204,"DISBURSEMENT",'07_Prestiti'!$B$5:$B$204,"<="&B9)-SUMIFS('07_Prestiti'!$H$5:$H$204,'07_Prestiti'!$C$5:$C$204,"REPAYMENT",'07_Prestiti'!$B$5:$B$204,"<="&B9)) -> 0 | H9: =IF(B9="","",SUMIFS('08_PL_Operativa'!$H$5:$H$503,'08_PL_Operativa'!$B$5:$B$503,"<="&B9)) -> -4.7 | I9: =IF(B9="","",C9-D9+E9-F9-G9+H9) -> 460064.47 | M9: =IF(B9="","",I9+IF(AND(MONTH(B9)=MONTH(DataOggi),YEAR(B9)=YEAR(DataOggi)),MV_Listed_Tot,IF(J9="",D9,J9))+IF(K9="",F9,K9)+IF(L9="",G9,L9)) -> 499995.3 | N9: =IF(B9="","",SUMIFS('03_Investitori'!$J$5:$J$104,'03_Investitori'!$C$5:$C$104,"<="&B9)) -> 500000 | O9: =IF(OR(B9="",N9=0,N9=""),"",M9/N9) -> 0.9999906 | P9: =IFERROR(IF(OR(B9="",O8=""),"",O9/O8-1),"") -> 0
A10: =IF(B10="","",ROW()-4) -> 6 | B10: 45838 | C10: =IF(B10="","",SUMIFS('03_Investitori'!$H$5:$H$104,'03_Investitori'!$C$5:$C$104,"<="&B10)) -> 500000 | D10: =IF(B10="","",SUMIFS('04_Trades'!$K$5:$K$1004,'04_Trades'!$C$5:$C$1004,"BUY",'04_Trades'!$B$5:$B$1004,"<="&B10)-SUMIFS('04_Trades'!$K$5:$K$1004,'04_Trades'!$C$5:$C$1004,"SELL",'04_Trades'!$B$5:$B$1004,"<="&B10)) -> 40911.589 | E10: =IF(B10="","",SUMIFS('05_Dividendi_Interessi'!$I$5:$I$504,'05_Dividendi_Interessi'!$B$5:$B$504,"<="&B10)) -> 0 | F10: =IF(B10="","",SUMIFS('06_Partecipazioni'!$I$5:$I$204,'06_Partecipazioni'!$C$5:$C$204,"BUY",'06_Partecipazioni'!$B$5:$B$204,"<="&B10)-SUMIFS('06_Partecipazioni'!$I$5:$I$204,'06_Partecipazioni'!$C$5:$C$204,"SELL",'06_Partecipazioni'!$B$5:$B$204,"<="&B10)) -> 0 | G10: =IF(B10="","",SUMIFS('07_Prestiti'!$H$5:$H$204,'07_Prestiti'!$C$5:$C$204,"DISBURSEMENT",'07_Prestiti'!$B$5:$B$204,"<="&B10)-SUMIFS('07_Prestiti'!$H$5:$H$204,'07_Prestiti'!$C$5:$C$204,"REPAYMENT",'07_Prestiti'!$B$5:$B$204,"<="&B10)) -> 0 | H10: =IF(B10="","",SUMIFS('08_PL_Operativa'!$H$5:$H$503,'08_PL_Operativa'!$B$5:$B$503,"<="&B10)) -> -4.7 | I10: =IF(B10="","",C10-D10+E10-F10-G10+H10) -> 459083.71 | M10: =IF(B10="","",I10+IF(AND(MONTH(B10)=MONTH(DataOggi),YEAR(B10)=YEAR(DataOggi)),MV_Listed_Tot,IF(J10="",D10,J10))+IF(K10="",F10,K10)+IF(L10="",G10,L10)) -> 499995.3 | N10: =IF(B10="","",SUMIFS('03_Investitori'!$J$5:$J$104,'03_Investitori'!$C$5:$C$104,"<="&B10)) -> 500000 | O10: =IF(OR(B10="",N10=0,N10=""),"",M10/N10) -> 0.9999906 | P10: =IFERROR(IF(OR(B10="",O9=""),"",O10/O9-1),"") -> 0
A11: =IF(B11="","",ROW()-4) -> 7 | B11: 45869 | C11: =IF(B11="","",SUMIFS('03_Investitori'!$H$5:$H$104,'03_Investitori'!$C$5:$C$104,"<="&B11)) -> 500000 | D11: =IF(B11="","",SUMIFS('04_Trades'!$K$5:$K$1004,'04_Trades'!$C$5:$C$1004,"BUY",'04_Trades'!$B$5:$B$1004,"<="&B11)-SUMIFS('04_Trades'!$K$5:$K$1004,'04_Trades'!$C$5:$C$1004,"SELL",'04_Trades'!$B$5:$B$1004,"<="&B11)) -> 311135.69 | E11: =IF(B11="","",SUMIFS('05_Dividendi_Interessi'!$I$5:$I$504,'05_Dividendi_Interessi'!$B$5:$B$504,"<="&B11)) -> 8.55 | F11: =IF(B11="","",SUMIFS('06_Partecipazioni'!$I$5:$I$204,'06_Partecipazioni'!$C$5:$C$204,"BUY",'06_Partecipazioni'!$B$5:$B$204,"<="&B11)-SUMIFS('06_Partecipazioni'!$I$5:$I$204,'06_Partecipazioni'!$C$5:$C$204,"SELL",'06_Partecipazioni'!$B$5:$B$204,"<="&B11)) -> 0 | G11: =IF(B11="","",SUMIFS('07_Prestiti'!$H$5:$H$204,'07_Prestiti'!$C$5:$C$204,"DISBURSEMENT",'07_Prestiti'!$B$5:$B$204,"<="&B11)-SUMIFS('07_Prestiti'!$H$5:$H$204,'07_Prestiti'!$C$5:$C$204,"REPAYMENT",'07_Prestiti'!$B$5:$B$204,"<="&B11)) -> 0 | H11: =IF(B11="","",SUMIFS('08_PL_Operativa'!$H$5:$H$503,'08_PL_Operativa'!$B$5:$B$503,"<="&B11)) -> -338.76 | I11: =IF(B11="","",C11-D11+E11-F11-G11+H11) -> 188534.1 | M11: =IF(B11="","",I11+IF(AND(MONTH(B11)=MONTH(DataOggi),YEAR(B11)=YEAR(DataOggi)),MV_Listed_Tot,IF(J11="",D11,J11))+IF(K11="",F11,K11)+IF(L11="",G11,L11)) -> 499669.79 | N11: =IF(B11="","",SUMIFS('03_Investitori'!$J$5:$J$104,'03_Investitori'!$C$5:$C$104,"<="&B11)) -> 500000 | O11: =IF(OR(B11="",N11=0,N11=""),"",M11/N11) -> 0.99933958 | P11: =IFERROR(IF(OR(B11="",O10=""),"",O11/O10-1),"") -> -0.00065102612
A12: =IF(B12="","",ROW()-4) -> 8 | B12: 45900 | C12: =IF(B12="","",SUMIFS('03_Investitori'!$H$5:$H$104,'03_Investitori'!$C$5:$C$104,"<="&B12)) -> 500000 | D12: =IF(B12="","",SUMIFS('04_Trades'!$K$5:$K$1004,'04_Trades'!$C$5:$C$1004,"BUY",'04_Trades'!$B$5:$B$1004,"<="&B12)-SUMIFS('04_Trades'!$K$5:$K$1004,'04_Trades'!$C$5:$C$1004,"SELL",'04_Trades'!$B$5:$B$1004,"<="&B12)) -> 432125.45 | E12: =IF(B12="","",SUMIFS('05_Dividendi_Interessi'!$I$5:$I$504,'05_Dividendi_Interessi'!$B$5:$B$504,"<="&B12)) -> 43.67 | F12: =IF(B12="","",SUMIFS('06_Partecipazioni'!$I$5:$I$204,'06_Partecipazioni'!$C$5:$C$204,"BUY",'06_Partecipazioni'!$B$5:$B$204,"<="&B12)-SUMIFS('06_Partecipazioni'!$I$5:$I$204,'06_Partecipazioni'!$C$5:$C$204,"SELL",'06_Partecipazioni'!$B$5:$B$204,"<="&B12)) -> 0 | G12: =IF(B12="","",SUMIFS('07_Prestiti'!$H$5:$H$204,'07_Prestiti'!$C$5:$C$204,"DISBURSEMENT",'07_Prestiti'!$B$5:$B$204,"<="&B12)-SUMIFS('07_Prestiti'!$H$5:$H$204,'07_Prestiti'!$C$5:$C$204,"REPAYMENT",'07_Prestiti'!$B$5:$B$204,"<="&B12)) -> 0 | H12: =IF(B12="","",SUMIFS('08_PL_Operativa'!$H$5:$H$503,'08_PL_Operativa'!$B$5:$B$503,"<="&B12)) -> -359.39 | I12: =IF(B12="","",C12-D12+E12-F12-G12+H12) -> 67558.829 | M12: =IF(B12="","",I12+IF(AND(MONTH(B12)=MONTH(DataOggi),YEAR(B12)=YEAR(DataOggi)),MV_Listed_Tot,IF(J12="",D12,J12))+IF(K12="",F12,K12)+IF(L12="",G12,L12)) -> 499684.28 | N12: =IF(B12="","",SUMIFS('03_Investitori'!$J$5:$J$104,'03_Investitori'!$C$5:$C$104,"<="&B12)) -> 500000 | O12: =IF(OR(B12="",N12=0,N12=""),"",M12/N12) -> 0.99936856 | P12: =IFERROR(IF(OR(B12="",O11=""),"",O12/O11-1),"") -> 2.8999152e-05
A13: =IF(B13="","",ROW()-4) -> 9 | B13: 45930 | C13: =IF(B13="","",SUMIFS('03_Investitori'!$H$5:$H$104,'03_Investitori'!$C$5:$C$104,"<="&B13)) -> 1500000 | D13: =IF(B13="","",SUMIFS('04_Trades'!$K$5:$K$1004,'04_Trades'!$C$5:$C$1004,"BUY",'04_Trades'!$B$5:$B$1004,"<="&B13)-SUMIFS('04_Trades'!$K$5:$K$1004,'04_Trades'!$C$5:$C$1004,"SELL",'04_Trades'!$B$5:$B$1004,"<="&B13)) -> 605733.76 | E13: =IF(B13="","",SUMIFS('05_Dividendi_Interessi'!$I$5:$I$504,'05_Dividendi_Interessi'!$B$5:$B$504,"<="&B13)) -> 1698 | F13: =IF(B13="","",SUMIFS('06_Partecipazioni'!$I$5:$I$204,'06_Partecipazioni'!$C$5:$C$204,"BUY",'06_Partecipazioni'!$B$5:$B$204,"<="&B13)-SUMIFS('06_Partecipazioni'!$I$5:$I$204,'06_Partecipazioni'!$C$5:$C$204,"SELL",'06_Partecipazioni'!$B$5:$B$204,"<="&B13)) -> 0 | G13: =IF(B13="","",SUMIFS('07_Prestiti'!$H$5:$H$204,'07_Prestiti'!$C$5:$C$204,"DISBURSEMENT",'07_Prestiti'!$B$5:$B$204,"<="&B13)-SUMIFS('07_Prestiti'!$H$5:$H$204,'07_Prestiti'!$C$5:$C$204,"REPAYMENT",'07_Prestiti'!$B$5:$B$204,"<="&B13)) -> 0 | H13: =IF(B13="","",SUMIFS('08_PL_Operativa'!$H$5:$H$503,'08_PL_Operativa'!$B$5:$B$503,"<="&B13)) -> -577.18 | I13: =IF(B13="","",C13-D13+E13-F13-G13+H13) -> 895387.06 | M13: =IF(B13="","",I13+IF(AND(MONTH(B13)=MONTH(DataOggi),YEAR(B13)=YEAR(DataOggi)),MV_Listed_Tot,IF(J13="",D13,J13))+IF(K13="",F13,K13)+IF(L13="",G13,L13)) -> 1501120.8 | N13: =IF(B13="","",SUMIFS('03_Investitori'!$J$5:$J$104,'03_Investitori'!$C$5:$C$104,"<="&B13)) -> 1500000 | O13: =IF(OR(B13="",N13=0,N13=""),"",M13/N13) -> 1.0007472 | P13: =IFERROR(IF(OR(B13="",O12=""),"",O13/O12-1),"") -> 0.0013795244
A14: =IF(B14="","",ROW()-4) -> 10 | B14: 45961 | C14: =IF(B14="","",SUMIFS('03_Investitori'!$H$5:$H$104,'03_Investitori'!$C$5:$C$104,"<="&B14)) -> 1500000 | D14: =IF(B14="","",SUMIFS('04_Trades'!$K$5:$K$1004,'04_Trades'!$C$5:$C$1004,"BUY",'04_Trades'!$B$5:$B$1004,"<="&B14)-SUMIFS('04_Trades'!$K$5:$K$1004,'04_Trades'!$C$5:$C$1004,"SELL",'04_Trades'!$B$5:$B$1004,"<="&B14)) -> 860981.97 | E14: =IF(B14="","",SUMIFS('05_Dividendi_Interessi'!$I$5:$I$504,'05_Dividendi_Interessi'!$B$5:$B$504,"<="&B14)) -> 2243.12 | F14: =IF(B14="","",SUMIFS('06_Partecipazioni'!$I$5:$I$204,'06_Partecipazioni'!$C$5:$C$204,"BUY",'06_Partecipazioni'!$B$5:$B$204,"<="&B14)-SUMIFS('06_Partecipazioni'!$I$5:$I$204,'06_Partecipazioni'!$C$5:$C$204,"SELL",'06_Partecipazioni'!$B$5:$B$204,"<="&B14)) -> 135000 | G14: =IF(B14="","",SUMIFS('07_Prestiti'!$H$5:$H$204,'07_Prestiti'!$C$5:$C$204,"DISBURSEMENT",'07_Prestiti'!$B$5:$B$204,"<="&B14)-SUMIFS('07_Prestiti'!$H$5:$H$204,'07_Prestiti'!$C$5:$C$204,"REPAYMENT",'07_Prestiti'!$B$5:$B$204,"<="&B14)) -> 15000 | H14: =IF(B14="","",SUMIFS('08_PL_Operativa'!$H$5:$H$503,'08_PL_Operativa'!$B$5:$B$503,"<="&B14)) -> -1106.95 | I14: =IF(B14="","",C14-D14+E14-F14-G14+H14) -> 490154.2 | M14: =IF(B14="","",I14+IF(AND(MONTH(B14)=MONTH(DataOggi),YEAR(B14)=YEAR(DataOggi)),MV_Listed_Tot,IF(J14="",D14,J14))+IF(K14="",F14,K14)+IF(L14="",G14,L14)) -> 1501136.2 | N14: =IF(B14="","",SUMIFS('03_Investitori'!$J$5:$J$104,'03_Investitori'!$C$5:$C$104,"<="&B14)) -> 1500000 | O14: =IF(OR(B14="",N14=0,N14=""),"",M14/N14) -> 1.0007574 | P14: =IFERROR(IF(OR(B14="",O13=""),"",O14/O13-1),"") -> 1.0225693e-05
A15: =IF(B15="","",ROW()-4) -> 11 | B15: 45991 | C15: =IF(B15="","",SUMIFS('03_Investitori'!$H$5:$H$104,'03_Investitori'!$C$5:$C$104,"<="&B15)) -> 1500000 | D15: =IF(B15="","",SUMIFS('04_Trades'!$K$5:$K$1004,'04_Trades'!$C$5:$C$1004,"BUY",'04_Trades'!$B$5:$B$1004,"<="&B15)-SUMIFS('04_Trades'!$K$5:$K$1004,'04_Trades'!$C$5:$C$1004,"SELL",'04_Trades'!$B$5:$B$1004,"<="&B15)) -> 824469.42 | E15: =IF(B15="","",SUMIFS('05_Dividendi_Interessi'!$I$5:$I$504,'05_Dividendi_Interessi'!$B$5:$B$504,"<="&B15)) -> 2580.3 | F15: =IF(B15="","",SUMIFS('06_Partecipazioni'!$I$5:$I$204,'06_Partecipazioni'!$C$5:$C$204,"BUY",'06_Partecipazioni'!$B$5:$B$204,"<="&B15)-SUMIFS('06_Partecipazioni'!$I$5:$I$204,'06_Partecipazioni'!$C$5:$C$204,"SELL",'06_Partecipazioni'!$B$5:$B$204,"<="&B15)) -> 135000 | G15: =IF(B15="","",SUMIFS('07_Prestiti'!$H$5:$H$204,'07_Prestiti'!$C$5:$C$204,"DISBURSEMENT",'07_Prestiti'!$B$5:$B$204,"<="&B15)-SUMIFS('07_Prestiti'!$H$5:$H$204,'07_Prestiti'!$C$5:$C$204,"REPAYMENT",'07_Prestiti'!$B$5:$B$204,"<="&B15)) -> 15000 | H15: =IF(B15="","",SUMIFS('08_PL_Operativa'!$H$5:$H$503,'08_PL_Operativa'!$B$5:$B$503,"<="&B15)) -> -1106.95 | I15: =IF(B15="","",C15-D15+E15-F15-G15+H15) -> 527003.93 | M15: =IF(B15="","",I15+IF(AND(MONTH(B15)=MONTH(DataOggi),YEAR(B15)=YEAR(DataOggi)),MV_Listed_Tot,IF(J15="",D15,J15))+IF(K15="",F15,K15)+IF(L15="",G15,L15)) -> 1501473.4 | N15: =IF(B15="","",SUMIFS('03_Investitori'!$J$5:$J$104,'03_Investitori'!$C$5:$C$104,"<="&B15)) -> 1500000 | O15: =IF(OR(B15="",N15=0,N15=""),"",M15/N15) -> 1.0009822 | P15: =IFERROR(IF(OR(B15="",O14=""),"",O15/O14-1),"") -> 0.00022461653
A16: =IF(B16="","",ROW()-4) -> 12 | B16: 46022 | C16: =IF(B16="","",SUMIFS('03_Investitori'!$H$5:$H$104,'03_Investitori'!$C$5:$C$104,"<="&B16)) -> 1500000 | D16: =IF(B16="","",SUMIFS('04_Trades'!$K$5:$K$1004,'04_Trades'!$C$5:$C$1004,"BUY",'04_Trades'!$B$5:$B$1004,"<="&B16)-SUMIFS('04_Trades'!$K$5:$K$1004,'04_Trades'!$C$5:$C$1004,"SELL",'04_Trades'!$B$5:$B$1004,"<="&B16)) -> 830035.89 | E16: =IF(B16="","",SUMIFS('05_Dividendi_Interessi'!$I$5:$I$504,'05_Dividendi_Interessi'!$B$5:$B$504,"<="&B16)) -> 2580.3 | F16: =IF(B16="","",SUMIFS('06_Partecipazioni'!$I$5:$I$204,'06_Partecipazioni'!$C$5:$C$204,"BUY",'06_Partecipazioni'!$B$5:$B$204,"<="&B16)-SUMIFS('06_Partecipazioni'!$I$5:$I$204,'06_Partecipazioni'!$C$5:$C$204,"SELL",'06_Partecipazioni'!$B$5:$B$204,"<="&B16)) -> 165000 | G16: =IF(B16="","",SUMIFS('07_Prestiti'!$H$5:$H$204,'07_Prestiti'!$C$5:$C$204,"DISBURSEMENT",'07_Prestiti'!$B$5:$B$204,"<="&B16)-SUMIFS('07_Prestiti'!$H$5:$H$204,'07_Prestiti'!$C$5:$C$204,"REPAYMENT",'07_Prestiti'!$B$5:$B$204,"<="&B16)) -> 60000 | H16: =IF(B16="","",SUMIFS('08_PL_Operativa'!$H$5:$H$503,'08_PL_Operativa'!$B$5:$B$503,"<="&B16)) -> -76224.82 | I16: =IF(B16="","",C16-D16+E16-F16-G16+H16) -> 371319.59 | M16: =IF(B16="","",I16+IF(AND(MONTH(B16)=MONTH(DataOggi),YEAR(B16)=YEAR(DataOggi)),MV_Listed_Tot,IF(J16="",D16,J16))+IF(K16="",F16,K16)+IF(L16="",G16,L16)) -> 1426355.5 | N16: =IF(B16="","",SUMIFS('03_Investitori'!$J$5:$J$104,'03_Investitori'!$C$5:$C$104,"<="&B16)) -> 1500000 | O16: =IF(OR(B16="",N16=0,N16=""),"",M16/N16) -> 0.95090365 | P16: =IFERROR(IF(OR(B16="",O15=""),"",O16/O15-1),"") -> -0.050029439
A17: =IF(B17="","",ROW()-4) -> 13 | B17: 46053 | C17: =IF(B17="","",SUMIFS('03_Investitori'!$H$5:$H$104,'03_Investitori'!$C$5:$C$104,"<="&B17)) -> 1500000 | D17: =IF(B17="","",SUMIFS('04_Trades'!$K$5:$K$1004,'04_Trades'!$C$5:$C$1004,"BUY",'04_Trades'!$B$5:$B$1004,"<="&B17)-SUMIFS('04_Trades'!$K$5:$K$1004,'04_Trades'!$C$5:$C$1004,"SELL",'04_Trades'!$B$5:$B$1004,"<="&B17)) -> 833535.11 | E17: =IF(B17="","",SUMIFS('05_Dividendi_Interessi'!$I$5:$I$504,'05_Dividendi_Interessi'!$B$5:$B$504,"<="&B17)) -> 3470.07 | F17: =IF(B17="","",SUMIFS('06_Partecipazioni'!$I$5:$I$204,'06_Partecipazioni'!$C$5:$C$204,"BUY",'06_Partecipazioni'!$B$5:$B$204,"<="&B17)-SUMIFS('06_Partecipazioni'!$I$5:$I$204,'06_Partecipazioni'!$C$5:$C$204,"SELL",'06_Partecipazioni'!$B$5:$B$204,"<="&B17)) -> 165000 | G17: =IF(B17="","",SUMIFS('07_Prestiti'!$H$5:$H$204,'07_Prestiti'!$C$5:$C$204,"DISBURSEMENT",'07_Prestiti'!$B$5:$B$204,"<="&B17)-SUMIFS('07_Prestiti'!$H$5:$H$204,'07_Prestiti'!$C$5:$C$204,"REPAYMENT",'07_Prestiti'!$B$5:$B$204,"<="&B17)) -> 70000 | H17: =IF(B17="","",SUMIFS('08_PL_Operativa'!$H$5:$H$503,'08_PL_Operativa'!$B$5:$B$503,"<="&B17)) -> -76842.59 | I17: =IF(B17="","",C17-D17+E17-F17-G17+H17) -> 358092.37 | M17: =IF(B17="","",I17+IF(AND(MONTH(B17)=MONTH(DataOggi),YEAR(B17)=YEAR(DataOggi)),MV_Listed_Tot,IF(J17="",D17,J17))+IF(K17="",F17,K17)+IF(L17="",G17,L17)) -> 1426627.5 | N17: =IF(B17="","",SUMIFS('03_Investitori'!$J$5:$J$104,'03_Investitori'!$C$5:$C$104,"<="&B17)) -> 1500000 | O17: =IF(OR(B17="",N17=0,N17=""),"",M17/N17) -> 0.95108499 | P17: =IFERROR(IF(OR(B17="",O16=""),"",O17/O16-1),"") -> 0.0001906958
... A20: =IF(B20="","",ROW()-4) -> 16 | B20: 46142 | C20: =IF(B20="","",SUMIFS('03_Investitori'!$H$5:$H$104,'03_Investitori'!$C$5:$C$104,"<="&B20)) -> 2000000 | D20: =IF(B20="","",SUMIFS('04_Trades'!$K$5:$K$1004,'04_Trades'!$C$5:$C$1004,"BUY",'04_Trades'!$B$5:$B$1004,"<="&B20)-SUMIFS('04_Trades'!$K$5:$K$1004,'04_Trades'!$C$5:$C$1004,"SELL",'04_Trades'!$B$5:$B$1004,"<="&B20)) -> 1082225.7 | E20: =IF(B20="","",SUMIFS('05_Dividendi_Interessi'!$I$5:$I$504,'05_Dividendi_Interessi'!$B$5:$B$504,"<="&B20)) -> 8226.2 | F20: =IF(B20="","",SUMIFS('06_Partecipazioni'!$I$5:$I$204,'06_Partecipazioni'!$C$5:$C$204,"BUY",'06_Partecipazioni'!$B$5:$B$204,"<="&B20)-SUMIFS('06_Partecipazioni'!$I$5:$I$204,'06_Partecipazioni'!$C$5:$C$204,"SELL",'06_Partecipazioni'!$B$5:$B$204,"<="&B20)) -> 165000 | G20: =IF(B20="","",SUMIFS('07_Prestiti'!$H$5:$H$204,'07_Prestiti'!$C$5:$C$204,"DISBURSEMENT",'07_Prestiti'!$B$5:$B$204,"<="&B20)-SUMIFS('07_Prestiti'!$H$5:$H$204,'07_Prestiti'!$C$5:$C$204,"REPAYMENT",'07_Prestiti'!$B$5:$B$204,"<="&B20)) -> 135000 | H20: =IF(B20="","",SUMIFS('08_PL_Operativa'!$H$5:$H$503,'08_PL_Operativa'!$B$5:$B$503,"<="&B20)) -> -14238.73 | I20: =IF(B20="","",C20-D20+E20-F20-G20+H20) -> 611761.75 | M20: =IF(B20="","",I20+IF(AND(MONTH(B20)=MONTH(DataOggi),YEAR(B20)=YEAR(DataOggi)),MV_Listed_Tot,IF(J20="",D20,J20))+IF(K20="",F20,K20)+IF(L20="",G20,L20)) -> 1993987.5 | N20: =IF(B20="","",SUMIFS('03_Investitori'!$J$5:$J$104,'03_Investitori'!$C$5:$C$104,"<="&B20)) -> 2000000 | O20: =IF(OR(B20="",N20=0,N20=""),"",M20/N20) -> 0.99699373 | P20: =IFERROR(IF(OR(B20="",O19=""),"",O20/O19-1),"") -> 0.0008567267
A21: =IF(B21="","",ROW()-4) | C21: =IF(B21="","",SUMIFS('03_Investitori'!$H$5:$H$104,'03_Investitori'!$C$5:$C$104,"<="&B21)) | D21: =IF(B21="","",SUMIFS('04_Trades'!$K$5:$K$1004,'04_Trades'!$C$5:$C$1004,"BUY",'04_Trades'!$B$5:$B$1004,"<="&B21)-SUMIFS('04_Trades'!$K$5:$K$1004,'04_Trades'!$C$5:$C$1004,"SELL",'04_Trades'!$B$5:$B$1004,"<="&B21)) | E21: =IF(B21="","",SUMIFS('05_Dividendi_Interessi'!$I$5:$I$504,'05_Dividendi_Interessi'!$B$5:$B$504,"<="&B21)) | F21: =IF(B21="","",SUMIFS('06_Partecipazioni'!$I$5:$I$204,'06_Partecipazioni'!$C$5:$C$204,"BUY",'06_Partecipazioni'!$B$5:$B$204,"<="&B21)-SUMIFS('06_Partecipazioni'!$I$5:$I$204,'06_Partecipazioni'!$C$5:$C$204,"SELL",'06_Partecipazioni'!$B$5:$B$204,"<="&B21)) | G21: =IF(B21="","",SUMIFS('07_Prestiti'!$H$5:$H$204,'07_Prestiti'!$C$5:$C$204,"DISBURSEMENT",'07_Prestiti'!$B$5:$B$204,"<="&B21)-SUMIFS('07_Prestiti'!$H$5:$H$204,'07_Prestiti'!$C$5:$C$204,"REPAYMENT",'07_Prestiti'!$B$5:$B$204,"<="&B21)) | H21: =IF(B21="","",SUMIFS('08_PL_Operativa'!$H$5:$H$503,'08_PL_Operativa'!$B$5:$B$503,"<="&B21)) | I21: =IF(B21="","",C21-D21+E21-F21-G21+H21) | M21: =IF(B21="","",I21+IF(AND(MONTH(B21)=MONTH(DataOggi),YEAR(B21)=YEAR(DataOggi)),MV_Listed_Tot,IF(J21="",D21,J21))+IF(K21="",F21,K21)+IF(L21="",G21,L21)) | N21: =IF(B21="","",SUMIFS('03_Investitori'!$J$5:$J$104,'03_Investitori'!$C$5:$C$104,"<="&B21)) | O21: =IF(OR(B21="",N21=0,N21=""),"",M21/N21) | P21: =IFERROR(IF(OR(B21="",O20=""),"",O21/O20-1),"")
A22: =IF(B22="","",ROW()-4) | C22: =IF(B22="","",SUMIFS('03_Investitori'!$H$5:$H$104,'03_Investitori'!$C$5:$C$104,"<="&B22)) | D22: =IF(B22="","",SUMIFS('04_Trades'!$K$5:$K$1004,'04_Trades'!$C$5:$C$1004,"BUY",'04_Trades'!$B$5:$B$1004,"<="&B22)-SUMIFS('04_Trades'!$K$5:$K$1004,'04_Trades'!$C$5:$C$1004,"SELL",'04_Trades'!$B$5:$B$1004,"<="&B22)) | E22: =IF(B22="","",SUMIFS('05_Dividendi_Interessi'!$I$5:$I$504,'05_Dividendi_Interessi'!$B$5:$B$504,"<="&B22)) | F22: =IF(B22="","",SUMIFS('06_Partecipazioni'!$I$5:$I$204,'06_Partecipazioni'!$C$5:$C$204,"BUY",'06_Partecipazioni'!$B$5:$B$204,"<="&B22)-SUMIFS('06_Partecipazioni'!$I$5:$I$204,'06_Partecipazioni'!$C$5:$C$204,"SELL",'06_Partecipazioni'!$B$5:$B$204,"<="&B22)) | G22: =IF(B22="","",SUMIFS('07_Prestiti'!$H$5:$H$204,'07_Prestiti'!$C$5:$C$204,"DISBURSEMENT",'07_Prestiti'!$B$5:$B$204,"<="&B22)-SUMIFS('07_Prestiti'!$H$5:$H$204,'07_Prestiti'!$C$5:$C$204,"REPAYMENT",'07_Prestiti'!$B$5:$B$204,"<="&B22)) | H22: =IF(B22="","",SUMIFS('08_PL_Operativa'!$H$5:$H$503,'08_PL_Operativa'!$B$5:$B$503,"<="&B22)) | I22: =IF(B22="","",C22-D22+E22-F22-G22+H22) | M22: =IF(B22="","",I22+IF(AND(MONTH(B22)=MONTH(DataOggi),YEAR(B22)=YEAR(DataOggi)),MV_Listed_Tot,IF(J22="",D22,J22))+IF(K22="",F22,K22)+IF(L22="",G22,L22)) | N22: =IF(B22="","",SUMIFS('03_Investitori'!$J$5:$J$104,'03_Investitori'!$C$5:$C$104,"<="&B22)) | O22: =IF(OR(B22="",N22=0,N22=""),"",M22/N22) | P22: =IFERROR(IF(OR(B22="",O21=""),"",O22/O21-1),"")
A23: =IF(B23="","",ROW()-4) | C23: =IF(B23="","",SUMIFS('03_Investitori'!$H$5:$H$104,'03_Investitori'!$C$5:$C$104,"<="&B23)) | D23: =IF(B23="","",SUMIFS('04_Trades'!$K$5:$K$1004,'04_Trades'!$C$5:$C$1004,"BUY",'04_Trades'!$B$5:$B$1004,"<="&B23)-SUMIFS('04_Trades'!$K$5:$K$1004,'04_Trades'!$C$5:$C$1004,"SELL",'04_Trades'!$B$5:$B$1004,"<="&B23)) | E23: =IF(B23="","",SUMIFS('05_Dividendi_Interessi'!$I$5:$I$504,'05_Dividendi_Interessi'!$B$5:$B$504,"<="&B23)) | F23: =IF(B23="","",SUMIFS('06_Partecipazioni'!$I$5:$I$204,'06_Partecipazioni'!$C$5:$C$204,"BUY",'06_Partecipazioni'!$B$5:$B$204,"<="&B23)-SUMIFS('06_Partecipazioni'!$I$5:$I$204,'06_Partecipazioni'!$C$5:$C$204,"SELL",'06_Partecipazioni'!$B$5:$B$204,"<="&B23)) | G23: =IF(B23="","",SUMIFS('07_Prestiti'!$H$5:$H$204,'07_Prestiti'!$C$5:$C$204,"DISBURSEMENT",'07_Prestiti'!$B$5:$B$204,"<="&B23)-SUMIFS('07_Prestiti'!$H$5:$H$204,'07_Prestiti'!$C$5:$C$204,"REPAYMENT",'07_Prestiti'!$B$5:$B$204,"<="&B23)) | H23: =IF(B23="","",SUMIFS('08_PL_Operativa'!$H$5:$H$503,'08_PL_Operativa'!$B$5:$B$503,"<="&B23)) | I23: =IF(B23="","",C23-D23+E23-F23-G23+H23) | M23: =IF(B23="","",I23+IF(AND(MONTH(B23)=MONTH(DataOggi),YEAR(B23)=YEAR(DataOggi)),MV_Listed_Tot,IF(J23="",D23,J23))+IF(K23="",F23,K23)+IF(L23="",G23,L23)) | N23: =IF(B23="","",SUMIFS('03_Investitori'!$J$5:$J$104,'03_Investitori'!$C$5:$C$104,"<="&B23)) | O23: =IF(OR(B23="",N23=0,N23=""),"",M23/N23) | P23: =IFERROR(IF(OR(B23="",O22=""),"",O23/O22-1),"")
A24: =IF(B24="","",ROW()-4) | C24: =IF(B24="","",SUMIFS('03_Investitori'!$H$5:$H$104,'03_Investitori'!$C$5:$C$104,"<="&B24)) | D24: =IF(B24="","",SUMIFS('04_Trades'!$K$5:$K$1004,'04_Trades'!$C$5:$C$1004,"BUY",'04_Trades'!$B$5:$B$1004,"<="&B24)-SUMIFS('04_Trades'!$K$5:$K$1004,'04_Trades'!$C$5:$C$1004,"SELL",'04_Trades'!$B$5:$B$1004,"<="&B24)) | E24: =IF(B24="","",SUMIFS('05_Dividendi_Interessi'!$I$5:$I$504,'05_Dividendi_Interessi'!$B$5:$B$504,"<="&B24)) | F24: =IF(B24="","",SUMIFS('06_Partecipazioni'!$I$5:$I$204,'06_Partecipazioni'!$C$5:$C$204,"BUY",'06_Partecipazioni'!$B$5:$B$204,"<="&B24)-SUMIFS('06_Partecipazioni'!$I$5:$I$204,'06_Partecipazioni'!$C$5:$C$204,"SELL",'06_Partecipazioni'!$B$5:$B$204,"<="&B24)) | G24: =IF(B24="","",SUMIFS('07_Prestiti'!$H$5:$H$204,'07_Prestiti'!$C$5:$C$204,"DISBURSEMENT",'07_Prestiti'!$B$5:$B$204,"<="&B24)-SUMIFS('07_Prestiti'!$H$5:$H$204,'07_Prestiti'!$C$5:$C$204,"REPAYMENT",'07_Prestiti'!$B$5:$B$204,"<="&B24)) | H24: =IF(B24="","",SUMIFS('08_PL_Operativa'!$H$5:$H$503,'08_PL_Operativa'!$B$5:$B$503,"<="&B24)) | I24: =IF(B24="","",C24-D24+E24-F24-G24+H24) | M24: =IF(B24="","",I24+IF(AND(MONTH(B24)=MONTH(DataOggi),YEAR(B24)=YEAR(DataOggi)),MV_Listed_Tot,IF(J24="",D24,J24))+IF(K24="",F24,K24)+IF(L24="",G24,L24)) | N24: =IF(B24="","",SUMIFS('03_Investitori'!$J$5:$J$104,'03_Investitori'!$C$5:$C$104,"<="&B24)) | O24: =IF(OR(B24="",N24=0,N24=""),"",M24/N24) | P24: =IFERROR(IF(OR(B24="",O23=""),"",O24/O23-1),"")
A25: =IF(B25="","",ROW()-4) | C25: =IF(B25="","",SUMIFS('03_Investitori'!$H$5:$H$104,'03_Investitori'!$C$5:$C$104,"<="&B25)) | D25: =IF(B25="","",SUMIFS('04_Trades'!$K$5:$K$1004,'04_Trades'!$C$5:$C$1004,"BUY",'04_Trades'!$B$5:$B$1004,"<="&B25)-SUMIFS('04_Trades'!$K$5:$K$1004,'04_Trades'!$C$5:$C$1004,"SELL",'04_Trades'!$B$5:$B$1004,"<="&B25)) | E25: =IF(B25="","",SUMIFS('05_Dividendi_Interessi'!$I$5:$I$504,'05_Dividendi_Interessi'!$B$5:$B$504,"<="&B25)) | F25: =IF(B25="","",SUMIFS('06_Partecipazioni'!$I$5:$I$204,'06_Partecipazioni'!$C$5:$C$204,"BUY",'06_Partecipazioni'!$B$5:$B$204,"<="&B25)-SUMIFS('06_Partecipazioni'!$I$5:$I$204,'06_Partecipazioni'!$C$5:$C$204,"SELL",'06_Partecipazioni'!$B$5:$B$204,"<="&B25)) | G25: =IF(B25="","",SUMIFS('07_Prestiti'!$H$5:$H$204,'07_Prestiti'!$C$5:$C$204,"DISBURSEMENT",'07_Prestiti'!$B$5:$B$204,"<="&B25)-SUMIFS('07_Prestiti'!$H$5:$H$204,'07_Prestiti'!$C$5:$C$204,"REPAYMENT",'07_Prestiti'!$B$5:$B$204,"<="&B25)) | H25: =IF(B25="","",SUMIFS('08_PL_Operativa'!$H$5:$H$503,'08_PL_Operativa'!$B$5:$B$503,"<="&B25)) | I25: =IF(B25="","",C25-D25+E25-F25-G25+H25) | M25: =IF(B25="","",I25+IF(AND(MONTH(B25)=MONTH(DataOggi),YEAR(B25)=YEAR(DataOggi)),MV_Listed_Tot,IF(J25="",D25,J25))+IF(K25="",F25,K25)+IF(L25="",G25,L25)) | N25: =IF(B25="","",SUMIFS('03_Investitori'!$J$5:$J$104,'03_Investitori'!$C$5:$C$104,"<="&B25)) | O25: =IF(OR(B25="",N25=0,N25=""),"",M25/N25) | P25: =IFERROR(IF(OR(B25="",O24=""),"",O25/O24-1),"")
A26: =IF(B26="","",ROW()-4) | C26: =IF(B26="","",SUMIFS('03_Investitori'!$H$5:$H$104,'03_Investitori'!$C$5:$C$104,"<="&B26)) | D26: =IF(B26="","",SUMIFS('04_Trades'!$K$5:$K$1004,'04_Trades'!$C$5:$C$1004,"BUY",'04_Trades'!$B$5:$B$1004,"<="&B26)-SUMIFS('04_Trades'!$K$5:$K$1004,'04_Trades'!$C$5:$C$1004,"SELL",'04_Trades'!$B$5:$B$1004,"<="&B26)) | E26: =IF(B26="","",SUMIFS('05_Dividendi_Interessi'!$I$5:$I$504,'05_Dividendi_Interessi'!$B$5:$B$504,"<="&B26)) | F26: =IF(B26="","",SUMIFS('06_Partecipazioni'!$I$5:$I$204,'06_Partecipazioni'!$C$5:$C$204,"BUY",'06_Partecipazioni'!$B$5:$B$204,"<="&B26)-SUMIFS('06_Partecipazioni'!$I$5:$I$204,'06_Partecipazioni'!$C$5:$C$204,"SELL",'06_Partecipazioni'!$B$5:$B$204,"<="&B26)) | G26: =IF(B26="","",SUMIFS('07_Prestiti'!$H$5:$H$204,'07_Prestiti'!$C$5:$C$204,"DISBURSEMENT",'07_Prestiti'!$B$5:$B$204,"<="&B26)-SUMIFS('07_Prestiti'!$H$5:$H$204,'07_Prestiti'!$C$5:$C$204,"REPAYMENT",'07_Prestiti'!$B$5:$B$204,"<="&B26)) | H26: =IF(B26="","",SUMIFS('08_PL_Operativa'!$H$5:$H$503,'08_PL_Operativa'!$B$5:$B$503,"<="&B26)) | I26: =IF(B26="","",C26-D26+E26-F26-G26+H26) | M26: =IF(B26="","",I26+IF(AND(MONTH(B26)=MONTH(DataOggi),YEAR(B26)=YEAR(DataOggi)),MV_Listed_Tot,IF(J26="",D26,J26))+IF(K26="",F26,K26)+IF(L26="",G26,L26)) | N26: =IF(B26="","",SUMIFS('03_Investitori'!$J$5:$J$104,'03_Investitori'!$C$5:$C$104,"<="&B26)) | O26: =IF(OR(B26="",N26=0,N26=""),"",M26/N26) | P26: =IFERROR(IF(OR(B26="",O25=""),"",O26/O25-1),"")
A27: =IF(B27="","",ROW()-4) | C27: =IF(B27="","",SUMIFS('03_Investitori'!$H$5:$H$104,'03_Investitori'!$C$5:$C$104,"<="&B27)) | D27: =IF(B27="","",SUMIFS('04_Trades'!$K$5:$K$1004,'04_Trades'!$C$5:$C$1004,"BUY",'04_Trades'!$B$5:$B$1004,"<="&B27)-SUMIFS('04_Trades'!$K$5:$K$1004,'04_Trades'!$C$5:$C$1004,"SELL",'04_Trades'!$B$5:$B$1004,"<="&B27)) | E27: =IF(B27="","",SUMIFS('05_Dividendi_Interessi'!$I$5:$I$504,'05_Dividendi_Interessi'!$B$5:$B$504,"<="&B27)) | F27: =IF(B27="","",SUMIFS('06_Partecipazioni'!$I$5:$I$204,'06_Partecipazioni'!$C$5:$C$204,"BUY",'06_Partecipazioni'!$B$5:$B$204,"<="&B27)-SUMIFS('06_Partecipazioni'!$I$5:$I$204,'06_Partecipazioni'!$C$5:$C$204,"SELL",'06_Partecipazioni'!$B$5:$B$204,"<="&B27)) | G27: =IF(B27="","",SUMIFS('07_Prestiti'!$H$5:$H$204,'07_Prestiti'!$C$5:$C$204,"DISBURSEMENT",'07_Prestiti'!$B$5:$B$204,"<="&B27)-SUMIFS('07_Prestiti'!$H$5:$H$204,'07_Prestiti'!$C$5:$C$204,"REPAYMENT",'07_Prestiti'!$B$5:$B$204,"<="&B27)) | H27: =IF(B27="","",SUMIFS('08_PL_Operativa'!$H$5:$H$503,'08_PL_Operativa'!$B$5:$B$503,"<="&B27)) | I27: =IF(B27="","",C27-D27+E27-F27-G27+H27) | M27: =IF(B27="","",I27+IF(AND(MONTH(B27)=MONTH(DataOggi),YEAR(B27)=YEAR(DataOggi)),MV_Listed_Tot,IF(J27="",D27,J27))+IF(K27="",F27,K27)+IF(L27="",G27,L27)) | N27: =IF(B27="","",SUMIFS('03_Investitori'!$J$5:$J$104,'03_Investitori'!$C$5:$C$104,"<="&B27)) | O27: =IF(OR(B27="",N27=0,N27=""),"",M27/N27) | P27: =IFERROR(IF(OR(B27="",O26=""),"",O27/O26-1),"")
A28: =IF(B28="","",ROW()-4) | C28: =IF(B28="","",SUMIFS('03_Investitori'!$H$5:$H$104,'03_Investitori'!$C$5:$C$104,"<="&B28)) | D28: =IF(B28="","",SUMIFS('04_Trades'!$K$5:$K$1004,'04_Trades'!$C$5:$C$1004,"BUY",'04_Trades'!$B$5:$B$1004,"<="&B28)-SUMIFS('04_Trades'!$K$5:$K$1004,'04_Trades'!$C$5:$C$1004,"SELL",'04_Trades'!$B$5:$B$1004,"<="&B28)) | E28: =IF(B28="","",SUMIFS('05_Dividendi_Interessi'!$I$5:$I$504,'05_Dividendi_Interessi'!$B$5:$B$504,"<="&B28)) | F28: =IF(B28="","",SUMIFS('06_Partecipazioni'!$I$5:$I$204,'06_Partecipazioni'!$C$5:$C$204,"BUY",'06_Partecipazioni'!$B$5:$B$204,"<="&B28)-SUMIFS('06_Partecipazioni'!$I$5:$I$204,'06_Partecipazioni'!$C$5:$C$204,"SELL",'06_Partecipazioni'!$B$5:$B$204,"<="&B28)) | G28: =IF(B28="","",SUMIFS('07_Prestiti'!$H$5:$H$204,'07_Prestiti'!$C$5:$C$204,"DISBURSEMENT",'07_Prestiti'!$B$5:$B$204,"<="&B28)-SUMIFS('07_Prestiti'!$H$5:$H$204,'07_Prestiti'!$C$5:$C$204,"REPAYMENT",'07_Prestiti'!$B$5:$B$204,"<="&B28)) | H28: =IF(B28="","",SUMIFS('08_PL_Operativa'!$H$5:$H$503,'08_PL_Operativa'!$B$5:$B$503,"<="&B28)) | I28: =IF(B28="","",C28-D28+E28-F28-G28+H28) | M28: =IF(B28="","",I28+IF(AND(MONTH(B28)=MONTH(DataOggi),YEAR(B28)=YEAR(DataOggi)),MV_Listed_Tot,IF(J28="",D28,J28))+IF(K28="",F28,K28)+IF(L28="",G28,L28)) | N28: =IF(B28="","",SUMIFS('03_Investitori'!$J$5:$J$104,'03_Investitori'!$C$5:$C$104,"<="&B28)) | O28: =IF(OR(B28="",N28=0,N28=""),"",M28/N28) | P28: =IFERROR(IF(OR(B28="",O27=""),"",O28/O27-1),"")
A29: =IF(B29="","",ROW()-4) | C29: =IF(B29="","",SUMIFS('03_Investitori'!$H$5:$H$104,'03_Investitori'!$C$5:$C$104,"<="&B29)) | D29: =IF(B29="","",SUMIFS('04_Trades'!$K$5:$K$1004,'04_Trades'!$C$5:$C$1004,"BUY",'04_Trades'!$B$5:$B$1004,"<="&B29)-SUMIFS('04_Trades'!$K$5:$K$1004,'04_Trades'!$C$5:$C$1004,"SELL",'04_Trades'!$B$5:$B$1004,"<="&B29)) | E29: =IF(B29="","",SUMIFS('05_Dividendi_Interessi'!$I$5:$I$504,'05_Dividendi_Interessi'!$B$5:$B$504,"<="&B29)) | F29: =IF(B29="","",SUMIFS('06_Partecipazioni'!$I$5:$I$204,'06_Partecipazioni'!$C$5:$C$204,"BUY",'06_Partecipazioni'!$B$5:$B$204,"<="&B29)-SUMIFS('06_Partecipazioni'!$I$5:$I$204,'06_Partecipazioni'!$C$5:$C$204,"SELL",'06_Partecipazioni'!$B$5:$B$204,"<="&B29)) | G29: =IF(B29="","",SUMIFS('07_Prestiti'!$H$5:$H$204,'07_Prestiti'!$C$5:$C$204,"DISBURSEMENT",'07_Prestiti'!$B$5:$B$204,"<="&B29)-SUMIFS('07_Prestiti'!$H$5:$H$204,'07_Prestiti'!$C$5:$C$204,"REPAYMENT",'07_Prestiti'!$B$5:$B$204,"<="&B29)) | H29: =IF(B29="","",SUMIFS('08_PL_Operativa'!$H$5:$H$503,'08_PL_Operativa'!$B$5:$B$503,"<="&B29)) | I29: =IF(B29="","",C29-D29+E29-F29-G29+H29) | M29: =IF(B29="","",I29+IF(AND(MONTH(B29)=MONTH(DataOggi),YEAR(B29)=YEAR(DataOggi)),MV_Listed_Tot,IF(J29="",D29,J29))+IF(K29="",F29,K29)+IF(L29="",G29,L29)) | N29: =IF(B29="","",SUMIFS('03_Investitori'!$J$5:$J$104,'03_Investitori'!$C$5:$C$104,"<="&B29)) | O29: =IF(OR(B29="",N29=0,N29=""),"",M29/N29) | P29: =IFERROR(IF(OR(B29="",O28=""),"",O29/O28-1),"")
A30: =IF(B30="","",ROW()-4) | C30: =IF(B30="","",SUMIFS('03_Investitori'!$H$5:$H$104,'03_Investitori'!$C$5:$C$104,"<="&B30)) | D30: =IF(B30="","",SUMIFS('04_Trades'!$K$5:$K$1004,'04_Trades'!$C$5:$C$1004,"BUY",'04_Trades'!$B$5:$B$1004,"<="&B30)-SUMIFS('04_Trades'!$K$5:$K$1004,'04_Trades'!$C$5:$C$1004,"SELL",'04_Trades'!$B$5:$B$1004,"<="&B30)) | E30: =IF(B30="","",SUMIFS('05_Dividendi_Interessi'!$I$5:$I$504,'05_Dividendi_Interessi'!$B$5:$B$504,"<="&B30)) | F30: =IF(B30="","",SUMIFS('06_Partecipazioni'!$I$5:$I$204,'06_Partecipazioni'!$C$5:$C$204,"BUY",'06_Partecipazioni'!$B$5:$B$204,"<="&B30)-SUMIFS('06_Partecipazioni'!$I$5:$I$204,'06_Partecipazioni'!$C$5:$C$204,"SELL",'06_Partecipazioni'!$B$5:$B$204,"<="&B30)) | G30: =IF(B30="","",SUMIFS('07_Prestiti'!$H$5:$H$204,'07_Prestiti'!$C$5:$C$204,"DISBURSEMENT",'07_Prestiti'!$B$5:$B$204,"<="&B30)-SUMIFS('07_Prestiti'!$H$5:$H$204,'07_Prestiti'!$C$5:$C$204,"REPAYMENT",'07_Prestiti'!$B$5:$B$204,"<="&B30)) | H30: =IF(B30="","",SUMIFS('08_PL_Operativa'!$H$5:$H$503,'08_PL_Operativa'!$B$5:$B$503,"<="&B30)) | I30: =IF(B30="","",C30-D30+E30-F30-G30+H30) | M30: =IF(B30="","",I30+IF(AND(MONTH(B30)=MONTH(DataOggi),YEAR(B30)=YEAR(DataOggi)),MV_Listed_Tot,IF(J30="",D30,J30))+IF(K30="",F30,K30)+IF(L30="",G30,L30)) | N30: =IF(B30="","",SUMIFS('03_Investitori'!$J$5:$J$104,'03_Investitori'!$C$5:$C$104,"<="&B30)) | O30: =IF(OR(B30="",N30=0,N30=""),"",M30/N30) | P30: =IFERROR(IF(OR(B30="",O29=""),"",O30/O29-1),"")
A31: =IF(B31="","",ROW()-4) | C31: =IF(B31="","",SUMIFS('03_Investitori'!$H$5:$H$104,'03_Investitori'!$C$5:$C$104,"<="&B31)) | D31: =IF(B31="","",SUMIFS('04_Trades'!$K$5:$K$1004,'04_Trades'!$C$5:$C$1004,"BUY",'04_Trades'!$B$5:$B$1004,"<="&B31)-SUMIFS('04_Trades'!$K$5:$K$1004,'04_Trades'!$C$5:$C$1004,"SELL",'04_Trades'!$B$5:$B$1004,"<="&B31)) | E31: =IF(B31="","",SUMIFS('05_Dividendi_Interessi'!$I$5:$I$504,'05_Dividendi_Interessi'!$B$5:$B$504,"<="&B31)) | F31: =IF(B31="","",SUMIFS('06_Partecipazioni'!$I$5:$I$204,'06_Partecipazioni'!$C$5:$C$204,"BUY",'06_Partecipazioni'!$B$5:$B$204,"<="&B31)-SUMIFS('06_Partecipazioni'!$I$5:$I$204,'06_Partecipazioni'!$C$5:$C$204,"SELL",'06_Partecipazioni'!$B$5:$B$204,"<="&B31)) | G31: =IF(B31="","",SUMIFS('07_Prestiti'!$H$5:$H$204,'07_Prestiti'!$C$5:$C$204,"DISBURSEMENT",'07_Prestiti'!$B$5:$B$204,"<="&B31)-SUMIFS('07_Prestiti'!$H$5:$H$204,'07_Prestiti'!$C$5:$C$204,"REPAYMENT",'07_Prestiti'!$B$5:$B$204,"<="&B31)) | H31: =IF(B31="","",SUMIFS('08_PL_Operativa'!$H$5:$H$503,'08_PL_Operativa'!$B$5:$B$503,"<="&B31)) | I31: =IF(B31="","",C31-D31+E31-F31-G31+H31) | M31: =IF(B31="","",I31+IF(AND(MONTH(B31)=MONTH(DataOggi),YEAR(B31)=YEAR(DataOggi)),MV_Listed_Tot,IF(J31="",D31,J31))+IF(K31="",F31,K31)+IF(L31="",G31,L31)) | N31: =IF(B31="","",SUMIFS('03_Investitori'!$J$5:$J$104,'03_Investitori'!$C$5:$C$104,"<="&B31)) | O31: =IF(OR(B31="",N31=0,N31=""),"",M31/N31) | P31: =IFERROR(IF(OR(B31="",O30=""),"",O31/O30-1),"")
A32: =IF(B32="","",ROW()-4) | C32: =IF(B32="","",SUMIFS('03_Investitori'!$H$5:$H$104,'03_Investitori'!$C$5:$C$104,"<="&B32)) | D32: =IF(B32="","",SUMIFS('04_Trades'!$K$5:$K$1004,'04_Trades'!$C$5:$C$1004,"BUY",'04_Trades'!$B$5:$B$1004,"<="&B32)-SUMIFS('04_Trades'!$K$5:$K$1004,'04_Trades'!$C$5:$C$1004,"SELL",'04_Trades'!$B$5:$B$1004,"<="&B32)) | E32: =IF(B32="","",SUMIFS('05_Dividendi_Interessi'!$I$5:$I$504,'05_Dividendi_Interessi'!$B$5:$B$504,"<="&B32)) | F32: =IF(B32="","",SUMIFS('06_Partecipazioni'!$I$5:$I$204,'06_Partecipazioni'!$C$5:$C$204,"BUY",'06_Partecipazioni'!$B$5:$B$204,"<="&B32)-SUMIFS('06_Partecipazioni'!$I$5:$I$204,'06_Partecipazioni'!$C$5:$C$204,"SELL",'06_Partecipazioni'!$B$5:$B$204,"<="&B32)) | G32: =IF(B32="","",SUMIFS('07_Prestiti'!$H$5:$H$204,'07_Prestiti'!$C$5:$C$204,"DISBURSEMENT",'07_Prestiti'!$B$5:$B$204,"<="&B32)-SUMIFS('07_Prestiti'!$H$5:$H$204,'07_Prestiti'!$C$5:$C$204,"REPAYMENT",'07_Prestiti'!$B$5:$B$204,"<="&B32)) | H32: =IF(B32="","",SUMIFS('08_PL_Operativa'!$H$5:$H$503,'08_PL_Operativa'!$B$5:$B$503,"<="&B32)) | I32: =IF(B32="","",C32-D32+E32-F32-G32+H32) | M32: =IF(B32="","",I32+IF(AND(MONTH(B32)=MONTH(DataOggi),YEAR(B32)=YEAR(DataOggi)),MV_Listed_Tot,IF(J32="",D32,J32))+IF(K32="",F32,K32)+IF(L32="",G32,L32)) | N32: =IF(B32="","",SUMIFS('03_Investitori'!$J$5:$J$104,'03_Investitori'!$C$5:$C$104,"<="&B32)) | O32: =IF(OR(B32="",N32=0,N32=""),"",M32/N32) | P32: =IFERROR(IF(OR(B32="",O31=""),"",O32/O31-1),"")
... A124: =IF(B124="","",ROW()-4) | C124: =IF(B124="","",SUMIFS('03_Investitori'!$H$5:$H$104,'03_Investitori'!$C$5:$C$104,"<="&B124)) | D124: =IF(B124="","",SUMIFS('04_Trades'!$K$5:$K$1004,'04_Trades'!$C$5:$C$1004,"BUY",'04_Trades'!$B$5:$B$1004,"<="&B124)-SUMIFS('04_Trades'!$K$5:$K$1004,'04_Trades'!$C$5:$C$1004,"SELL",'04_Trades'!$B$5:$B$1004,"<="&B124)) | E124: =IF(B124="","",SUMIFS('05_Dividendi_Interessi'!$I$5:$I$504,'05_Dividendi_Interessi'!$B$5:$B$504,"<="&B124)) | F124: =IF(B124="","",SUMIFS('06_Partecipazioni'!$I$5:$I$204,'06_Partecipazioni'!$C$5:$C$204,"BUY",'06_Partecipazioni'!$B$5:$B$204,"<="&B124)-SUMIFS('06_Partecipazioni'!$I$5:$I$204,'06_Partecipazioni'!$C$5:$C$204,"SELL",'06_Partecipazioni'!$B$5:$B$204,"<="&B124)) | G124: =IF(B124="","",SUMIFS('07_Prestiti'!$H$5:$H$204,'07_Prestiti'!$C$5:$C$204,"DISBURSEMENT",'07_Prestiti'!$B$5:$B$204,"<="&B124)-SUMIFS('07_Prestiti'!$H$5:$H$204,'07_Prestiti'!$C$5:$C$204,"REPAYMENT",'07_Prestiti'!$B$5:$B$204,"<="&B124)) | H124: =IF(B124="","",SUMIFS('08_PL_Operativa'!$H$5:$H$503,'08_PL_Operativa'!$B$5:$B$503,"<="&B124)) | I124: =IF(B124="","",C124-D124+E124-F124-G124+H124) | M124: =IF(B124="","",I124+IF(AND(MONTH(B124)=MONTH(DataOggi),YEAR(B124)=YEAR(DataOggi)),MV_Listed_Tot,IF(J124="",D124,J124))+IF(K124="",F124,K124)+IF(L124="",G124,L124)) | N124: =IF(B124="","",SUMIFS('03_Investitori'!$J$5:$J$104,'03_Investitori'!$C$5:$C$104,"<="&B124)) | O124: =IF(OR(B124="",N124=0,N124=""),"",M124/N124) | P124: =IFERROR(IF(OR(B124="",O123=""),"",O124/O123-1),"")

Sheet 11_Performance
A1: Performance Aggregata del Fondo
A2: Tutti gli indicatori sono calcolati alla data odierna. L'IRR usa XIRR sui flussi reali (sottoscrizioni + NAV oggi come terminal value). Sharpe usa rendimenti mensili annualizzati da 10_NAV_Mensile.
A4: Snapshot Corrente del Fondo | D4: CF Date (helper) | E4: CF Value (helper) | G4: Running Max NAV/Unit | H4: Drawdown
A5: Data Odierna | B5: =DataOggi -> 46160 | D5: =IF('03_Investitori'!C5="",DataOggi,'03_Investitori'!C5) -> 45736 | E5: =IF('03_Investitori'!H5="",0,-'03_Investitori'!H5) -> -500000 | G5: =IFERROR(IF('10_NAV_Mensile'!O5="","",'10_NAV_Mensile'!O5),"") | H5: =IFERROR(IF(OR(G5="",'10_NAV_Mensile'!O5=""),"",'10_NAV_Mensile'!O5/G5-1),"")
A6: Capitale Raccolto EUR | B6: =SUMIFS('03_Investitori'!$H$5:$H$104,'03_Investitori'!$C$5:$C$104,"<="&DataOggi) -> 2000000 | D6: =IF('03_Investitori'!C6="",DataOggi,'03_Investitori'!C6) -> 45904 | E6: =IF('03_Investitori'!H6="",0,-'03_Investitori'!H6) -> -500000 | G6: =IFERROR(IF('10_NAV_Mensile'!O6="","",MAX(G5,'10_NAV_Mensile'!O6)),"") | H6: =IFERROR(IF(OR(G6="",'10_NAV_Mensile'!O6=""),"",'10_NAV_Mensile'!O6/G6-1),"")
A7: Net Trade Cum. EUR (Listed) | B7: =SUMIFS('04_Trades'!$K$5:$K$1004,'04_Trades'!$C$5:$C$1004,"BUY",'04_Trades'!$B$5:$B$1004,"<="&DataOggi)-SUMIFS('04_Trades'!$K$5:$K$1004,'04_Trades'!$C$5:$C$1004,"SELL",'04_Trades'!$B$5:$B$1004,"<="&DataOggi) -> 1082225.7 | D7: =IF('03_Investitori'!C7="",DataOggi,'03_Investitori'!C7) -> 45910 | E7: =IF('03_Investitori'!H7="",0,-'03_Investitori'!H7) -> -500000 | G7: =IFERROR(IF('10_NAV_Mensile'!O7="","",MAX(G6,'10_NAV_Mensile'!O7)),"") -> 0.9999906 | H7: =IFERROR(IF(OR(G7="",'10_NAV_Mensile'!O7=""),"",'10_NAV_Mensile'!O7/G7-1),"") -> 0
A8: Div/Int Lordi Cum. EUR | B8: =SUMIFS('05_Dividendi_Interessi'!$I$5:$I$504,'05_Dividendi_Interessi'!$B$5:$B$504,"<="&DataOggi) -> 8226.2 | D8: =IF('03_Investitori'!C8="",DataOggi,'03_Investitori'!C8) -> 46097 | E8: =IF('03_Investitori'!H8="",0,-'03_Investitori'!H8) -> -500000 | G8: =IFERROR(IF('10_NAV_Mensile'!O8="","",MAX(G7,'10_NAV_Mensile'!O8)),"") -> 0.9999906 | H8: =IFERROR(IF(OR(G8="",'10_NAV_Mensile'!O8=""),"",'10_NAV_Mensile'!O8/G8-1),"") -> 0
A9: Part. Net Cum. EUR | B9: =SUMIFS('06_Partecipazioni'!$I$5:$I$204,'06_Partecipazioni'!$C$5:$C$204,"BUY",'06_Partecipazioni'!$B$5:$B$204,"<="&DataOggi)-SUMIFS('06_Partecipazioni'!$I$5:$I$204,'06_Partecipazioni'!$C$5:$C$204,"SELL",'06_Partecipazioni'!$B$5:$B$204,"<="&DataOggi) -> 165000 | D9: =IF('03_Investitori'!C9="",DataOggi,'03_Investitori'!C9) -> 46160 | E9: =IF('03_Investitori'!H9="",0,-'03_Investitori'!H9) -> 0 | G9: =IFERROR(IF('10_NAV_Mensile'!O9="","",MAX(G8,'10_NAV_Mensile'!O9)),"") -> 0.9999906 | H9: =IFERROR(IF(OR(G9="",'10_NAV_Mensile'!O9=""),"",'10_NAV_Mensile'!O9/G9-1),"") -> 0
A10: Loan Net Cum. EUR | B10: =SUMIFS('07_Prestiti'!$H$5:$H$204,'07_Prestiti'!$C$5:$C$204,"DISBURSEMENT",'07_Prestiti'!$B$5:$B$204,"<="&DataOggi)-SUMIFS('07_Prestiti'!$H$5:$H$204,'07_Prestiti'!$C$5:$C$204,"REPAYMENT",'07_Prestiti'!$B$5:$B$204,"<="&DataOggi) -> 135000 | D10: =IF('03_Investitori'!C10="",DataOggi,'03_Investitori'!C10) -> 46160 | E10: =IF('03_Investitori'!H10="",0,-'03_Investitori'!H10) -> 0 | G10: =IFERROR(IF('10_NAV_Mensile'!O10="","",MAX(G9,'10_NAV_Mensile'!O10)),"") -> 0.9999906 | H10: =IFERROR(IF(OR(G10="",'10_NAV_Mensile'!O10=""),"",'10_NAV_Mensile'!O10/G10-1),"") -> 0
A11: P/L Operativa Cum. EUR | B11: =SUMIFS('08_PL_Operativa'!$H$5:$H$503,'08_PL_Operativa'!$B$5:$B$503,"<="&DataOggi) -> -14238.73 | D11: =IF('03_Investitori'!C11="",DataOggi,'03_Investitori'!C11) -> 46160 | E11: =IF('03_Investitori'!H11="",0,-'03_Investitori'!H11) -> 0 | G11: =IFERROR(IF('10_NAV_Mensile'!O11="","",MAX(G10,'10_NAV_Mensile'!O11)),"") -> 0.9999906 | H11: =IFERROR(IF(OR(G11="",'10_NAV_Mensile'!O11=""),"",'10_NAV_Mensile'!O11/G11-1),"") -> -0.00065102612
A12: Cassa EUR | B12: =B6-B7+B8-B9-B10+B11 -> 611761.75 | D12: =IF('03_Investitori'!C12="",DataOggi,'03_Investitori'!C12) -> 46160 | E12: =IF('03_Investitori'!H12="",0,-'03_Investitori'!H12) -> 0 | G12: =IFERROR(IF('10_NAV_Mensile'!O12="","",MAX(G11,'10_NAV_Mensile'!O12)),"") -> 0.9999906 | H12: =IFERROR(IF(OR(G12="",'10_NAV_Mensile'!O12=""),"",'10_NAV_Mensile'!O12/G12-1),"") -> -0.00062204585
A13: Listed MV EUR (ultimo prezzo) | B13: =IFERROR(MV_Listed_Tot,0) -> 1069752.7 | D13: =IF('03_Investitori'!C13="",DataOggi,'03_Investitori'!C13) -> 46160 | E13: =IF('03_Investitori'!H13="",0,-'03_Investitori'!H13) -> 0 | G13: =IFERROR(IF('10_NAV_Mensile'!O13="","",MAX(G12,'10_NAV_Mensile'!O13)),"") -> 1.0007472 | H13: =IFERROR(IF(OR(G13="",'10_NAV_Mensile'!O13=""),"",'10_NAV_Mensile'!O13/G13-1),"") -> 0
A14: Partecipazioni MV EUR | B14: =IF(COUNT('06_Partecipazioni'!$J$5:$J$204)=0,B9,SUM('06_Partecipazioni'!$J$5:$J$204)) -> 155000 | D14: =IF('03_Investitori'!C14="",DataOggi,'03_Investitori'!C14) -> 46160 | E14: =IF('03_Investitori'!H14="",0,-'03_Investitori'!H14) -> 0 | G14: =IFERROR(IF('10_NAV_Mensile'!O14="","",MAX(G13,'10_NAV_Mensile'!O14)),"") -> 1.0007574 | H14: =IFERROR(IF(OR(G14="",'10_NAV_Mensile'!O14=""),"",'10_NAV_Mensile'!O14/G14-1),"") -> 0
A15: Prestiti Outstanding EUR | B15: =IF(COUNT('07_Prestiti'!$I$5:$I$204)=0,B10,SUM('07_Prestiti'!$I$5:$I$204)) -> 135000 | D15: =IF('03_Investitori'!C15="",DataOggi,'03_Investitori'!C15) -> 46160 | E15: =IF('03_Investitori'!H15="",0,-'03_Investitori'!H15) -> 0 | G15: =IFERROR(IF('10_NAV_Mensile'!O15="","",MAX(G14,'10_NAV_Mensile'!O15)),"") -> 1.0009822 | H15: =IFERROR(IF(OR(G15="",'10_NAV_Mensile'!O15=""),"",'10_NAV_Mensile'!O15/G15-1),"") -> 0
A16: NAV TOTALE EUR | B16: =B12+B13+B14+B15 -> 1971514.5 | D16: =IF('03_Investitori'!C16="",DataOggi,'03_Investitori'!C16) -> 46160 | E16: =IF('03_Investitori'!H16="",0,-'03_Investitori'!H16) -> 0 | G16: =IFERROR(IF('10_NAV_Mensile'!O16="","",MAX(G15,'10_NAV_Mensile'!O16)),"") -> 1.0009822 | H16: =IFERROR(IF(OR(G16="",'10_NAV_Mensile'!O16=""),"",'10_NAV_Mensile'!O16/G16-1),"") -> -0.050029439
A17: Quote Outstanding | B17: =SUMIFS('03_Investitori'!$J$5:$J$104,'03_Investitori'!$C$5:$C$104,"<="&DataOggi) -> 2000000 | D17: =IF('03_Investitori'!C17="",DataOggi,'03_Investitori'!C17) -> 46160 | E17: =IF('03_Investitori'!H17="",0,-'03_Investitori'!H17) -> 0 | G17: =IFERROR(IF('10_NAV_Mensile'!O17="","",MAX(G16,'10_NAV_Mensile'!O17)),"") -> 1.0009822 | H17: =IFERROR(IF(OR(G17="",'10_NAV_Mensile'!O17=""),"",'10_NAV_Mensile'!O17/G17-1),"") -> -0.049848284
A18: NAV/Unit Corrente | B18: =IFERROR(B16/B17,0) -> 0.98575725 | D18: =IF('03_Investitori'!C18="",DataOggi,'03_Investitori'!C18) -> 46160 | E18: =IF('03_Investitori'!H18="",0,-'03_Investitori'!H18) -> 0 | G18: =IFERROR(IF('10_NAV_Mensile'!O18="","",MAX(G17,'10_NAV_Mensile'!O18)),"") -> 1.0009822 | H18: =IFERROR(IF(OR(G18="",'10_NAV_Mensile'!O18=""),"",'10_NAV_Mensile'!O18/G18-1),"") -> -0.049836556
D19: =IF('03_Investitori'!C19="",DataOggi,'03_Investitori'!C19) -> 46160 | E19: =IF('03_Investitori'!H19="",0,-'03_Investitori'!H19) -> 0 | G19: =IFERROR(IF('10_NAV_Mensile'!O19="","",MAX(G18,'10_NAV_Mensile'!O19)),"") -> 1.0009822 | H19: =IFERROR(IF(OR(G19="",'10_NAV_Mensile'!O19=""),"",'10_NAV_Mensile'!O19/G19-1),"") -> -0.0048371671
D20: =IF('03_Investitori'!C20="",DataOggi,'03_Investitori'!C20) -> 46160 | E20: =IF('03_Investitori'!H20="",0,-'03_Investitori'!H20) -> 0 | G20: =IFERROR(IF('10_NAV_Mensile'!O20="","",MAX(G19,'10_NAV_Mensile'!O20)),"") -> 1.0009822 | H20: =IFERROR(IF(OR(G20="",'10_NAV_Mensile'!O20=""),"",'10_NAV_Mensile'!O20/G20-1),"") -> -0.0039845845
A21: KPI di Fondo | D21: =IF('03_Investitori'!C21="",DataOggi,'03_Investitori'!C21) -> 46160 | E21: =IF('03_Investitori'!H21="",0,-'03_Investitori'!H21) -> 0 | G21: =IFERROR(IF('10_NAV_Mensile'!O21="","",MAX(G20,'10_NAV_Mensile'!O21)),"") | H21: =IFERROR(IF(OR(G21="",'10_NAV_Mensile'!O21=""),"",'10_NAV_Mensile'!O21/G21-1),"")
A22: MOIC (Multiple on Invested Capital) | B22: =IFERROR(NAV_Curr/Capital_Tot,0) -> 0.98575725 | D22: =IF('03_Investitori'!C22="",DataOggi,'03_Investitori'!C22) -> 46160 | E22: =IF('03_Investitori'!H22="",0,-'03_Investitori'!H22) -> 0 | G22: =IFERROR(IF('10_NAV_Mensile'!O22="","",MAX(G21,'10_NAV_Mensile'!O22)),"") | H22: =IFERROR(IF(OR(G22="",'10_NAV_Mensile'!O22=""),"",'10_NAV_Mensile'!O22/G22-1),"")
A23: Profitto Totale EUR | B23: =NAV_Curr-Capital_Tot -> -28485.504 | D23: =IF('03_Investitori'!C23="",DataOggi,'03_Investitori'!C23) -> 46160 | E23: =IF('03_Investitori'!H23="",0,-'03_Investitori'!H23) -> 0 | G23: =IFERROR(IF('10_NAV_Mensile'!O23="","",MAX(G22,'10_NAV_Mensile'!O23)),"") | H23: =IFERROR(IF(OR(G23="",'10_NAV_Mensile'!O23=""),"",'10_NAV_Mensile'!O23/G23-1),"")
A24: Return Totale % | B24: =IFERROR(NAV_Curr/Capital_Tot-1,0) -> -0.014242752 | D24: =IF('03_Investitori'!C24="",DataOggi,'03_Investitori'!C24) -> 46160 | E24: =IF('03_Investitori'!H24="",0,-'03_Investitori'!H24) -> 0 | G24: =IFERROR(IF('10_NAV_Mensile'!O24="","",MAX(G23,'10_NAV_Mensile'!O24)),"") | H24: =IFERROR(IF(OR(G24="",'10_NAV_Mensile'!O24=""),"",'10_NAV_Mensile'!O24/G24-1),"")
A25: IRR (XIRR sulle sottoscrizioni) | B25: =IFERROR(XIRR($E$5:$E$105,$D$5:$D$105),0) -> -0.020910069 | D25: =IF('03_Investitori'!C25="",DataOggi,'03_Investitori'!C25) -> 46160 | E25: =IF('03_Investitori'!H25="",0,-'03_Investitori'!H25) -> 0 | G25: =IFERROR(IF('10_NAV_Mensile'!O25="","",MAX(G24,'10_NAV_Mensile'!O25)),"") | H25: =IFERROR(IF(OR(G25="",'10_NAV_Mensile'!O25=""),"",'10_NAV_Mensile'!O25/G25-1),"")
A26: CAGR Time-Weighted (NAV/Unit) | B26: =IFERROR((NAV_Curr/Capital_Tot)^(365.25/(DataOggi-_xludf.MINIFS('03_Investitori'!$C$5:$C$104,'03_Investitori'!$C$5:$C$104,">0")))-1,0) -> 0 | D26: =IF('03_Investitori'!C26="",DataOggi,'03_Investitori'!C26) -> 46160 | E26: =IF('03_Investitori'!H26="",0,-'03_Investitori'!H26) -> 0 | G26: =IFERROR(IF('10_NAV_Mensile'!O26="","",MAX(G25,'10_NAV_Mensile'!O26)),"") | H26: =IFERROR(IF(OR(G26="",'10_NAV_Mensile'!O26=""),"",'10_NAV_Mensile'!O26/G26-1),"")
A27: Volatilità Annualizzata | B27: =IFERROR(STDEV('10_NAV_Mensile'!$P$5:$P$124)*SQRT(12),0) -> 0.06891298 | D27: =IF('03_Investitori'!C27="",DataOggi,'03_Investitori'!C27) -> 46160 | E27: =IF('03_Investitori'!H27="",0,-'03_Investitori'!H27) -> 0 | G27: =IFERROR(IF('10_NAV_Mensile'!O27="","",MAX(G26,'10_NAV_Mensile'!O27)),"") | H27: =IFERROR(IF(OR(G27="",'10_NAV_Mensile'!O27=""),"",'10_NAV_Mensile'!O27/G27-1),"")
A28: Sharpe Ratio | B28: =IFERROR((AVERAGE('10_NAV_Mensile'!$P$5:$P$124)*12-RiskFree)/B27,0) -> -0.44360567 | D28: =IF('03_Investitori'!C28="",DataOggi,'03_Investitori'!C28) -> 46160 | E28: =IF('03_Investitori'!H28="",0,-'03_Investitori'!H28) -> 0 | G28: =IFERROR(IF('10_NAV_Mensile'!O28="","",MAX(G27,'10_NAV_Mensile'!O28)),"") | H28: =IFERROR(IF(OR(G28="",'10_NAV_Mensile'!O28=""),"",'10_NAV_Mensile'!O28/G28-1),"")
A29: Sortino Ratio | B29: =IFERROR((AVERAGE('10_NAV_Mensile'!$P$6:$P$124)*12-RiskFree)/(_xlfn.STDEV.P(IF('10_NAV_Mensile'!$P$6:$P$124<0,'10_NAV_Mensile'!$P$6:$P$124))*SQRT(12)),0) -> 0 | D29: =IF('03_Investitori'!C29="",DataOggi,'03_Investitori'!C29) -> 46160 | E29: =IF('03_Investitori'!H29="",0,-'03_Investitori'!H29) -> 0 | G29: =IFERROR(IF('10_NAV_Mensile'!O29="","",MAX(G28,'10_NAV_Mensile'!O29)),"") | H29: =IFERROR(IF(OR(G29="",'10_NAV_Mensile'!O29=""),"",'10_NAV_Mensile'!O29/G29-1),"")
A30: Max Drawdown | B30: =IFERROR(MIN($H$5:$H$124),0) -> -0.050029439 | D30: =IF('03_Investitori'!C30="",DataOggi,'03_Investitori'!C30) -> 46160 | E30: =IF('03_Investitori'!H30="",0,-'03_Investitori'!H30) -> 0 | G30: =IFERROR(IF('10_NAV_Mensile'!O30="","",MAX(G29,'10_NAV_Mensile'!O30)),"") | H30: =IFERROR(IF(OR(G30="",'10_NAV_Mensile'!O30=""),"",'10_NAV_Mensile'!O30/G30-1),"")
A31: # Mesi Positivi | B31: =COUNTIF('10_NAV_Mensile'!$P$5:$P$124,">0") -> 8 | D31: =IF('03_Investitori'!C31="",DataOggi,'03_Investitori'!C31) -> 46160 | E31: =IF('03_Investitori'!H31="",0,-'03_Investitori'!H31) -> 0 | G31: =IFERROR(IF('10_NAV_Mensile'!O31="","",MAX(G30,'10_NAV_Mensile'!O31)),"") | H31: =IFERROR(IF(OR(G31="",'10_NAV_Mensile'!O31=""),"",'10_NAV_Mensile'!O31/G31-1),"")
A32: # Mesi Totali | B32: =COUNT('10_NAV_Mensile'!$P$5:$P$124) -> 13 | D32: =IF('03_Investitori'!C32="",DataOggi,'03_Investitori'!C32) -> 46160 | E32: =IF('03_Investitori'!H32="",0,-'03_Investitori'!H32) -> 0 | G32: =IFERROR(IF('10_NAV_Mensile'!O32="","",MAX(G31,'10_NAV_Mensile'!O32)),"") | H32: =IFERROR(IF(OR(G32="",'10_NAV_Mensile'!O32=""),"",'10_NAV_Mensile'!O32/G32-1),"")
A33: Win Rate | B33: =IFERROR(B31/B32,0) -> 0.61538462 | D33: =IF('03_Investitori'!C33="",DataOggi,'03_Investitori'!C33) -> 46160 | E33: =IF('03_Investitori'!H33="",0,-'03_Investitori'!H33) -> 0 | G33: =IFERROR(IF('10_NAV_Mensile'!O33="","",MAX(G32,'10_NAV_Mensile'!O33)),"") | H33: =IFERROR(IF(OR(G33="",'10_NAV_Mensile'!O33=""),"",'10_NAV_Mensile'!O33/G33-1),"")
D34: =IF('03_Investitori'!C34="",DataOggi,'03_Investitori'!C34) -> 46160 | E34: =IF('03_Investitori'!H34="",0,-'03_Investitori'!H34) -> 0 | G34: =IFERROR(IF('10_NAV_Mensile'!O34="","",MAX(G33,'10_NAV_Mensile'!O34)),"") | H34: =IFERROR(IF(OR(G34="",'10_NAV_Mensile'!O34=""),"",'10_NAV_Mensile'!O34/G34-1),"")
D35: =IF('03_Investitori'!C35="",DataOggi,'03_Investitori'!C35) -> 46160 | E35: =IF('03_Investitori'!H35="",0,-'03_Investitori'!H35) -> 0 | G35: =IFERROR(IF('10_NAV_Mensile'!O35="","",MAX(G34,'10_NAV_Mensile'!O35)),"") | H35: =IFERROR(IF(OR(G35="",'10_NAV_Mensile'!O35=""),"",'10_NAV_Mensile'!O35/G35-1),"")
D36: =IF('03_Investitori'!C36="",DataOggi,'03_Investitori'!C36) -> 46160 | E36: =IF('03_Investitori'!H36="",0,-'03_Investitori'!H36) -> 0 | G36: =IFERROR(IF('10_NAV_Mensile'!O36="","",MAX(G35,'10_NAV_Mensile'!O36)),"") | H36: =IFERROR(IF(OR(G36="",'10_NAV_Mensile'!O36=""),"",'10_NAV_Mensile'!O36/G36-1),"")
D37: =IF('03_Investitori'!C37="",DataOggi,'03_Investitori'!C37) -> 46160 | E37: =IF('03_Investitori'!H37="",0,-'03_Investitori'!H37) -> 0 | G37: =IFERROR(IF('10_NAV_Mensile'!O37="","",MAX(G36,'10_NAV_Mensile'!O37)),"") | H37: =IFERROR(IF(OR(G37="",'10_NAV_Mensile'!O37=""),"",'10_NAV_Mensile'!O37/G37-1),"")
D38: =IF('03_Investitori'!C38="",DataOggi,'03_Investitori'!C38) -> 46160 | E38: =IF('03_Investitori'!H38="",0,-'03_Investitori'!H38) -> 0 | G38: =IFERROR(IF('10_NAV_Mensile'!O38="","",MAX(G37,'10_NAV_Mensile'!O38)),"") | H38: =IFERROR(IF(OR(G38="",'10_NAV_Mensile'!O38=""),"",'10_NAV_Mensile'!O38/G38-1),"")
D39: =IF('03_Investitori'!C39="",DataOggi,'03_Investitori'!C39) -> 46160 | E39: =IF('03_Investitori'!H39="",0,-'03_Investitori'!H39) -> 0 | G39: =IFERROR(IF('10_NAV_Mensile'!O39="","",MAX(G38,'10_NAV_Mensile'!O39)),"") | H39: =IFERROR(IF(OR(G39="",'10_NAV_Mensile'!O39=""),"",'10_NAV_Mensile'!O39/G39-1),"")
D40: =IF('03_Investitori'!C40="",DataOggi,'03_Investitori'!C40) -> 46160 | E40: =IF('03_Investitori'!H40="",0,-'03_Investitori'!H40) -> 0 | G40: =IFERROR(IF('10_NAV_Mensile'!O40="","",MAX(G39,'10_NAV_Mensile'!O40)),"") | H40: =IFERROR(IF(OR(G40="",'10_NAV_Mensile'!O40=""),"",'10_NAV_Mensile'!O40/G40-1),"")
D41: =IF('03_Investitori'!C41="",DataOggi,'03_Investitori'!C41) -> 46160 | E41: =IF('03_Investitori'!H41="",0,-'03_Investitori'!H41) -> 0 | G41: =IFERROR(IF('10_NAV_Mensile'!O41="","",MAX(G40,'10_NAV_Mensile'!O41)),"") | H41: =IFERROR(IF(OR(G41="",'10_NAV_Mensile'!O41=""),"",'10_NAV_Mensile'!O41/G41-1),"")
D42: =IF('03_Investitori'!C42="",DataOggi,'03_Investitori'!C42) -> 46160 | E42: =IF('03_Investitori'!H42="",0,-'03_Investitori'!H42) -> 0 | G42: =IFERROR(IF('10_NAV_Mensile'!O42="","",MAX(G41,'10_NAV_Mensile'!O42)),"") | H42: =IFERROR(IF(OR(G42="",'10_NAV_Mensile'!O42=""),"",'10_NAV_Mensile'!O42/G42-1),"")
D43: =IF('03_Investitori'!C43="",DataOggi,'03_Investitori'!C43) -> 46160 | E43: =IF('03_Investitori'!H43="",0,-'03_Investitori'!H43) -> 0 | G43: =IFERROR(IF('10_NAV_Mensile'!O43="","",MAX(G42,'10_NAV_Mensile'!O43)),"") | H43: =IFERROR(IF(OR(G43="",'10_NAV_Mensile'!O43=""),"",'10_NAV_Mensile'!O43/G43-1),"")
D44: =IF('03_Investitori'!C44="",DataOggi,'03_Investitori'!C44) -> 46160 | E44: =IF('03_Investitori'!H44="",0,-'03_Investitori'!H44) -> 0 | G44: =IFERROR(IF('10_NAV_Mensile'!O44="","",MAX(G43,'10_NAV_Mensile'!O44)),"") | H44: =IFERROR(IF(OR(G44="",'10_NAV_Mensile'!O44=""),"",'10_NAV_Mensile'!O44/G44-1),"")
D45: =IF('03_Investitori'!C45="",DataOggi,'03_Investitori'!C45) -> 46160 | E45: =IF('03_Investitori'!H45="",0,-'03_Investitori'!H45) -> 0 | G45: =IFERROR(IF('10_NAV_Mensile'!O45="","",MAX(G44,'10_NAV_Mensile'!O45)),"") | H45: =IFERROR(IF(OR(G45="",'10_NAV_Mensile'!O45=""),"",'10_NAV_Mensile'!O45/G45-1),"")
... D104: =IF('03_Investitori'!C104="",DataOggi,'03_Investitori'!C104) -> 46160 | E104: =IF('03_Investitori'!H104="",0,-'03_Investitori'!H104) -> 0 | G104: =IFERROR(IF('10_NAV_Mensile'!O104="","",MAX(G103,'10_NAV_Mensile'!O104)),"") | H104: =IFERROR(IF(OR(G104="",'10_NAV_Mensile'!O104=""),"",'10_NAV_Mensile'!O104/G104-1),"")
D105: =DataOggi -> 46160 | E105: =NAV_Curr -> 1971514.5 | G105: =IFERROR(IF('10_NAV_Mensile'!O105="","",MAX(G104,'10_NAV_Mensile'!O105)),"") | H105: =IFERROR(IF(OR(G105="",'10_NAV_Mensile'!O105=""),"",'10_NAV_Mensile'!O105/G105-1),"")
G106: =IFERROR(IF('10_NAV_Mensile'!O106="","",MAX(G105,'10_NAV_Mensile'!O106)),"") | H106: =IFERROR(IF(OR(G106="",'10_NAV_Mensile'!O106=""),"",'10_NAV_Mensile'!O106/G106-1),"")
G107: =IFERROR(IF('10_NAV_Mensile'!O107="","",MAX(G106,'10_NAV_Mensile'!O107)),"") | H107: =IFERROR(IF(OR(G107="",'10_NAV_Mensile'!O107=""),"",'10_NAV_Mensile'!O107/G107-1),"")
G108: =IFERROR(IF('10_NAV_Mensile'!O108="","",MAX(G107,'10_NAV_Mensile'!O108)),"") | H108: =IFERROR(IF(OR(G108="",'10_NAV_Mensile'!O108=""),"",'10_NAV_Mensile'!O108/G108-1),"")
G109: =IFERROR(IF('10_NAV_Mensile'!O109="","",MAX(G108,'10_NAV_Mensile'!O109)),"") | H109: =IFERROR(IF(OR(G109="",'10_NAV_Mensile'!O109=""),"",'10_NAV_Mensile'!O109/G109-1),"")
G110: =IFERROR(IF('10_NAV_Mensile'!O110="","",MAX(G109,'10_NAV_Mensile'!O110)),"") | H110: =IFERROR(IF(OR(G110="",'10_NAV_Mensile'!O110=""),"",'10_NAV_Mensile'!O110/G110-1),"")
G111: =IFERROR(IF('10_NAV_Mensile'!O111="","",MAX(G110,'10_NAV_Mensile'!O111)),"") | H111: =IFERROR(IF(OR(G111="",'10_NAV_Mensile'!O111=""),"",'10_NAV_Mensile'!O111/G111-1),"")
G112: =IFERROR(IF('10_NAV_Mensile'!O112="","",MAX(G111,'10_NAV_Mensile'!O112)),"") | H112: =IFERROR(IF(OR(G112="",'10_NAV_Mensile'!O112=""),"",'10_NAV_Mensile'!O112/G112-1),"")
G113: =IFERROR(IF('10_NAV_Mensile'!O113="","",MAX(G112,'10_NAV_Mensile'!O113)),"") | H113: =IFERROR(IF(OR(G113="",'10_NAV_Mensile'!O113=""),"",'10_NAV_Mensile'!O113/G113-1),"")
G114: =IFERROR(IF('10_NAV_Mensile'!O114="","",MAX(G113,'10_NAV_Mensile'!O114)),"") | H114: =IFERROR(IF(OR(G114="",'10_NAV_Mensile'!O114=""),"",'10_NAV_Mensile'!O114/G114-1),"")
G115: =IFERROR(IF('10_NAV_Mensile'!O115="","",MAX(G114,'10_NAV_Mensile'!O115)),"") | H115: =IFERROR(IF(OR(G115="",'10_NAV_Mensile'!O115=""),"",'10_NAV_Mensile'!O115/G115-1),"")
G116: =IFERROR(IF('10_NAV_Mensile'!O116="","",MAX(G115,'10_NAV_Mensile'!O116)),"") | H116: =IFERROR(IF(OR(G116="",'10_NAV_Mensile'!O116=""),"",'10_NAV_Mensile'!O116/G116-1),"")
G117: =IFERROR(IF('10_NAV_Mensile'!O117="","",MAX(G116,'10_NAV_Mensile'!O117)),"") | H117: =IFERROR(IF(OR(G117="",'10_NAV_Mensile'!O117=""),"",'10_NAV_Mensile'!O117/G117-1),"")
... G124: =IFERROR(IF('10_NAV_Mensile'!O124="","",MAX(G123,'10_NAV_Mensile'!O124)),"") | H124: =IFERROR(IF(OR(G124="",'10_NAV_Mensile'!O124=""),"",'10_NAV_Mensile'!O124/G124-1),"")

Sheet 12_Perf_Investitori
A1: Performance per Investitore
A2: Current Value = Quote × NAV/Unit corrente. IRR annualizzato calcolato come (Current/Capital)^(1/anni)-1. Hurdle Amount = Capital × ((1+Hurdle)^anni − 1).
A4: # | B4: Investitore | C4: Tipo | D4: Data Sottoscr. | E4: Capitale EUR | F4: Quote | G4: Anni Trascorsi | H4: NAV/Unit @ Sub | I4: Current Value EUR | J4: MOIC | K4: IRR Annualizz.
A5: =IF('03_Investitori'!B5="","",ROW()-4) -> 1 | B5: ='03_Investitori'!B5 -> Osy Harrison | C5: =IF('03_Investitori'!D5="","",'03_Investitori'!D5) -> LP | D5: =IF('03_Investitori'!C5="","",'03_Investitori'!C5) -> 45736 | E5: =IF('03_Investitori'!H5="","",'03_Investitori'!H5) -> 500000 | F5: =IF('03_Investitori'!J5="","",'03_Investitori'!J5) -> 500000 | G5: =IF('03_Investitori'!C5="","",(DataOggi-'03_Investitori'!C5)/365.25) -> 1.1608487 | H5: =IF('03_Investitori'!I5="","",'03_Investitori'!I5) -> 1 | I5: =IF(F5="","",F5*NAVperUnit_Curr) -> 492878.62 | J5: =IFERROR(IF(E5=0,"",I5/E5),"") -> 0.98575725 | K5: =IFERROR(IF(OR(E5="",E5=0,G5=0,G5=""),"",(I5/E5)^(1/G5)-1),"") -> -0.01228143
A6: =IF('03_Investitori'!B6="","",ROW()-4) -> 2 | B6: ='03_Investitori'!B6 -> Bradley Jackson | C6: =IF('03_Investitori'!D6="","",'03_Investitori'!D6) -> LP | D6: =IF('03_Investitori'!C6="","",'03_Investitori'!C6) -> 45904 | E6: =IF('03_Investitori'!H6="","",'03_Investitori'!H6) -> 500000 | F6: =IF('03_Investitori'!J6="","",'03_Investitori'!J6) -> 500000 | G6: =IF('03_Investitori'!C6="","",(DataOggi-'03_Investitori'!C6)/365.25) -> 0.7008898 | H6: =IF('03_Investitori'!I6="","",'03_Investitori'!I6) -> 1 | I6: =IF(F6="","",F6*NAVperUnit_Curr) -> 492878.62 | J6: =IFERROR(IF(E6=0,"",I6/E6),"") -> 0.98575725 | K6: =IFERROR(IF(OR(E6="",E6=0,G6=0,G6=""),"",(I6/E6)^(1/G6)-1),"") -> -0.020259031
A7: =IF('03_Investitori'!B7="","",ROW()-4) -> 3 | B7: ='03_Investitori'!B7 -> Grant Kauffman | C7: =IF('03_Investitori'!D7="","",'03_Investitori'!D7) -> LP | D7: =IF('03_Investitori'!C7="","",'03_Investitori'!C7) -> 45910 | E7: =IF('03_Investitori'!H7="","",'03_Investitori'!H7) -> 500000 | F7: =IF('03_Investitori'!J7="","",'03_Investitori'!J7) -> 500000 | G7: =IF('03_Investitori'!C7="","",(DataOggi-'03_Investitori'!C7)/365.25) -> 0.6844627 | H7: =IF('03_Investitori'!I7="","",'03_Investitori'!I7) -> 1 | I7: =IF(F7="","",F7*NAVperUnit_Curr) -> 492878.62 | J7: =IFERROR(IF(E7=0,"",I7/E7),"") -> 0.98575725 | K7: =IFERROR(IF(OR(E7="",E7=0,G7=0,G7=""),"",(I7/E7)^(1/G7)-1),"") -> -0.020740171
A8: =IF('03_Investitori'!B8="","",ROW()-4) -> 4 | B8: ='03_Investitori'!B8 -> Esra Sertoglu | C8: =IF('03_Investitori'!D8="","",'03_Investitori'!D8) -> LP | D8: =IF('03_Investitori'!C8="","",'03_Investitori'!C8) -> 46097 | E8: =IF('03_Investitori'!H8="","",'03_Investitori'!H8) -> 500000 | F8: =IF('03_Investitori'!J8="","",'03_Investitori'!J8) -> 500000 | G8: =IF('03_Investitori'!C8="","",(DataOggi-'03_Investitori'!C8)/365.25) -> 0.1724846 | H8: =IF('03_Investitori'!I8="","",'03_Investitori'!I8) -> 1 | I8: =IF(F8="","",F8*NAVperUnit_Curr) -> 492878.62 | J8: =IFERROR(IF(E8=0,"",I8/E8),"") -> 0.98575725 | K8: =IFERROR(IF(OR(E8="",E8=0,G8=0,G8=""),"",(I8/E8)^(1/G8)-1),"") -> -0.079803215
A9: =IF('03_Investitori'!B9="","",ROW()-4) | B9: ='03_Investitori'!B9 -> 0 | C9: =IF('03_Investitori'!D9="","",'03_Investitori'!D9) | D9: =IF('03_Investitori'!C9="","",'03_Investitori'!C9) | E9: =IF('03_Investitori'!H9="","",'03_Investitori'!H9) | F9: =IF('03_Investitori'!J9="","",'03_Investitori'!J9) | G9: =IF('03_Investitori'!C9="","",(DataOggi-'03_Investitori'!C9)/365.25) | H9: =IF('03_Investitori'!I9="","",'03_Investitori'!I9) | I9: =IF(F9="","",F9*NAVperUnit_Curr) | J9: =IFERROR(IF(E9=0,"",I9/E9),"") | K9: =IFERROR(IF(OR(E9="",E9=0,G9=0,G9=""),"",(I9/E9)^(1/G9)-1),"")
A10: =IF('03_Investitori'!B10="","",ROW()-4) | B10: ='03_Investitori'!B10 -> 0 | C10: =IF('03_Investitori'!D10="","",'03_Investitori'!D10) | D10: =IF('03_Investitori'!C10="","",'03_Investitori'!C10) | E10: =IF('03_Investitori'!H10="","",'03_Investitori'!H10) | F10: =IF('03_Investitori'!J10="","",'03_Investitori'!J10) | G10: =IF('03_Investitori'!C10="","",(DataOggi-'03_Investitori'!C10)/365.25) | H10: =IF('03_Investitori'!I10="","",'03_Investitori'!I10) | I10: =IF(F10="","",F10*NAVperUnit_Curr) | J10: =IFERROR(IF(E10=0,"",I10/E10),"") | K10: =IFERROR(IF(OR(E10="",E10=0,G10=0,G10=""),"",(I10/E10)^(1/G10)-1),"")
A11: =IF('03_Investitori'!B11="","",ROW()-4) | B11: ='03_Investitori'!B11 -> 0 | C11: =IF('03_Investitori'!D11="","",'03_Investitori'!D11) | D11: =IF('03_Investitori'!C11="","",'03_Investitori'!C11) | E11: =IF('03_Investitori'!H11="","",'03_Investitori'!H11) | F11: =IF('03_Investitori'!J11="","",'03_Investitori'!J11) | G11: =IF('03_Investitori'!C11="","",(DataOggi-'03_Investitori'!C11)/365.25) | H11: =IF('03_Investitori'!I11="","",'03_Investitori'!I11) | I11: =IF(F11="","",F11*NAVperUnit_Curr) | J11: =IFERROR(IF(E11=0,"",I11/E11),"") | K11: =IFERROR(IF(OR(E11="",E11=0,G11=0,G11=""),"",(I11/E11)^(1/G11)-1),"")
A12: =IF('03_Investitori'!B12="","",ROW()-4) | B12: ='03_Investitori'!B12 -> 0 | C12: =IF('03_Investitori'!D12="","",'03_Investitori'!D12) | D12: =IF('03_Investitori'!C12="","",'03_Investitori'!C12) | E12: =IF('03_Investitori'!H12="","",'03_Investitori'!H12) | F12: =IF('03_Investitori'!J12="","",'03_Investitori'!J12) | G12: =IF('03_Investitori'!C12="","",(DataOggi-'03_Investitori'!C12)/365.25) | H12: =IF('03_Investitori'!I12="","",'03_Investitori'!I12) | I12: =IF(F12="","",F12*NAVperUnit_Curr) | J12: =IFERROR(IF(E12=0,"",I12/E12),"") | K12: =IFERROR(IF(OR(E12="",E12=0,G12=0,G12=""),"",(I12/E12)^(1/G12)-1),"")
A13: =IF('03_Investitori'!B13="","",ROW()-4) | B13: ='03_Investitori'!B13 -> 0 | C13: =IF('03_Investitori'!D13="","",'03_Investitori'!D13) | D13: =IF('03_Investitori'!C13="","",'03_Investitori'!C13) | E13: =IF('03_Investitori'!H13="","",'03_Investitori'!H13) | F13: =IF('03_Investitori'!J13="","",'03_Investitori'!J13) | G13: =IF('03_Investitori'!C13="","",(DataOggi-'03_Investitori'!C13)/365.25) | H13: =IF('03_Investitori'!I13="","",'03_Investitori'!I13) | I13: =IF(F13="","",F13*NAVperUnit_Curr) | J13: =IFERROR(IF(E13=0,"",I13/E13),"") | K13: =IFERROR(IF(OR(E13="",E13=0,G13=0,G13=""),"",(I13/E13)^(1/G13)-1),"")
A14: =IF('03_Investitori'!B14="","",ROW()-4) | B14: ='03_Investitori'!B14 -> 0 | C14: =IF('03_Investitori'!D14="","",'03_Investitori'!D14) | D14: =IF('03_Investitori'!C14="","",'03_Investitori'!C14) | E14: =IF('03_Investitori'!H14="","",'03_Investitori'!H14) | F14: =IF('03_Investitori'!J14="","",'03_Investitori'!J14) | G14: =IF('03_Investitori'!C14="","",(DataOggi-'03_Investitori'!C14)/365.25) | H14: =IF('03_Investitori'!I14="","",'03_Investitori'!I14) | I14: =IF(F14="","",F14*NAVperUnit_Curr) | J14: =IFERROR(IF(E14=0,"",I14/E14),"") | K14: =IFERROR(IF(OR(E14="",E14=0,G14=0,G14=""),"",(I14/E14)^(1/G14)-1),"")
A15: =IF('03_Investitori'!B15="","",ROW()-4) | B15: ='03_Investitori'!B15 -> 0 | C15: =IF('03_Investitori'!D15="","",'03_Investitori'!D15) | D15: =IF('03_Investitori'!C15="","",'03_Investitori'!C15) | E15: =IF('03_Investitori'!H15="","",'03_Investitori'!H15) | F15: =IF('03_Investitori'!J15="","",'03_Investitori'!J15) | G15: =IF('03_Investitori'!C15="","",(DataOggi-'03_Investitori'!C15)/365.25) | H15: =IF('03_Investitori'!I15="","",'03_Investitori'!I15) | I15: =IF(F15="","",F15*NAVperUnit_Curr) | J15: =IFERROR(IF(E15=0,"",I15/E15),"") | K15: =IFERROR(IF(OR(E15="",E15=0,G15=0,G15=""),"",(I15/E15)^(1/G15)-1),"")
A16: =IF('03_Investitori'!B16="","",ROW()-4) | B16: ='03_Investitori'!B16 -> 0 | C16: =IF('03_Investitori'!D16="","",'03_Investitori'!D16) | D16: =IF('03_Investitori'!C16="","",'03_Investitori'!C16) | E16: =IF('03_Investitori'!H16="","",'03_Investitori'!H16) | F16: =IF('03_Investitori'!J16="","",'03_Investitori'!J16) | G16: =IF('03_Investitori'!C16="","",(DataOggi-'03_Investitori'!C16)/365.25) | H16: =IF('03_Investitori'!I16="","",'03_Investitori'!I16) | I16: =IF(F16="","",F16*NAVperUnit_Curr) | J16: =IFERROR(IF(E16=0,"",I16/E16),"") | K16: =IFERROR(IF(OR(E16="",E16=0,G16=0,G16=""),"",(I16/E16)^(1/G16)-1),"")
... A104: =IF('03_Investitori'!B104="","",ROW()-4) | B104: ='03_Investitori'!B104 -> 0 | C104: =IF('03_Investitori'!D104="","",'03_Investitori'!D104) | D104: =IF('03_Investitori'!C104="","",'03_Investitori'!C104) | E104: =IF('03_Investitori'!H104="","",'03_Investitori'!H104) | F104: =IF('03_Investitori'!J104="","",'03_Investitori'!J104) | G104: =IF('03_Investitori'!C104="","",(DataOggi-'03_Investitori'!C104)/365.25) | H104: =IF('03_Investitori'!I104="","",'03_Investitori'!I104) | I104: =IF(F104="","",F104*NAVperUnit_Curr) | J104: =IFERROR(IF(E104=0,"",I104/E104),"") | K104: =IFERROR(IF(OR(E104="",E104=0,G104=0,G104=""),"",(I104/E104)^(1/G104)-1),"")
B106: TOTALE LP+GP | E106: =SUMIF(E5:E105,"<>") -> 2000000 | F106: =SUMIF(F5:F105,"<>") -> 2000000 | I106: =SUMIF(I5:I105,"<>") -> 1971514.5 | J106: =IFERROR(I106/E106,0) -> 0.98575725

Sheet 13_Waterfall
A2: Assume distribuzione integrale del NAV corrente alla data odierna. Solo gli LP partecipano all'hurdle; il GP riceve solo il carry. Le quote GP nella tabella Investitori vengono trattate come LP nei tier 1 e 2 (return of capital + preferred).
A4: Parametri Aggregati | K4: Investitore | L4: Cap EUR | M4: Anni | N4: Hurdle Acc. EUR
A5: Capitale LP+GP Totale EUR | B5: =Capital_Tot -> 2000000 | K5: =IF('03_Investitori'!B5="","",'03_Investitori'!B5) -> Osy Harrison | L5: =IF('03_Investitori'!H5="",0,'03_Investitori'!H5) -> 500000 | M5: =IF('03_Investitori'!C5="",0,(DataOggi-'03_Investitori'!C5)/365.25) -> 1.1608487 | N5: =IF(L5=0,0,L5*((1+Hurdle)^M5-1)) -> 29136.323
A6: Hurdle Rate (annuo) | B6: =Hurdle -> 0.05 | K6: =IF('03_Investitori'!B6="","",'03_Investitori'!B6) -> Bradley Jackson | L6: =IF('03_Investitori'!H6="",0,'03_Investitori'!H6) -> 500000 | M6: =IF('03_Investitori'!C6="",0,(DataOggi-'03_Investitori'!C6)/365.25) -> 0.7008898 | N6: =IF(L6=0,0,L6*((1+Hurdle)^M6-1)) -> 17393.976
A7: Hurdle Amount Totale EUR | B7: =SUM(N5:N104) -> 67735.291 | K7: =IF('03_Investitori'!B7="","",'03_Investitori'!B7) -> Grant Kauffman | L7: =IF('03_Investitori'!H7="",0,'03_Investitori'!H7) -> 500000 | M7: =IF('03_Investitori'!C7="",0,(DataOggi-'03_Investitori'!C7)/365.25) -> 0.6844627 | N7: =IF(L7=0,0,L7*((1+Hurdle)^M7-1)) -> 16979.461
A8: NAV Corrente EUR | B8: =NAV_Curr -> 1971514.5 | K8: =IF('03_Investitori'!B8="","",'03_Investitori'!B8) -> Esra Sertoglu | L8: =IF('03_Investitori'!H8="",0,'03_Investitori'!H8) -> 500000 | M8: =IF('03_Investitori'!C8="",0,(DataOggi-'03_Investitori'!C8)/365.25) -> 0.1724846 | N8: =IF(L8=0,0,L8*((1+Hurdle)^M8-1)) -> 4225.5311
A9: Profitto Totale EUR | B9: =B8-B5 -> -28485.504 | K9: =IF('03_Investitori'!B9="","",'03_Investitori'!B9) | L9: =IF('03_Investitori'!H9="",0,'03_Investitori'!H9) -> 0 | M9: =IF('03_Investitori'!C9="",0,(DataOggi-'03_Investitori'!C9)/365.25) -> 0 | N9: =IF(L9=0,0,L9*((1+Hurdle)^M9-1)) -> 0
K10: =IF('03_Investitori'!B10="","",'03_Investitori'!B10) | L10: =IF('03_Investitori'!H10="",0,'03_Investitori'!H10) -> 0 | M10: =IF('03_Investitori'!C10="",0,(DataOggi-'03_Investitori'!C10)/365.25) -> 0 | N10: =IF(L10=0,0,L10*((1+Hurdle)^M10-1)) -> 0
K11: =IF('03_Investitori'!B11="","",'03_Investitori'!B11) | L11: =IF('03_Investitori'!H11="",0,'03_Investitori'!H11) -> 0 | M11: =IF('03_Investitori'!C11="",0,(DataOggi-'03_Investitori'!C11)/365.25) -> 0 | N11: =IF(L11=0,0,L11*((1+Hurdle)^M11-1)) -> 0
A12: Calcolo Waterfall | K12: =IF('03_Investitori'!B12="","",'03_Investitori'!B12) | L12: =IF('03_Investitori'!H12="",0,'03_Investitori'!H12) -> 0 | M12: =IF('03_Investitori'!C12="",0,(DataOggi-'03_Investitori'!C12)/365.25) -> 0 | N12: =IF(L12=0,0,L12*((1+Hurdle)^M12-1)) -> 0
A13: Tier | B13: LP EUR | C13: GP EUR | D13: Beneficiari | K13: =IF('03_Investitori'!B13="","",'03_Investitori'!B13) | L13: =IF('03_Investitori'!H13="",0,'03_Investitori'!H13) -> 0 | M13: =IF('03_Investitori'!C13="",0,(DataOggi-'03_Investitori'!C13)/365.25) -> 0 | N13: =IF(L13=0,0,L13*((1+Hurdle)^M13-1)) -> 0
A14: Tier 1 — Return of Capital LP+GP | B14: =MIN(NAV_Curr,B5) -> 1971514.5 | C14: =0 -> 0 | D14: TUTTI | K14: =IF('03_Investitori'!B14="","",'03_Investitori'!B14) | L14: =IF('03_Investitori'!H14="",0,'03_Investitori'!H14) -> 0 | M14: =IF('03_Investitori'!C14="",0,(DataOggi-'03_Investitori'!C14)/365.25) -> 0 | N14: =IF(L14=0,0,L14*((1+Hurdle)^M14-1)) -> 0
A15: Resta dopo Tier 1 | B15: =NAV_Curr-B14 -> 0 | K15: =IF('03_Investitori'!B15="","",'03_Investitori'!B15) | L15: =IF('03_Investitori'!H15="",0,'03_Investitori'!H15) -> 0 | M15: =IF('03_Investitori'!C15="",0,(DataOggi-'03_Investitori'!C15)/365.25) -> 0 | N15: =IF(L15=0,0,L15*((1+Hurdle)^M15-1)) -> 0
A16: Tier 2 — Preferred 5% (hurdle) | B16: =MIN(B15,B7) -> 0 | C16: =0 -> 0 | D16: LP+GP | K16: =IF('03_Investitori'!B16="","",'03_Investitori'!B16) | L16: =IF('03_Investitori'!H16="",0,'03_Investitori'!H16) -> 0 | M16: =IF('03_Investitori'!C16="",0,(DataOggi-'03_Investitori'!C16)/365.25) -> 0 | N16: =IF(L16=0,0,L16*((1+Hurdle)^M16-1)) -> 0
A17: Resta dopo Tier 2 | B17: =B15-B16 -> 0 | K17: =IF('03_Investitori'!B17="","",'03_Investitori'!B17) | L17: =IF('03_Investitori'!H17="",0,'03_Investitori'!H17) -> 0 | M17: =IF('03_Investitori'!C17="",0,(DataOggi-'03_Investitori'!C17)/365.25) -> 0 | N17: =IF(L17=0,0,L17*((1+Hurdle)^M17-1)) -> 0
A18: Tier 3 — GP Catch-up | B18: =0 -> 0 | C18: =MIN(B17,B16*CatchUpPct/(1-CatchUpPct)) -> 0 | D18: GP | K18: =IF('03_Investitori'!B18="","",'03_Investitori'!B18) | L18: =IF('03_Investitori'!H18="",0,'03_Investitori'!H18) -> 0 | M18: =IF('03_Investitori'!C18="",0,(DataOggi-'03_Investitori'!C18)/365.25) -> 0 | N18: =IF(L18=0,0,L18*((1+Hurdle)^M18-1)) -> 0
A19: Resta dopo Tier 3 | B19: =B17-C18 -> 0 | K19: =IF('03_Investitori'!B19="","",'03_Investitori'!B19) | L19: =IF('03_Investitori'!H19="",0,'03_Investitori'!H19) -> 0 | M19: =IF('03_Investitori'!C19="",0,(DataOggi-'03_Investitori'!C19)/365.25) -> 0 | N19: =IF(L19=0,0,L19*((1+Hurdle)^M19-1)) -> 0
A20: Tier 4 — Split LP/GP | B20: =B19*(1-GPCarry) -> 0 | C20: =B19*GPCarry -> 0 | D20: 80/20 | K20: =IF('03_Investitori'!B20="","",'03_Investitori'!B20) | L20: =IF('03_Investitori'!H20="",0,'03_Investitori'!H20) -> 0 | M20: =IF('03_Investitori'!C20="",0,(DataOggi-'03_Investitori'!C20)/365.25) -> 0 | N20: =IF(L20=0,0,L20*((1+Hurdle)^M20-1)) -> 0
K21: =IF('03_Investitori'!B21="","",'03_Investitori'!B21) | L21: =IF('03_Investitori'!H21="",0,'03_Investitori'!H21) -> 0 | M21: =IF('03_Investitori'!C21="",0,(DataOggi-'03_Investitori'!C21)/365.25) -> 0 | N21: =IF(L21=0,0,L21*((1+Hurdle)^M21-1)) -> 0
A22: TOTALE DISTRIBUITO | B22: =B14+B16+B20 -> 1971514.5 | C22: =C18+C20 -> 0 | K22: =IF('03_Investitori'!B22="","",'03_Investitori'!B22) | L22: =IF('03_Investitori'!H22="",0,'03_Investitori'!H22) -> 0 | M22: =IF('03_Investitori'!C22="",0,(DataOggi-'03_Investitori'!C22)/365.25) -> 0 | N22: =IF(L22=0,0,L22*((1+Hurdle)^M22-1)) -> 0
A23: Check (LP+GP = NAV) | B23: =B22+C22 -> 1971514.5 | C23: =IF(ROUND(B23-NAV_Curr,2)=0,"OK ✓","DIFF: "&ROUND(B23-NAV_Curr,2)) -> OK ✓ | K23: =IF('03_Investitori'!B23="","",'03_Investitori'!B23) | L23: =IF('03_Investitori'!H23="",0,'03_Investitori'!H23) -> 0 | M23: =IF('03_Investitori'!C23="",0,(DataOggi-'03_Investitori'!C23)/365.25) -> 0 | N23: =IF(L23=0,0,L23*((1+Hurdle)^M23-1)) -> 0
K24: =IF('03_Investitori'!B24="","",'03_Investitori'!B24) | L24: =IF('03_Investitori'!H24="",0,'03_Investitori'!H24) -> 0 | M24: =IF('03_Investitori'!C24="",0,(DataOggi-'03_Investitori'!C24)/365.25) -> 0 | N24: =IF(L24=0,0,L24*((1+Hurdle)^M24-1)) -> 0
K25: =IF('03_Investitori'!B25="","",'03_Investitori'!B25) | L25: =IF('03_Investitori'!H25="",0,'03_Investitori'!H25) -> 0 | M25: =IF('03_Investitori'!C25="",0,(DataOggi-'03_Investitori'!C25)/365.25) -> 0 | N25: =IF(L25=0,0,L25*((1+Hurdle)^M25-1)) -> 0
A26: Distribuzione per Investitore (pro-rata) | K26: =IF('03_Investitori'!B26="","",'03_Investitori'!B26) | L26: =IF('03_Investitori'!H26="",0,'03_Investitori'!H26) -> 0 | M26: =IF('03_Investitori'!C26="",0,(DataOggi-'03_Investitori'!C26)/365.25) -> 0 | N26: =IF(L26=0,0,L26*((1+Hurdle)^M26-1)) -> 0
A27: Investitore | B27: Tipo | C27: Capitale EUR | D27: Hurdle Acc. EUR | E27: T1 ROC | F27: T2 Preferred | G27: T4 Split LP | H27: Totale Distribuito | K27: =IF('03_Investitori'!B27="","",'03_Investitori'!B27) | L27: =IF('03_Investitori'!H27="",0,'03_Investitori'!H27) -> 0 | M27: =IF('03_Investitori'!C27="",0,(DataOggi-'03_Investitori'!C27)/365.25) -> 0 | N27: =IF(L27=0,0,L27*((1+Hurdle)^M27-1)) -> 0
A28: =IF('03_Investitori'!B5="","",'03_Investitori'!B5) -> Osy Harrison | B28: =IF('03_Investitori'!D5="","",'03_Investitori'!D5) -> LP | C28: =IF('03_Investitori'!H5="","",'03_Investitori'!H5) -> 500000 | D28: =N5 -> 29136.323 | E28: =IF(OR(C28="",$B$5=0),0,$B$14*C28/$B$5) -> 492878.62 | F28: =IF(OR($B$7=0,D28=""),0,$B$16*D28/$B$7) -> 0 | G28: =IF(OR(C28="",$B$5=0),0,$B$20*C28/$B$5) -> 0 | H28: =E28+F28+G28 -> 492878.62 | K28: =IF('03_Investitori'!B28="","",'03_Investitori'!B28) | L28: =IF('03_Investitori'!H28="",0,'03_Investitori'!H28) -> 0 | M28: =IF('03_Investitori'!C28="",0,(DataOggi-'03_Investitori'!C28)/365.25) -> 0 | N28: =IF(L28=0,0,L28*((1+Hurdle)^M28-1)) -> 0
A29: =IF('03_Investitori'!B6="","",'03_Investitori'!B6) -> Bradley Jackson | B29: =IF('03_Investitori'!D6="","",'03_Investitori'!D6) -> LP | C29: =IF('03_Investitori'!H6="","",'03_Investitori'!H6) -> 500000 | D29: =N6 -> 17393.976 | E29: =IF(OR(C29="",$B$5=0),0,$B$14*C29/$B$5) -> 492878.62 | F29: =IF(OR($B$7=0,D29=""),0,$B$16*D29/$B$7) -> 0 | G29: =IF(OR(C29="",$B$5=0),0,$B$20*C29/$B$5) -> 0 | H29: =E29+F29+G29 -> 492878.62 | K29: =IF('03_Investitori'!B29="","",'03_Investitori'!B29) | L29: =IF('03_Investitori'!H29="",0,'03_Investitori'!H29) -> 0 | M29: =IF('03_Investitori'!C29="",0,(DataOggi-'03_Investitori'!C29)/365.25) -> 0 | N29: =IF(L29=0,0,L29*((1+Hurdle)^M29-1)) -> 0
A30: =IF('03_Investitori'!B7="","",'03_Investitori'!B7) -> Grant Kauffman | B30: =IF('03_Investitori'!D7="","",'03_Investitori'!D7) -> LP | C30: =IF('03_Investitori'!H7="","",'03_Investitori'!H7) -> 500000 | D30: =N7 -> 16979.461 | E30: =IF(OR(C30="",$B$5=0),0,$B$14*C30/$B$5) -> 492878.62 | F30: =IF(OR($B$7=0,D30=""),0,$B$16*D30/$B$7) -> 0 | G30: =IF(OR(C30="",$B$5=0),0,$B$20*C30/$B$5) -> 0 | H30: =E30+F30+G30 -> 492878.62 | K30: =IF('03_Investitori'!B30="","",'03_Investitori'!B30) | L30: =IF('03_Investitori'!H30="",0,'03_Investitori'!H30) -> 0 | M30: =IF('03_Investitori'!C30="",0,(DataOggi-'03_Investitori'!C30)/365.25) -> 0 | N30: =IF(L30=0,0,L30*((1+Hurdle)^M30-1)) -> 0
A31: =IF('03_Investitori'!B8="","",'03_Investitori'!B8) -> Esra Sertoglu | B31: =IF('03_Investitori'!D8="","",'03_Investitori'!D8) -> LP | C31: =IF('03_Investitori'!H8="","",'03_Investitori'!H8) -> 500000 | D31: =N8 -> 4225.5311 | E31: =IF(OR(C31="",$B$5=0),0,$B$14*C31/$B$5) -> 492878.62 | F31: =IF(OR($B$7=0,D31=""),0,$B$16*D31/$B$7) -> 0 | G31: =IF(OR(C31="",$B$5=0),0,$B$20*C31/$B$5) -> 0 | H31: =E31+F31+G31 -> 492878.62 | K31: =IF('03_Investitori'!B31="","",'03_Investitori'!B31) | L31: =IF('03_Investitori'!H31="",0,'03_Investitori'!H31) -> 0 | M31: =IF('03_Investitori'!C31="",0,(DataOggi-'03_Investitori'!C31)/365.25) -> 0 | N31: =IF(L31=0,0,L31*((1+Hurdle)^M31-1)) -> 0
A32: =IF('03_Investitori'!B9="","",'03_Investitori'!B9) | B32: =IF('03_Investitori'!D9="","",'03_Investitori'!D9) | C32: =IF('03_Investitori'!H9="","",'03_Investitori'!H9) | D32: =N9 -> 0 | E32: =IF(OR(C32="",$B$5=0),0,$B$14*C32/$B$5) -> 0 | F32: =IF(OR($B$7=0,D32=""),0,$B$16*D32/$B$7) -> 0 | G32: =IF(OR(C32="",$B$5=0),0,$B$20*C32/$B$5) -> 0 | H32: =E32+F32+G32 -> 0 | K32: =IF('03_Investitori'!B32="","",'03_Investitori'!B32) | L32: =IF('03_Investitori'!H32="",0,'03_Investitori'!H32) -> 0 | M32: =IF('03_Investitori'!C32="",0,(DataOggi-'03_Investitori'!C32)/365.25) -> 0 | N32: =IF(L32=0,0,L32*((1+Hurdle)^M32-1)) -> 0
A33: =IF('03_Investitori'!B10="","",'03_Investitori'!B10) | B33: =IF('03_Investitori'!D10="","",'03_Investitori'!D10) | C33: =IF('03_Investitori'!H10="","",'03_Investitori'!H10) | D33: =N10 -> 0 | E33: =IF(OR(C33="",$B$5=0),0,$B$14*C33/$B$5) -> 0 | F33: =IF(OR($B$7=0,D33=""),0,$B$16*D33/$B$7) -> 0 | G33: =IF(OR(C33="",$B$5=0),0,$B$20*C33/$B$5) -> 0 | H33: =E33+F33+G33 -> 0 | K33: =IF('03_Investitori'!B33="","",'03_Investitori'!B33) | L33: =IF('03_Investitori'!H33="",0,'03_Investitori'!H33) -> 0 | M33: =IF('03_Investitori'!C33="",0,(DataOggi-'03_Investitori'!C33)/365.25) -> 0 | N33: =IF(L33=0,0,L33*((1+Hurdle)^M33-1)) -> 0
A34: =IF('03_Investitori'!B11="","",'03_Investitori'!B11) | B34: =IF('03_Investitori'!D11="","",'03_Investitori'!D11) | C34: =IF('03_Investitori'!H11="","",'03_Investitori'!H11) | D34: =N11 -> 0 | E34: =IF(OR(C34="",$B$5=0),0,$B$14*C34/$B$5) -> 0 | F34: =IF(OR($B$7=0,D34=""),0,$B$16*D34/$B$7) -> 0 | G34: =IF(OR(C34="",$B$5=0),0,$B$20*C34/$B$5) -> 0 | H34: =E34+F34+G34 -> 0 | K34: =IF('03_Investitori'!B34="","",'03_Investitori'!B34) | L34: =IF('03_Investitori'!H34="",0,'03_Investitori'!H34) -> 0 | M34: =IF('03_Investitori'!C34="",0,(DataOggi-'03_Investitori'!C34)/365.25) -> 0 | N34: =IF(L34=0,0,L34*((1+Hurdle)^M34-1)) -> 0
A35: =IF('03_Investitori'!B12="","",'03_Investitori'!B12) | B35: =IF('03_Investitori'!D12="","",'03_Investitori'!D12) | C35: =IF('03_Investitori'!H12="","",'03_Investitori'!H12) | D35: =N12 -> 0 | E35: =IF(OR(C35="",$B$5=0),0,$B$14*C35/$B$5) -> 0 | F35: =IF(OR($B$7=0,D35=""),0,$B$16*D35/$B$7) -> 0 | G35: =IF(OR(C35="",$B$5=0),0,$B$20*C35/$B$5) -> 0 | H35: =E35+F35+G35 -> 0 | K35: =IF('03_Investitori'!B35="","",'03_Investitori'!B35) | L35: =IF('03_Investitori'!H35="",0,'03_Investitori'!H35) -> 0 | M35: =IF('03_Investitori'!C35="",0,(DataOggi-'03_Investitori'!C35)/365.25) -> 0 | N35: =IF(L35=0,0,L35*((1+Hurdle)^M35-1)) -> 0
A36: =IF('03_Investitori'!B13="","",'03_Investitori'!B13) | B36: =IF('03_Investitori'!D13="","",'03_Investitori'!D13) | C36: =IF('03_Investitori'!H13="","",'03_Investitori'!H13) | D36: =N13 -> 0 | E36: =IF(OR(C36="",$B$5=0),0,$B$14*C36/$B$5) -> 0 | F36: =IF(OR($B$7=0,D36=""),0,$B$16*D36/$B$7) -> 0 | G36: =IF(OR(C36="",$B$5=0),0,$B$20*C36/$B$5) -> 0 | H36: =E36+F36+G36 -> 0 | K36: =IF('03_Investitori'!B36="","",'03_Investitori'!B36) | L36: =IF('03_Investitori'!H36="",0,'03_Investitori'!H36) -> 0 | M36: =IF('03_Investitori'!C36="",0,(DataOggi-'03_Investitori'!C36)/365.25) -> 0 | N36: =IF(L36=0,0,L36*((1+Hurdle)^M36-1)) -> 0
A37: =IF('03_Investitori'!B14="","",'03_Investitori'!B14) | B37: =IF('03_Investitori'!D14="","",'03_Investitori'!D14) | C37: =IF('03_Investitori'!H14="","",'03_Investitori'!H14) | D37: =N14 -> 0 | E37: =IF(OR(C37="",$B$5=0),0,$B$14*C37/$B$5) -> 0 | F37: =IF(OR($B$7=0,D37=""),0,$B$16*D37/$B$7) -> 0 | G37: =IF(OR(C37="",$B$5=0),0,$B$20*C37/$B$5) -> 0 | H37: =E37+F37+G37 -> 0 | K37: =IF('03_Investitori'!B37="","",'03_Investitori'!B37) | L37: =IF('03_Investitori'!H37="",0,'03_Investitori'!H37) -> 0 | M37: =IF('03_Investitori'!C37="",0,(DataOggi-'03_Investitori'!C37)/365.25) -> 0 | N37: =IF(L37=0,0,L37*((1+Hurdle)^M37-1)) -> 0
A38: =IF('03_Investitori'!B15="","",'03_Investitori'!B15) | B38: =IF('03_Investitori'!D15="","",'03_Investitori'!D15) | C38: =IF('03_Investitori'!H15="","",'03_Investitori'!H15) | D38: =N15 -> 0 | E38: =IF(OR(C38="",$B$5=0),0,$B$14*C38/$B$5) -> 0 | F38: =IF(OR($B$7=0,D38=""),0,$B$16*D38/$B$7) -> 0 | G38: =IF(OR(C38="",$B$5=0),0,$B$20*C38/$B$5) -> 0 | H38: =E38+F38+G38 -> 0 | K38: =IF('03_Investitori'!B38="","",'03_Investitori'!B38) | L38: =IF('03_Investitori'!H38="",0,'03_Investitori'!H38) -> 0 | M38: =IF('03_Investitori'!C38="",0,(DataOggi-'03_Investitori'!C38)/365.25) -> 0 | N38: =IF(L38=0,0,L38*((1+Hurdle)^M38-1)) -> 0
A39: =IF('03_Investitori'!B16="","",'03_Investitori'!B16) | B39: =IF('03_Investitori'!D16="","",'03_Investitori'!D16) | C39: =IF('03_Investitori'!H16="","",'03_Investitori'!H16) | D39: =N16 -> 0 | E39: =IF(OR(C39="",$B$5=0),0,$B$14*C39/$B$5) -> 0 | F39: =IF(OR($B$7=0,D39=""),0,$B$16*D39/$B$7) -> 0 | G39: =IF(OR(C39="",$B$5=0),0,$B$20*C39/$B$5) -> 0 | H39: =E39+F39+G39 -> 0 | K39: =IF('03_Investitori'!B39="","",'03_Investitori'!B39) | L39: =IF('03_Investitori'!H39="",0,'03_Investitori'!H39) -> 0 | M39: =IF('03_Investitori'!C39="",0,(DataOggi-'03_Investitori'!C39)/365.25) -> 0 | N39: =IF(L39=0,0,L39*((1+Hurdle)^M39-1)) -> 0
... A104: =IF('03_Investitori'!B81="","",'03_Investitori'!B81) | B104: =IF('03_Investitori'!D81="","",'03_Investitori'!D81) | C104: =IF('03_Investitori'!H81="","",'03_Investitori'!H81) | D104: =N81 -> 0 | E104: =IF(OR(C104="",$B$5=0),0,$B$14*C104/$B$5) -> 0 | F104: =IF(OR($B$7=0,D104=""),0,$B$16*D104/$B$7) -> 0 | G104: =IF(OR(C104="",$B$5=0),0,$B$20*C104/$B$5) -> 0 | H104: =E104+F104+G104 -> 0 | K104: =IF('03_Investitori'!B104="","",'03_Investitori'!B104) | L104: =IF('03_Investitori'!H104="",0,'03_Investitori'!H104) -> 0 | M104: =IF('03_Investitori'!C104="",0,(DataOggi-'03_Investitori'!C104)/365.25) -> 0 | N104: =IF(L104=0,0,L104*((1+Hurdle)^M104-1)) -> 0
A105: =IF('03_Investitori'!B82="","",'03_Investitori'!B82) | B105: =IF('03_Investitori'!D82="","",'03_Investitori'!D82) | C105: =IF('03_Investitori'!H82="","",'03_Investitori'!H82) | D105: =N82 -> 0 | E105: =IF(OR(C105="",$B$5=0),0,$B$14*C105/$B$5) -> 0 | F105: =IF(OR($B$7=0,D105=""),0,$B$16*D105/$B$7) -> 0 | G105: =IF(OR(C105="",$B$5=0),0,$B$20*C105/$B$5) -> 0 | H105: =E105+F105+G105 -> 0
A106: =IF('03_Investitori'!B83="","",'03_Investitori'!B83) | B106: =IF('03_Investitori'!D83="","",'03_Investitori'!D83) | C106: =IF('03_Investitori'!H83="","",'03_Investitori'!H83) | D106: =N83 -> 0 | E106: =IF(OR(C106="",$B$5=0),0,$B$14*C106/$B$5) -> 0 | F106: =IF(OR($B$7=0,D106=""),0,$B$16*D106/$B$7) -> 0 | G106: =IF(OR(C106="",$B$5=0),0,$B$20*C106/$B$5) -> 0 | H106: =E106+F106+G106 -> 0
A107: =IF('03_Investitori'!B84="","",'03_Investitori'!B84) | B107: =IF('03_Investitori'!D84="","",'03_Investitori'!D84) | C107: =IF('03_Investitori'!H84="","",'03_Investitori'!H84) | D107: =N84 -> 0 | E107: =IF(OR(C107="",$B$5=0),0,$B$14*C107/$B$5) -> 0 | F107: =IF(OR($B$7=0,D107=""),0,$B$16*D107/$B$7) -> 0 | G107: =IF(OR(C107="",$B$5=0),0,$B$20*C107/$B$5) -> 0 | H107: =E107+F107+G107 -> 0
A108: =IF('03_Investitori'!B85="","",'03_Investitori'!B85) | B108: =IF('03_Investitori'!D85="","",'03_Investitori'!D85) | C108: =IF('03_Investitori'!H85="","",'03_Investitori'!H85) | D108: =N85 -> 0 | E108: =IF(OR(C108="",$B$5=0),0,$B$14*C108/$B$5) -> 0 | F108: =IF(OR($B$7=0,D108=""),0,$B$16*D108/$B$7) -> 0 | G108: =IF(OR(C108="",$B$5=0),0,$B$20*C108/$B$5) -> 0 | H108: =E108+F108+G108 -> 0
A109: =IF('03_Investitori'!B86="","",'03_Investitori'!B86) | B109: =IF('03_Investitori'!D86="","",'03_Investitori'!D86) | C109: =IF('03_Investitori'!H86="","",'03_Investitori'!H86) | D109: =N86 -> 0 | E109: =IF(OR(C109="",$B$5=0),0,$B$14*C109/$B$5) -> 0 | F109: =IF(OR($B$7=0,D109=""),0,$B$16*D109/$B$7) -> 0 | G109: =IF(OR(C109="",$B$5=0),0,$B$20*C109/$B$5) -> 0 | H109: =E109+F109+G109 -> 0
A110: =IF('03_Investitori'!B87="","",'03_Investitori'!B87) | B110: =IF('03_Investitori'!D87="","",'03_Investitori'!D87) | C110: =IF('03_Investitori'!H87="","",'03_Investitori'!H87) | D110: =N87 -> 0 | E110: =IF(OR(C110="",$B$5=0),0,$B$14*C110/$B$5) -> 0 | F110: =IF(OR($B$7=0,D110=""),0,$B$16*D110/$B$7) -> 0 | G110: =IF(OR(C110="",$B$5=0),0,$B$20*C110/$B$5) -> 0 | H110: =E110+F110+G110 -> 0
A111: =IF('03_Investitori'!B88="","",'03_Investitori'!B88) | B111: =IF('03_Investitori'!D88="","",'03_Investitori'!D88) | C111: =IF('03_Investitori'!H88="","",'03_Investitori'!H88) | D111: =N88 -> 0 | E111: =IF(OR(C111="",$B$5=0),0,$B$14*C111/$B$5) -> 0 | F111: =IF(OR($B$7=0,D111=""),0,$B$16*D111/$B$7) -> 0 | G111: =IF(OR(C111="",$B$5=0),0,$B$20*C111/$B$5) -> 0 | H111: =E111+F111+G111 -> 0
A112: =IF('03_Investitori'!B89="","",'03_Investitori'!B89) | B112: =IF('03_Investitori'!D89="","",'03_Investitori'!D89) | C112: =IF('03_Investitori'!H89="","",'03_Investitori'!H89) | D112: =N89 -> 0 | E112: =IF(OR(C112="",$B$5=0),0,$B$14*C112/$B$5) -> 0 | F112: =IF(OR($B$7=0,D112=""),0,$B$16*D112/$B$7) -> 0 | G112: =IF(OR(C112="",$B$5=0),0,$B$20*C112/$B$5) -> 0 | H112: =E112+F112+G112 -> 0
A113: =IF('03_Investitori'!B90="","",'03_Investitori'!B90) | B113: =IF('03_Investitori'!D90="","",'03_Investitori'!D90) | C113: =IF('03_Investitori'!H90="","",'03_Investitori'!H90) | D113: =N90 -> 0 | E113: =IF(OR(C113="",$B$5=0),0,$B$14*C113/$B$5) -> 0 | F113: =IF(OR($B$7=0,D113=""),0,$B$16*D113/$B$7) -> 0 | G113: =IF(OR(C113="",$B$5=0),0,$B$20*C113/$B$5) -> 0 | H113: =E113+F113+G113 -> 0
A114: =IF('03_Investitori'!B91="","",'03_Investitori'!B91) | B114: =IF('03_Investitori'!D91="","",'03_Investitori'!D91) | C114: =IF('03_Investitori'!H91="","",'03_Investitori'!H91) | D114: =N91 -> 0 | E114: =IF(OR(C114="",$B$5=0),0,$B$14*C114/$B$5) -> 0 | F114: =IF(OR($B$7=0,D114=""),0,$B$16*D114/$B$7) -> 0 | G114: =IF(OR(C114="",$B$5=0),0,$B$20*C114/$B$5) -> 0 | H114: =E114+F114+G114 -> 0
A115: =IF('03_Investitori'!B92="","",'03_Investitori'!B92) | B115: =IF('03_Investitori'!D92="","",'03_Investitori'!D92) | C115: =IF('03_Investitori'!H92="","",'03_Investitori'!H92) | D115: =N92 -> 0 | E115: =IF(OR(C115="",$B$5=0),0,$B$14*C115/$B$5) -> 0 | F115: =IF(OR($B$7=0,D115=""),0,$B$16*D115/$B$7) -> 0 | G115: =IF(OR(C115="",$B$5=0),0,$B$20*C115/$B$5) -> 0 | H115: =E115+F115+G115 -> 0
A116: =IF('03_Investitori'!B93="","",'03_Investitori'!B93) | B116: =IF('03_Investitori'!D93="","",'03_Investitori'!D93) | C116: =IF('03_Investitori'!H93="","",'03_Investitori'!H93) | D116: =N93 -> 0 | E116: =IF(OR(C116="",$B$5=0),0,$B$14*C116/$B$5) -> 0 | F116: =IF(OR($B$7=0,D116=""),0,$B$16*D116/$B$7) -> 0 | G116: =IF(OR(C116="",$B$5=0),0,$B$20*C116/$B$5) -> 0 | H116: =E116+F116+G116 -> 0
... A127: =IF('03_Investitori'!B104="","",'03_Investitori'!B104) | B127: =IF('03_Investitori'!D104="","",'03_Investitori'!D104) | C127: =IF('03_Investitori'!H104="","",'03_Investitori'!H104) | D127: =N104 -> 0 | E127: =IF(OR(C127="",$B$5=0),0,$B$14*C127/$B$5) -> 0 | F127: =IF(OR($B$7=0,D127=""),0,$B$16*D127/$B$7) -> 0 | G127: =IF(OR(C127="",$B$5=0),0,$B$20*C127/$B$5) -> 0 | H127: =E127+F127+G127 -> 0

Sheet 99_Integrity
A1: Ariete Capital - Investment Tracker | Integrity Checks
A2: Controlli di integrita' automatici. OK = check passato, DIFF = scostamento da indagare.
A4: # | B4: Check | C4: Expected | D4: Actual | E4: Status
A5: 1 | B5: Waterfall total distribution = NAV corrente | C5: NAV_Curr | D5: ='13_Waterfall'!B22 -> 1971514.5 | E5: =IF(ABS('13_Waterfall'!B22-NAV_Curr)<0.01,"OK","DIFF: "&TEXT('13_Waterfall'!B22-NAV_Curr,"#,##0.00")) -> OK
A6: 2 | B6: Totale capitale Investitori = Capital_Tot | C6: Capital_Tot | D6: =SUM('03_Investitori'!$H$5:$H$104) -> 2000000 | E6: =IF(ABS(SUM('03_Investitori'!$H$5:$H$104)-Capital_Tot)<0.01,"OK","DIFF: "&TEXT(SUM('03_Investitori'!$H$5:$H$104)-Capital_Tot,"#,##0.00")) -> OK
A7: 3 | B7: MV Listed Spot (O60) > 0 | C7: > 0 | D7: ='09_Posizioni'!O60 -> 1069752.7 | E7: =IF('09_Posizioni'!O60>0,"OK","DIFF: MV Spot non positivo") -> OK
A8: 4 | B8: Listed_Tot_Cost (K60) > 0 | C8: > 0 | D8: =Listed_Tot_Cost -> 1084431.3 | E8: =IF(Listed_Tot_Cost>0,"OK","DIFF: cost negativo") -> OK
A9: 5 | B9: MV Spot >= Costo (K60) entro 30% in valore assoluto | C9: scostamento < 30% | D9: =IFERROR(ABS(MV_Listed_Tot-Listed_Tot_Cost)/Listed_Tot_Cost,1) -> 0.013535732 | E9: =IF(IFERROR(ABS(MV_Listed_Tot-Listed_Tot_Cost)/Listed_Tot_Cost,1)<0.3,"OK","DIFF: scostamento elevato") -> OK
A10: 6 | B10: ISIN VERIFY- placeholder in 04_Trades (deve essere riconciliato) | C10: 0 ISIN VERIFY- | D10: =COUNTIF('04_Trades'!$E$5:$E$1004,"VERIFY-*") -> 1 | E10: =IF(COUNTIF('04_Trades'!$E$5:$E$1004,"VERIFY-*")=0,"OK","DIFF: "&COUNTIF('04_Trades'!$E$5:$E$1004,"VERIFY-*")&" placeholder da risolvere") -> DIFF: 1 placeholder da risolvere
A11: 7 | B11: FX Rates 02_FX_Rates: Ultima Data Aggiornamento popolata | C11: tutte le righe popolate | D11: =COUNTA('02_FX_Rates'!$C$5:$C$10) -> 0 | E11: =IF(COUNTA('02_FX_Rates'!$C$5:$C$10)>=6,"OK","DIFF: date FX mancanti, "&(6-COUNTA('02_FX_Rates'!$C$5:$C$10))&" su 6") -> DIFF: date FX mancanti, 6 su 6
A12: 8 | B12: NAV_Curr ricalcolato = NAV ultimo mese popolato in 10_NAV_Mensile | C12: NAV_Curr | D12: =INDEX('10_NAV_Mensile'!$M$5:$M$124,COUNT('10_NAV_Mensile'!$B$5:$B$124)) -> 1993987.5 | E12: =IF(ABS(INDEX('10_NAV_Mensile'!$M$5:$M$124,COUNT('10_NAV_Mensile'!$B$5:$B$124))-NAV_Curr)<NAV_Curr*0.05,"OK","DIFF: scostamento >5% tra NAV mensile e NAV snapshot") -> OK
A13: 9 | B13: Units_Curr ricalcolato = SOMMA Quote in 03_Investitori | C13: Units_Curr | D13: =SUM('03_Investitori'!$J$5:$J$104) -> 2000000 | E13: =IF(ABS(SUM('03_Investitori'!$J$5:$J$104)-Units_Curr)<0.01,"OK","DIFF: "&TEXT(SUM('03_Investitori'!$J$5:$J$104)-Units_Curr,"#,##0.00")) -> OK
A14: 10 | B14: CAGR (B26) calcolato (non-zero in produzione) | C14: <> 0 quando NAV != Capital | D14: ='11_Performance'!B26 -> 0 | E14: =IF(AND('11_Performance'!B26=0,ABS(NAV_Curr-Capital_Tot)>1),"DIFF: CAGR=0 sospetto","OK") -> DIFF: CAGR=0 sospetto
A16: Generato dall'audit 2026-05-14. Aggiungere check secondo le necessita' future.
